Workbook

Sheet Summary of Results
B2: Mean AUPRC difference (%) between CLT‑TAB and competing models over 7 datasets | H2: Random | L2: =(L11+L17+L23+L29+L35+L41+L47)/7*100 -> 5431.4577
H3: LR | L3: =(L12+L18+L24+L30+L36+L42+L48)/7*100 -> 19.093696
H4: SCARF | L4: =(L14+L20+L26+L32+L38+L44+L50)/7*100 -> 8682.8174
H5: FT-transformer | L5: =(L15+L21+L27+L33+L39+L45+L51)/7*100 -> 355.01595
H6: CatBoost | L6: =(L16+L22+L28+L34+L40+L46+L52)/7*100 -> 5.047012
I7: the test set has the same size as the finetune set
B9: Datasets | F9: Unlabeled Pretrain size | G9: Finetune with labels (includes 100 anomalies) | I9: AUPRC (10 seed) | L9: difference, %
B10: name | C10: size | D10: type | E10: class balance | G10: size | H10: model | I10: mean | J10: σ | L10: AUPRC
B11: Bank Account Fraud (BAF) | C11: 1000000 | D11: Mixed | E11: 89.7 : 1 | F11: — | G11: 9066 | H11: Random | I11: =BAF!C5 -> 0.011 | J11: 0 | L11: =$I$13/I11-1 -> 11.290909
F12: — | H12: LR | I12: =BAF!D9 -> 0.08799 | J12: =BAF!E9 -> 0.0013087781 | L12: =$I$13/I12-1 -> 0.53653824
F13: 100000 | H13: CLT-TAB | I13: =BAF!D10 -> 0.1352 | J13: =BAF!E10 -> 0.013713862 | L13: =$I$13/I13-1 -> 0
H14: SCARF | I14: =BAF!D13 -> 0.00975 | J14: =BAF!E13 -> 0.00054267854 | L14: =$I$13/I14-1 -> 12.866667
F15: — | H15: FT-transformer | I15: =BAF!D11 -> 0.07221 | J15: =BAF!E11 -> 0.028507208 | L15: =$I$13/I15-1 -> 0.87231685
F16: — | H16: CatBoost | I16: =BAF!D12 -> 0.10124 | J16: =BAF!E12 -> 0.012253914 | L16: =$I$13/I16-1 -> 0.33544054
B17: Credit Card Fraud Detection | C17: 283726 | D17: numerical | E17: 577,8 : 1 | F17: — | G17: 59984 | H17: Random | I17: ='Fraud Detection'!C5 -> 0.0017 | J17: 0 | L17: =$I$19/I17-1 -> 363.62941
F18: — | H18: LR | I18: ='Fraud Detection'!D9 -> 0.6618 | J18: ='Fraud Detection'!E9 -> 1.110223e-16 | L18: =$I$19/I18-1 -> -0.06335751
F19: 163758 | H19: CLT-TAB | I19: ='Fraud Detection'!D10 -> 0.61987 | J19: ='Fraud Detection'!E10 -> 0.058983863 | L19: =$I$19/I19-1 -> 0
H20: SCARF | I20: ='Fraud Detection'!D13 -> 0.00105 | J20: ='Fraud Detection'!E13 -> 0.00016278821 | L20: =$I$19/I20-1 -> 589.35238
F21: — | H21: FT-transformer | I21: ='Fraud Detection'!D11 -> 0.02585 | J21: ='Fraud Detection'!E11 -> 0.035236891 | L21: =$I$19/I21-1 -> 22.979497
F22: — | H22: CatBoost | I22: ='Fraud Detection'!D12 -> 0.70481 | J22: ='Fraud Detection'!E12 -> 0.040313086 | L22: =$I$19/I22-1 -> -0.12051475
B23: Road-safety | C23: 111419 | D23: Mixed | E23: 1.0 : 1 | F23: — | G23: 200 | H23: Random | I23: =Road_safety!C5 -> 0.5 | J23: 0 | L23: =$I$25/I23-1 -> 0.41924
F24: — | H24: LR | I24: =Road_safety!D9 -> 0.65907 | J24: =Road_safety!E9 -> 0.0027996607 | L24: =$I$25/I24-1 -> 0.076698985
F25: 111019 | H25: CLT-TAB | I25: =Road_safety!D10 -> 0.70962 | J25: =Road_safety!E10 -> 0.015283965 | L25: =$I$25/I25-1 -> 0
H26: SCARF | I26: =Road_safety!D13 -> 0.53082 | J26: =Road_safety!E13 -> 0.018638069 | L26: =$I$25/I26-1 -> 0.33683735
F27: — | H27: FT-transformer | I27: =Road_safety!D11 -> 0.67523 | J27: =Road_safety!E11 -> 0.033669305 | L27: =$I$25/I27-1 -> 0.050930794
F28: — | H28: CatBoost | I28: =Road_safety!D12 -> 0.69933 | J28: =Road_safety!E12 -> 0.011061017 | L28: =$I$25/I28-1 -> 0.014714083
B29: NIDS Network Benchmark | C29: 72000 | D29: Mixed | E29: 1.1:1 | F29: — | G29: 208 | H29: Random | I29: =NIDS!C5 -> 0.4808 | J29: 0 | L29: =$I$31/I29-1 -> 1.0798669
F30: — | H30: LR | I30: =NIDS!D9 -> 0.97321 | J30: =NIDS!E9 -> 0.0027620463 | L30: =$I$31/I30-1 -> 0.027527461
F31: 0 | H31: CLT-TAB | I31: =NIDS!D10 -> 1 | J31: =NIDS!E10 -> 0 | L31: =$I$31/I31-1 -> 0
H32: SCARF | I32: =NIDS!D13 -> 0.49529 | J32: =NIDS!E13 -> 0.069659665 | L32: =$I$31/I32-1 -> 1.0190192
F33: — | H33: FT-transformer | I33: =NIDS!D11 -> 0.9977 | J33: =NIDS!E11 -> 0.001150652 | L33: =$I$31/I33-1 -> 0.0023053022
F34: — | H34: CatBoost | I34: =NIDS!D12 -> 0.99863 | J34: =NIDS!E12 -> 0.0018401359 | L34: =$I$31/I34-1 -> 0.0013718795
B35: Epsilon-30 (we used the first 30 features) | C35: 50 000 (случайная выборка из train) | D35: numerical | E35: 1.0 : 1 | F35: — | G35: 200 | H35: Random | I35: =Epsilon30!C5 -> 0.5 | J35: 0 | L35: =$I$37/I35-1 -> 0.1466
F36: — | H36: LR | I36: =Epsilon30!D9 -> 0.55167 | J36: =Epsilon30!E9 -> 0.0032177787 | L36: =$I$37/I36-1 -> 0.039208222
F37: 49600 | H37: CLT-TAB | I37: =Epsilon30!D10 -> 0.5733 | J37: =Epsilon30!E10 -> 0.018746733 | L37: =$I$37/I37-1 -> 0
H38: SCARF | I38: =Epsilon30!D13 -> 0.53467 | J38: =Epsilon30!E13 -> 0.015332583 | L38: =$I$37/I38-1 -> 0.072250173
F39: — | H39: FT-transformer | I39: =Epsilon30!D11 -> 0.54593 | J39: =Epsilon30!E11 -> 0.025933031 | L39: =$I$37/I39-1 -> 0.050134633
F40: — | H40: CatBoost | I40: =Epsilon30!D12 -> 0.51491 | J40: =Epsilon30!E12 -> 0.027687522 | L40: =$I$37/I40-1 -> 0.11339846
B41: Adult Census Income | C41: 48785 | D41: Mixed | E41: 3.2 : 1 | F41: — | G41: 622 | H41: Random | I41: =Adult!C5 -> 0.1608 | J41: 0 | L41: =$I$43/I41-1 -> 2.3002488
F42: — | H42: LR | I42: =Adult!D9 -> 0.41049 | J42: =Adult!E9 -> 0.0084127819 | L42: =$I$43/I42-1 -> 0.29279641
F43: 47541 | H43: CLT-TAB | I43: =Adult!D10 -> 0.53068 | J43: =Adult!E10 -> 0.017105835 | L43: =$I$43/I43-1 -> 0
H44: SCARF | I44: =Adult!D13 -> 0.14564 | J44: =Adult!E13 -> 0.011757398 | L44: =$I$43/I44-1 -> 2.6437792
F45: — | H45: FT-transformer | I45: =Adult!D11 -> 0.37263 | J45: =Adult!E11 -> 0.016933166 | L45: =$I$43/I45-1 -> 0.42414728
F46: — | H46: CatBoost | I46: =Adult!D12 -> 0.50624 | J46: =Adult!E12 -> 0.019672885 | L46: =$I$43/I46-1 -> 0.048277497
B47: UCI Credit Card | C47: 29944 | D47: Mixed | E47: 3.5 : 1 | F47: — | G47: 452 | H47: Random | I47: ='Card Default'!C5 -> 0.2212 | J47: 0 | L47: =$I$49/I47-1 -> 1.3357595
F48: — | H48: LR | I48: ='Card Default'!D9 -> 0.36203 | J48: ='Card Default'!E9 -> 0.012039273 | L48: =$I$49/I48-1 -> 0.42714692
F49: 29040 | H49: CLT-TAB | I49: ='Card Default'!D10 -> 0.51667 | J49: ='Card Default'!E10 -> 0.027509128 | L49: =$I$49/I49-1 -> 0
H50: SCARF | I50: ='Card Default'!D13 -> 0.20615 | J50: ='Card Default'!E13 -> 0.010437936 | L50: =$I$49/I50-1 -> 1.5062818
F51: — | H51: FT-transformer | I51: ='Card Default'!D11 -> 0.35105 | J51: ='Card Default'!E11 -> 0.01900396 | L51: =$I$49/I51-1 -> 0.47178465
F52: — | H52: CatBoost | I52: ='Card Default'!D12 -> 0.53786 | J52: ='Card Default'!E12 -> 0.031181026 | L52: =$I$49/I52-1 -> -0.039396869

Sheet Ablations 
C1: CLT-TAB | E1: AUPRC (10 seed)
B2: Ablations | C2: CATA | D2: SQP | E2: Bank Account Fraud (BAF) | F2: Credit Card Fraud Detection | G2: Road-safety | H2: NIDS Network Benchmark | I2: Epsilon-30 | J2: Adult Census Income | K2: UCI Credit Card
B3: Augmentation with importance weighting and stochastic pooling | C3: yes | D3: yes | E3: =BAF!D10 -> 0.1352 | F3: ='Fraud Detection'!D10 -> 0.61987 | G3: =Road_safety!D10 -> 0.70962 | H3: =NIDS!D10 -> 1 | I3: =Epsilon30!D10 -> 0.5733 | J3: =Adult!D10 -> 0.53068 | K3: ='Card Default'!D10 -> 0.51667
B4: Augmentation without importance weighting and stochastic pooling | C4: no | D4: yes | E4: =BAF!D18 -> 0.13191 | F4: ='Fraud Detection'!D18 -> 0.5962 | G4: =Road_safety!D18 -> 0.69868 | H4: =NIDS!D18 -> 1 | I4: =Epsilon30!D18 -> 0.57771 | J4: =Adult!D18 -> 0.53241 | K4: ='Card Default'!D18 -> 0.51004
B5: Augmentation with importance weighting and deterministic pooling | C5: yes | D5: no | E5: =BAF!D26 -> 0.14488 | F5: ='Fraud Detection'!D26 -> 0.59011 | G5: =Road_safety!D26 -> 0.70235 | H5: =NIDS!D26 -> 1 | I5: =Epsilon30!D26 -> 0.56395 | J5: =Adult!D26 -> 0.53823 | K5: ='Card Default'!D26 -> 0.50336
B6: Augmentation without importance weighting and deterministic pooling | C6: no | D6: no | E6: =BAF!D34 -> 0.14443 | F6: ='Fraud Detection'!D34 -> 0.57031 | G6: =Road_safety!D34 -> 0.70989 | H6: =NIDS!D34 -> 1 | I6: =Epsilon30!D34 -> 0.55798 | J6: =Adult!D34 -> 0.52528 | K6: ='Card Default'!D34 -> 0.50503
C7: Nominal difference in AUPRC values
B8: Green = performance worsened without tuning the component. Red = performance improved without tuning the component. Findings: - CATA is beneficial (no improvement without it). - Without SQP, 2/7 datasets improved → default settings are not universally optimal. Without both, 1/7 datasets improved (the same one where stochastic pooling was suboptimal). Conclusion: CATA yields stable results, while SQP may deteriorate performance and requires tuning for the dataset. | C8: no | D8: yes | E8: =E4-E$3 -> -0.00329 | F8: =F4-F$3 -> -0.02367 | G8: =G4-G$3 -> -0.01094 | H8: =H4-H$3 -> 0 | I8: =I4-I$3 -> 0.00441 | J8: =J4-J$3 -> 0.00173 | K8: =K4-K$3 -> -0.00663
C9: yes | D9: no | E9: =E5-E$3 -> 0.00968 | F9: =F5-F$3 -> -0.02976 | G9: =G5-G$3 -> -0.00727 | H9: =H5-H$3 -> 0 | I9: =I5-I$3 -> -0.00935 | J9: =J5-J$3 -> 0.00755 | K9: =K5-K$3 -> -0.01331
C10: no | D10: no | E10: =E6-E$3 -> 0.00923 | F10: =F6-F$3 -> -0.04956 | G10: =G6-G$3 -> 0.00027 | H10: =H6-H$3 -> 0 | I10: =I6-I$3 -> -0.01532 | J10: =J6-J$3 -> -0.0054 | K10: =K6-K$3 -> -0.01164
C11: Relative difference in AUPRC values (differences greater than 1% are marked)
C12: no | D12: yes | E12: =E4/E$3-1 -> -0.02433432 | F12: =F4/F$3-1 -> -0.038185426 | G12: =G4/G$3-1 -> -0.015416702 | H12: =H4/H$3-1 -> 0 | I12: =I4/I$3-1 -> 0.0076923077 | J12: =J4/J$3-1 -> 0.0032599683 | K12: =K4/K$3-1 -> -0.012832175
C13: yes | D13: no | E13: =E5/E$3-1 -> 0.071597633 | F13: =F5/F$3-1 -> -0.048010067 | G13: =G5/G$3-1 -> -0.01024492 | H13: =H5/H$3-1 -> 0 | I13: =I5/I$3-1 -> -0.016309088 | J13: =J5/J$3-1 -> 0.014227029 | K13: =K5/K$3-1 -> -0.025761124
C14: no | D14: no | E14: =E6/E$3-1 -> 0.068269231 | F14: =F6/F$3-1 -> -0.079952248 | G14: =G6/G$3-1 -> 0.00038048533 | H14: =H6/H$3-1 -> 0 | I14: =I6/I$3-1 -> -0.026722484 | J14: =J6/J$3-1 -> -0.010175624 | K14: =K6/K$3-1 -> -0.022528887

Sheet >>>
A1: ,

Sheet BAF
B1: Overview
B2: The Bank Account Fraud (BAF) dataset is a synthetic yet realistic tabular dataset introduced at NeurIPS 2022 for evaluating machine learning methods in fraud detection scenarios . It was generated by applying state-of-the-art tabular data generation techniques (CTGAN) to an anonymized, real-world bank account opening fraud detection dataset.
B3: We used the Bank Account Fraud (BAF) dataset, which contains 1 000 000 instances with a 1.1% anomaly rate. It comprises 18 numerical and 11 categorical features. The 'month' feature was removed prior to experimentation. The data were used after preprocessing (missing values, duplicates, and constant features were removed). F1 and Recall scores were obtained with a threshold of 0.5. We used 9 066 instances for finetuning, of which 100 were anomalies, and the same number (9 066 instances, 100 anomalies) for testing.
B5: Random AUPRC | C5: 0.011 | N5: Seed
G6: For reference | N6: 42 | R6: 43 | V6: 44 | Z6: 45 | AD6: 46 | AH6: 47 | AL6: 48 | AP6: 49 | AT6: 50 | AX6: 51
C7: effect, % | D7: AUPRC | G7: Recall | J7: F1 | N7: AUPRC | O7: For reference | R7: AUPRC | S7: For reference | V7: AUPRC | W7: For reference | Z7: AUPRC | AA7: For reference | AD7: AUPRC | AE7: For reference | AH7: AUPRC | AI7: For reference | AL7: AUPRC | AM7: For reference | AP7: AUPRC | AQ7: For reference | AT7: AUPRC | AU7: For reference | AX7: AUPRC | AY7: For reference
D8: mean | E8: σ | F8: CV | G8: mean | H8: σ | I8: CV | J8: mean | K8: σ | L8: CV | O8: Recall | P8: F1 | S8: Recall | T8: F1 | W8: Recall | X8: F1 | AA8: Recall | AB8: F1 | AE8: Recall | AF8: F1 | AI8: Recall | AJ8: F1 | AM8: Recall | AN8: F1 | AQ8: Recall | AR8: F1 | AU8: Recall | AV8: F1 | AY8: Recall | AZ8: F1
B9: LR | C9: =D10/D9-1 -> 0.53653824 | D9: =(N9+R9+V9+Z9+AD9+AH9+AL9+AP9+AT9+AX9)/10 -> 0.08799 | E9: =SQRT(((N9-D9)^2+(R9-D9)^2+(V9-D9)^2+(Z9-D9)^2+(AD9-D9)^2+(AH9-D9)^2+(AL9-D9)^2+(AP9-D9)^2+(AT9-D9)^2+(AX9-D9)^2)/10) -> 0.0013087781 | F9: =E9/D9 -> 0.014874168 | G9: =(O9+S9+W9+AA9+AE9+AI9+AM9+AQ9+AU9+AY9)/10 -> 0.795 | H9: =SQRT(((O9-G9)^2+(S9-G9)^2+(W9-G9)^2+(AA9-G9)^2+(AE9-G9)^2+(AI9-G9)^2+(AM9-G9)^2+(AQ9-G9)^2+(AU9-G9)^2+(AY9-G9)^2)/10) -> 0.0092195445 | I9: =H9/G9 -> 0.011596911 | J9: =(P9+T9+X9+AB9+AF9+AJ9+AN9+AR9+AV9+AZ9)/10 -> 0.07204 | K9: =SQRT(((P9-J9)^2+(T9-J9)^2+(X9-J9)^2+(AB9-J9)^2+(AF9-J9)^2+(AJ9-J9)^2+(AN9-J9)^2+(AR9-J9)^2+(AV9-J9)^2+(AZ9-J9)^2)/10) -> 0.00081264999 | L9: =K9/J9 -> 0.011280538 | N9: 0.0869 | O9: 0.8 | P9: 0.0726 | R9: 0.0868 | S9: 0.8 | T9: 0.0725 | V9: 0.0869 | W9: 0.8 | X9: 0.0726 | Z9: 0.0902 | AA9: 0.77 | AB9: 0.07 | AD9: 0.0897 | AE9: 0.79 | AF9: 0.0714 | AH9: 0.0868 | AI9: 0.8 | AJ9: 0.0725 | AL9: 0.0869 | AM9: 0.8 | AN9: 0.0726 | AP9: 0.088 | AQ9: 0.8 | AR9: 0.0724 | AT9: 0.0897 | AU9: 0.79 | AV9: 0.0714 | AX9: 0.088 | AY9: 0.8 | AZ9: 0.0724
B10: CLT-TAB | D10: =(N10+R10+V10+Z10+AD10+AH10+AL10+AP10+AT10+AX10)/10 -> 0.1352 | E10: =SQRT(((N10-D10)^2+(R10-D10)^2+(V10-D10)^2+(Z10-D10)^2+(AD10-D10)^2+(AH10-D10)^2+(AL10-D10)^2+(AP10-D10)^2+(AT10-D10)^2+(AX10-D10)^2)/10) -> 0.013713862 | F10: =E10/D10 -> 0.10143389 | G10: =(O10+S10+W10+AA10+AE10+AI10+AM10+AQ10+AU10+AY10)/10 -> 0.766 | H10: =SQRT(((O10-G10)^2+(S10-G10)^2+(W10-G10)^2+(AA10-G10)^2+(AE10-G10)^2+(AI10-G10)^2+(AM10-G10)^2+(AQ10-G10)^2+(AU10-G10)^2+(AY10-G10)^2)/10) -> 0.026907248 | I10: =H10/G10 -> 0.035126956 | J10: =(P10+T10+X10+AB10+AF10+AJ10+AN10+AR10+AV10+AZ10)/10 -> 0.08482 | K10: =SQRT(((P10-J10)^2+(T10-J10)^2+(X10-J10)^2+(AB10-J10)^2+(AF10-J10)^2+(AJ10-J10)^2+(AN10-J10)^2+(AR10-J10)^2+(AV10-J10)^2+(AZ10-J10)^2)/10) -> 0.0023055585 | L10: =K10/J10 -> 0.027181779 | N10: 0.146 | O10: 0.75 | P10: 0.0844 | R10: 0.1292 | S10: 0.76 | T10: 0.0819 | V10: 0.1237 | W10: 0.79 | X10: 0.0879 | Z10: 0.1427 | AA10: 0.8 | AB10: 0.0844 | AD10: 0.1605 | AE10: 0.79 | AF10: 0.0854 | AH10: 0.1465 | AI10: 0.78 | AJ10: 0.0869 | AL10: 0.1167 | AM10: 0.72 | AN10: 0.0834 | AP10: 0.1156 | AQ10: 0.77 | AR10: 0.086 | AT10: 0.1403 | AU10: 0.78 | AV10: 0.0875 | AX10: 0.1308 | AY10: 0.72 | AZ10: 0.0804
B11: FT-transformer | C11: =D10/D11-1 -> 0.87231685 | D11: =(N11+R11+V11+Z11+AD11+AH11+AL11+AP11+AT11+AX11)/10 -> 0.07221 | E11: =SQRT(((N11-D11)^2+(R11-D11)^2+(V11-D11)^2+(Z11-D11)^2+(AD11-D11)^2+(AH11-D11)^2+(AL11-D11)^2+(AP11-D11)^2+(AT11-D11)^2+(AX11-D11)^2)/10) -> 0.028507208 | F11: =E11/D11 -> 0.394782 | G11: =(O11+S11+W11+AA11+AE11+AI11+AM11+AQ11+AU11+AY11)/10 -> 0.326 | H11: =SQRT(((O11-G11)^2+(S11-G11)^2+(W11-G11)^2+(AA11-G11)^2+(AE11-G11)^2+(AI11-G11)^2+(AM11-G11)^2+(AQ11-G11)^2+(AU11-G11)^2+(AY11-G11)^2)/10) -> 0.36584696 | I11: =H11/G11 -> 1.1222299 | J11: =(P11+T11+X11+AB11+AF11+AJ11+AN11+AR11+AV11+AZ11)/10 -> 0.06797 | K11: =SQRT(((P11-J11)^2+(T11-J11)^2+(X11-J11)^2+(AB11-J11)^2+(AF11-J11)^2+(AJ11-J11)^2+(AN11-J11)^2+(AR11-J11)^2+(AV11-J11)^2+(AZ11-J11)^2)/10) -> 0.061533926 | L11: =K11/J11 -> 0.90531008 | N11: 0.102 | O11: 1 | P11: 0.0218 | R11: 0.1282 | S11: 1 | T11: 0.0218 | V11: 0.0669 | W11: 0 | X11: 0 | Z11: 0.0739 | AA11: 0.43 | AB11: 0.1004 | AD11: 0.0688 | AE11: 0 | AF11: 0 | AH11: 0.0864 | AI11: 0.12 | AJ11: 0.1558 | AL11: 0.0597 | AM11: 0.11 | AN11: 0.1058 | AP11: 0.0624 | AQ11: 0.23 | AR11: 0.1373 | AT11: 0.0133 | AU11: 0 | AV11: 0 | AX11: 0.0605 | AY11: 0.37 | AZ11: 0.1368
B12: CatBoost | C12: =D10/D12-1 -> 0.33544054 | D12: =(N12+R12+V12+Z12+AD12+AH12+AL12+AP12+AT12+AX12)/10 -> 0.10124 | E12: =SQRT(((N12-D12)^2+(R12-D12)^2+(V12-D12)^2+(Z12-D12)^2+(AD12-D12)^2+(AH12-D12)^2+(AL12-D12)^2+(AP12-D12)^2+(AT12-D12)^2+(AX12-D12)^2)/10) -> 0.012253914 | F12: =E12/D12 -> 0.12103826 | G12: =(O12+S12+W12+AA12+AE12+AI12+AM12+AQ12+AU12+AY12)/10 -> 0.463 | H12: =SQRT(((O12-G12)^2+(S12-G12)^2+(W12-G12)^2+(AA12-G12)^2+(AE12-G12)^2+(AI12-G12)^2+(AM12-G12)^2+(AQ12-G12)^2+(AU12-G12)^2+(AY12-G12)^2)/10) -> 0.15244999 | I12: =H12/G12 -> 0.32926564 | J12: =(P12+T12+X12+AB12+AF12+AJ12+AN12+AR12+AV12+AZ12)/10 -> 0.12503 | K12: =SQRT(((P12-J12)^2+(T12-J12)^2+(X12-J12)^2+(AB12-J12)^2+(AF12-J12)^2+(AJ12-J12)^2+(AN12-J12)^2+(AR12-J12)^2+(AV12-J12)^2+(AZ12-J12)^2)/10) -> 0.015465578 | L12: =K12/J12 -> 0.12369494 | N12: 0.0949 | O12: 0.56 | P12: 0.1142 | R12: 0.1083 | S12: 0.41 | T12: 0.1297 | V12: 0.1179 | W12: 0.61 | X12: 0.1064 | Z12: 0.094 | AA12: 0.47 | AB12: 0.1269 | AD12: 0.0946 | AE12: 0.31 | AF12: 0.1435 | AH12: 0.1171 | AI12: 0.57 | AJ12: 0.1194 | AL12: 0.0822 | AM12: 0.25 | AN12: 0.1506 | AP12: 0.0844 | AQ12: 0.21 | AR12: 0.1386 | AT12: 0.1082 | AU12: 0.57 | AV12: 0.1221 | AX12: 0.1108 | AY12: 0.67 | AZ12: 0.0989
B13: SCARF | C13: =D10/D13-1 -> 12.866667 | D13: =(N13+R13+V13+Z13+AD13+AH13+AL13+AP13+AT13+AX13)/10 -> 0.00975 | E13: =SQRT(((N13-D13)^2+(R13-D13)^2+(V13-D13)^2+(Z13-D13)^2+(AD13-D13)^2+(AH13-D13)^2+(AL13-D13)^2+(AP13-D13)^2+(AT13-D13)^2+(AX13-D13)^2)/10) -> 0.00054267854 | F13: =E13/D13 -> 0.055659338 | G13: =(O13+S13+W13+AA13+AE13+AI13+AM13+AQ13+AU13+AY13)/10 -> 0.299 | H13: =SQRT(((O13-G13)^2+(S13-G13)^2+(W13-G13)^2+(AA13-G13)^2+(AE13-G13)^2+(AI13-G13)^2+(AM13-G13)^2+(AQ13-G13)^2+(AU13-G13)^2+(AY13-G13)^2)/10) -> 0.056824291 | I13: =H13/G13 -> 0.19004779 | J13: =(P13+T13+X13+AB13+AF13+AJ13+AN13+AR13+AV13+AZ13)/10 -> 0.01673 | K13: =SQRT(((P13-J13)^2+(T13-J13)^2+(X13-J13)^2+(AB13-J13)^2+(AF13-J13)^2+(AJ13-J13)^2+(AN13-J13)^2+(AR13-J13)^2+(AV13-J13)^2+(AZ13-J13)^2)/10) -> 0.002446242 | L13: =K13/J13 -> 0.14621889 | N13: 0.0101 | O13: 0.43 | P13: 0.0201 | R13: 0.0091 | S13: 0.25 | T13: 0.0139 | V13: 0.0095 | W13: 0.29 | X13: 0.017 | Z13: 0.0101 | AA13: 0.35 | AB13: 0.0205 | AD13: 0.0101 | AE13: 0.31 | AF13: 0.0179 | AH13: 0.0098 | AI13: 0.25 | AJ13: 0.0152 | AL13: 0.0099 | AM13: 0.32 | AN13: 0.0174 | AP13: 0.0095 | AQ13: 0.27 | AR13: 0.015 | AT13: 0.0087 | AU13: 0.22 | AV13: 0.0125 | AX13: 0.0107 | AY13: 0.3 | AZ13: 0.0178
C15: effect, % | D15: AUPRC | G15: Recall | J15: F1 | N15: AUPRC | O15: For reference | R15: AUPRC | S15: For reference | V15: AUPRC | W15: For reference | Z15: AUPRC | AA15: For reference | AD15: AUPRC | AE15: For reference | AH15: AUPRC | AI15: For reference | AL15: AUPRC | AM15: For reference | AP15: AUPRC | AQ15: For reference | AT15: AUPRC | AU15: For reference | AX15: AUPRC | AY15: For reference
D16: mean | E16: σ | F16: CV | G16: mean | H16: σ | I16: CV | J16: mean | K16: σ | L16: CV | O16: Recall | P16: F1 | S16: Recall | T16: F1 | W16: Recall | X16: F1 | AA16: Recall | AB16: F1 | AE16: Recall | AF16: F1 | AI16: Recall | AJ16: F1 | AM16: Recall | AN16: F1 | AQ16: Recall | AR16: F1 | AU16: Recall | AV16: F1 | AY16: Recall | AZ16: F1
B17: LR | C17: =D18/D17-1 -> 0.49914763 | D17: =(N17+R17+V17+Z17+AD17+AH17+AL17+AP17+AT17+AX17)/10 -> 0.08799 | E17: =SQRT(((N17-D17)^2+(R17-D17)^2+(V17-D17)^2+(Z17-D17)^2+(AD17-D17)^2+(AH17-D17)^2+(AL17-D17)^2+(AP17-D17)^2+(AT17-D17)^2+(AX17-D17)^2)/10) -> 0.0013087781 | F17: =E17/D17 -> 0.014874168 | G17: =(O17+S17+W17+AA17+AE17+AI17+AM17+AQ17+AU17+AY17)/10 -> 0.795 | H17: =SQRT(((O17-G17)^2+(S17-G17)^2+(W17-G17)^2+(AA17-G17)^2+(AE17-G17)^2+(AI17-G17)^2+(AM17-G17)^2+(AQ17-G17)^2+(AU17-G17)^2+(AY17-G17)^2)/10) -> 0.0092195445 | I17: =H17/G17 -> 0.011596911 | J17: =(P17+T17+X17+AB17+AF17+AJ17+AN17+AR17+AV17+AZ17)/10 -> 0.07204 | K17: =SQRT(((P17-J17)^2+(T17-J17)^2+(X17-J17)^2+(AB17-J17)^2+(AF17-J17)^2+(AJ17-J17)^2+(AN17-J17)^2+(AR17-J17)^2+(AV17-J17)^2+(AZ17-J17)^2)/10) -> 0.00081264999 | L17: =K17/J17 -> 0.011280538 | N17: 0.0869 | O17: 0.8 | P17: 0.0726 | R17: 0.0868 | S17: 0.8 | T17: 0.0725 | V17: 0.0869 | W17: 0.8 | X17: 0.0726 | Z17: 0.0902 | AA17: 0.77 | AB17: 0.07 | AD17: 0.0897 | AE17: 0.79 | AF17: 0.0714 | AH17: 0.0868 | AI17: 0.8 | AJ17: 0.0725 | AL17: 0.0869 | AM17: 0.8 | AN17: 0.0726 | AP17: 0.088 | AQ17: 0.8 | AR17: 0.0724 | AT17: 0.0897 | AU17: 0.79 | AV17: 0.0714 | AX17: 0.088 | AY17: 0.8 | AZ17: 0.0724
B18: CLT-TAB without CATA | D18: =(N18+R18+V18+Z18+AD18+AH18+AL18+AP18+AT18+AX18)/10 -> 0.13191 | E18: =SQRT(((N18-D18)^2+(R18-D18)^2+(V18-D18)^2+(Z18-D18)^2+(AD18-D18)^2+(AH18-D18)^2+(AL18-D18)^2+(AP18-D18)^2+(AT18-D18)^2+(AX18-D18)^2)/10) -> 0.014124266 | F18: =E18/D18 -> 0.10707502 | G18: =(O18+S18+W18+AA18+AE18+AI18+AM18+AQ18+AU18+AY18)/10 -> 0.775 | H18: =SQRT(((O18-G18)^2+(S18-G18)^2+(W18-G18)^2+(AA18-G18)^2+(AE18-G18)^2+(AI18-G18)^2+(AM18-G18)^2+(AQ18-G18)^2+(AU18-G18)^2+(AY18-G18)^2)/10) -> 0.020124612 | I18: =H18/G18 -> 0.025967241 | J18: =(P18+T18+X18+AB18+AF18+AJ18+AN18+AR18+AV18+AZ18)/10 -> 0.08359 | K18: =SQRT(((P18-J18)^2+(T18-J18)^2+(X18-J18)^2+(AB18-J18)^2+(AF18-J18)^2+(AJ18-J18)^2+(AN18-J18)^2+(AR18-J18)^2+(AV18-J18)^2+(AZ18-J18)^2)/10) -> 0.002266473 | L18: =K18/J18 -> 0.027114165 | N18: 0.1331 | O18: 0.79 | P18: 0.08 | R18: 0.1415 | S18: 0.79 | T18: 0.0843 | V18: 0.1191 | W18: 0.79 | X18: 0.0876 | Z18: 0.1339 | AA18: 0.77 | AB18: 0.0831 | AD18: 0.1488 | AE18: 0.78 | AF18: 0.0857 | AH18: 0.1221 | AI18: 0.76 | AJ18: 0.0849 | AL18: 0.1436 | AM18: 0.74 | AN18: 0.0806 | AP18: 0.1411 | AQ18: 0.81 | AR18: 0.0849 | AT18: 0.0987 | AU18: 0.75 | AV18: 0.0834 | AX18: 0.1372 | AY18: 0.77 | AZ18: 0.0814
B19: FT-transformer | C19: =D18/D19-1 -> 0.8267553 | D19: =(N19+R19+V19+Z19+AD19+AH19+AL19+AP19+AT19+AX19)/10 -> 0.07221 | E19: =SQRT(((N19-D19)^2+(R19-D19)^2+(V19-D19)^2+(Z19-D19)^2+(AD19-D19)^2+(AH19-D19)^2+(AL19-D19)^2+(AP19-D19)^2+(AT19-D19)^2+(AX19-D19)^2)/10) -> 0.028507208 | F19: =E19/D19 -> 0.394782 | G19: =(O19+S19+W19+AA19+AE19+AI19+AM19+AQ19+AU19+AY19)/10 -> 0.326 | H19: =SQRT(((O19-G19)^2+(S19-G19)^2+(W19-G19)^2+(AA19-G19)^2+(AE19-G19)^2+(AI19-G19)^2+(AM19-G19)^2+(AQ19-G19)^2+(AU19-G19)^2+(AY19-G19)^2)/10) -> 0.36584696 | I19: =H19/G19 -> 1.1222299 | J19: =(P19+T19+X19+AB19+AF19+AJ19+AN19+AR19+AV19+AZ19)/10 -> 0.06797 | K19: =SQRT(((P19-J19)^2+(T19-J19)^2+(X19-J19)^2+(AB19-J19)^2+(AF19-J19)^2+(AJ19-J19)^2+(AN19-J19)^2+(AR19-J19)^2+(AV19-J19)^2+(AZ19-J19)^2)/10) -> 0.061533926 | L19: =K19/J19 -> 0.90531008 | N19: 0.102 | O19: 1 | P19: 0.0218 | R19: 0.1282 | S19: 1 | T19: 0.0218 | V19: 0.0669 | W19: 0 | X19: 0 | Z19: 0.0739 | AA19: 0.43 | AB19: 0.1004 | AD19: 0.0688 | AE19: 0 | AF19: 0 | AH19: 0.0864 | AI19: 0.12 | AJ19: 0.1558 | AL19: 0.0597 | AM19: 0.11 | AN19: 0.1058 | AP19: 0.0624 | AQ19: 0.23 | AR19: 0.1373 | AT19: 0.0133 | AU19: 0 | AV19: 0 | AX19: 0.0605 | AY19: 0.37 | AZ19: 0.1368
B20: CatBoost | C20: =D18/D20-1 -> 0.3029435 | D20: =(N20+R20+V20+Z20+AD20+AH20+AL20+AP20+AT20+AX20)/10 -> 0.10124 | E20: =SQRT(((N20-D20)^2+(R20-D20)^2+(V20-D20)^2+(Z20-D20)^2+(AD20-D20)^2+(AH20-D20)^2+(AL20-D20)^2+(AP20-D20)^2+(AT20-D20)^2+(AX20-D20)^2)/10) -> 0.012253914 | F20: =E20/D20 -> 0.12103826 | G20: =(O20+S20+W20+AA20+AE20+AI20+AM20+AQ20+AU20+AY20)/10 -> 0.463 | H20: =SQRT(((O20-G20)^2+(S20-G20)^2+(W20-G20)^2+(AA20-G20)^2+(AE20-G20)^2+(AI20-G20)^2+(AM20-G20)^2+(AQ20-G20)^2+(AU20-G20)^2+(AY20-G20)^2)/10) -> 0.15244999 | I20: =H20/G20 -> 0.32926564 | J20: =(P20+T20+X20+AB20+AF20+AJ20+AN20+AR20+AV20+AZ20)/10 -> 0.12503 | K20: =SQRT(((P20-J20)^2+(T20-J20)^2+(X20-J20)^2+(AB20-J20)^2+(AF20-J20)^2+(AJ20-J20)^2+(AN20-J20)^2+(AR20-J20)^2+(AV20-J20)^2+(AZ20-J20)^2)/10) -> 0.015465578 | L20: =K20/J20 -> 0.12369494 | N20: 0.0949 | O20: 0.56 | P20: 0.1142 | R20: 0.1083 | S20: 0.41 | T20: 0.1297 | V20: 0.1179 | W20: 0.61 | X20: 0.1064 | Z20: 0.094 | AA20: 0.47 | AB20: 0.1269 | AD20: 0.0946 | AE20: 0.31 | AF20: 0.1435 | AH20: 0.1171 | AI20: 0.57 | AJ20: 0.1194 | AL20: 0.0822 | AM20: 0.25 | AN20: 0.1506 | AP20: 0.0844 | AQ20: 0.21 | AR20: 0.1386 | AT20: 0.1082 | AU20: 0.57 | AV20: 0.1221 | AX20: 0.1108 | AY20: 0.67 | AZ20: 0.0989
B21: SCARF | C21: =D18/D21-1 -> 12.529231 | D21: =(N21+R21+V21+Z21+AD21+AH21+AL21+AP21+AT21+AX21)/10 -> 0.00975 | E21: =SQRT(((N21-D21)^2+(R21-D21)^2+(V21-D21)^2+(Z21-D21)^2+(AD21-D21)^2+(AH21-D21)^2+(AL21-D21)^2+(AP21-D21)^2+(AT21-D21)^2+(AX21-D21)^2)/10) -> 0.00054267854 | F21: =E21/D21 -> 0.055659338 | G21: =(O21+S21+W21+AA21+AE21+AI21+AM21+AQ21+AU21+AY21)/10 -> 0.299 | H21: =SQRT(((O21-G21)^2+(S21-G21)^2+(W21-G21)^2+(AA21-G21)^2+(AE21-G21)^2+(AI21-G21)^2+(AM21-G21)^2+(AQ21-G21)^2+(AU21-G21)^2+(AY21-G21)^2)/10) -> 0.056824291 | I21: =H21/G21 -> 0.19004779 | J21: =(P21+T21+X21+AB21+AF21+AJ21+AN21+AR21+AV21+AZ21)/10 -> 0.01673 | K21: =SQRT(((P21-J21)^2+(T21-J21)^2+(X21-J21)^2+(AB21-J21)^2+(AF21-J21)^2+(AJ21-J21)^2+(AN21-J21)^2+(AR21-J21)^2+(AV21-J21)^2+(AZ21-J21)^2)/10) -> 0.002446242 | L21: =K21/J21 -> 0.14621889 | N21: 0.0101 | O21: 0.43 | P21: 0.0201 | R21: 0.0091 | S21: 0.25 | T21: 0.0139 | V21: 0.0095 | W21: 0.29 | X21: 0.017 | Z21: 0.0101 | AA21: 0.35 | AB21: 0.0205 | AD21: 0.0101 | AE21: 0.31 | AF21: 0.0179 | AH21: 0.0098 | AI21: 0.25 | AJ21: 0.0152 | AL21: 0.0099 | AM21: 0.32 | AN21: 0.0174 | AP21: 0.0095 | AQ21: 0.27 | AR21: 0.015 | AT21: 0.0087 | AU21: 0.22 | AV21: 0.0125 | AX21: 0.0107 | AY21: 0.3 | AZ21: 0.0178
C23: effect, % | D23: AUPRC | G23: Recall | J23: F1 | N23: AUPRC | O23: For reference | R23: AUPRC | S23: For reference | V23: AUPRC | W23: For reference | Z23: AUPRC | AA23: For reference | AD23: AUPRC | AE23: For reference | AH23: AUPRC | AI23: For reference | AL23: AUPRC | AM23: For reference | AP23: AUPRC | AQ23: For reference | AT23: AUPRC | AU23: For reference | AX23: AUPRC | AY23: For reference
D24: mean | E24: σ | F24: CV | G24: mean | H24: σ | I24: CV | J24: mean | K24: σ | L24: CV | O24: Recall | P24: F1 | S24: Recall | T24: F1 | W24: Recall | X24: F1 | AA24: Recall | AB24: F1 | AE24: Recall | AF24: F1 | AI24: Recall | AJ24: F1 | AM24: Recall | AN24: F1 | AQ24: Recall | AR24: F1 | AU24: Recall | AV24: F1 | AY24: Recall | AZ24: F1
B25: LR | C25: =D26/D25-1 -> 0.64655074 | D25: =(N25+R25+V25+Z25+AD25+AH25+AL25+AP25+AT25+AX25)/10 -> 0.08799 | E25: =SQRT(((N25-D25)^2+(R25-D25)^2+(V25-D25)^2+(Z25-D25)^2+(AD25-D25)^2+(AH25-D25)^2+(AL25-D25)^2+(AP25-D25)^2+(AT25-D25)^2+(AX25-D25)^2)/10) -> 0.0013087781 | F25: =E25/D25 -> 0.014874168 | G25: =(O25+S25+W25+AA25+AE25+AI25+AM25+AQ25+AU25+AY25)/10 -> 0.795 | H25: =SQRT(((O25-G25)^2+(S25-G25)^2+(W25-G25)^2+(AA25-G25)^2+(AE25-G25)^2+(AI25-G25)^2+(AM25-G25)^2+(AQ25-G25)^2+(AU25-G25)^2+(AY25-G25)^2)/10) -> 0.0092195445 | I25: =H25/G25 -> 0.011596911 | J25: =(P25+T25+X25+AB25+AF25+AJ25+AN25+AR25+AV25+AZ25)/10 -> 0.07204 | K25: =SQRT(((P25-J25)^2+(T25-J25)^2+(X25-J25)^2+(AB25-J25)^2+(AF25-J25)^2+(AJ25-J25)^2+(AN25-J25)^2+(AR25-J25)^2+(AV25-J25)^2+(AZ25-J25)^2)/10) -> 0.00081264999 | L25: =K25/J25 -> 0.011280538 | N25: 0.0869 | O25: 0.8 | P25: 0.0726 | R25: 0.0868 | S25: 0.8 | T25: 0.0725 | V25: 0.0869 | W25: 0.8 | X25: 0.0726 | Z25: 0.0902 | AA25: 0.77 | AB25: 0.07 | AD25: 0.0897 | AE25: 0.79 | AF25: 0.0714 | AH25: 0.0868 | AI25: 0.8 | AJ25: 0.0725 | AL25: 0.0869 | AM25: 0.8 | AN25: 0.0726 | AP25: 0.088 | AQ25: 0.8 | AR25: 0.0724 | AT25: 0.0897 | AU25: 0.79 | AV25: 0.0714 | AX25: 0.088 | AY25: 0.8 | AZ25: 0.0724
B26: CLT-TAB without SQP | D26: =(N26+R26+V26+Z26+AD26+AH26+AL26+AP26+AT26+AX26)/10 -> 0.14488 | E26: =SQRT(((N26-D26)^2+(R26-D26)^2+(V26-D26)^2+(Z26-D26)^2+(AD26-D26)^2+(AH26-D26)^2+(AL26-D26)^2+(AP26-D26)^2+(AT26-D26)^2+(AX26-D26)^2)/10) -> 0.0090093063 | F26: =E26/D26 -> 0.06218461 | G26: =(O26+S26+W26+AA26+AE26+AI26+AM26+AQ26+AU26+AY26)/10 -> 0.789 | H26: =SQRT(((O26-G26)^2+(S26-G26)^2+(W26-G26)^2+(AA26-G26)^2+(AE26-G26)^2+(AI26-G26)^2+(AM26-G26)^2+(AQ26-G26)^2+(AU26-G26)^2+(AY26-G26)^2)/10) -> 0.026248809 | I26: =H26/G26 -> 0.033268453 | J26: =(P26+T26+X26+AB26+AF26+AJ26+AN26+AR26+AV26+AZ26)/10 -> 0.08433 | K26: =SQRT(((P26-J26)^2+(T26-J26)^2+(X26-J26)^2+(AB26-J26)^2+(AF26-J26)^2+(AJ26-J26)^2+(AN26-J26)^2+(AR26-J26)^2+(AV26-J26)^2+(AZ26-J26)^2)/10) -> 0.0027044593 | L26: =K26/J26 -> 0.032069955 | N26: 0.1507 | O26: 0.76 | P26: 0.079 | R26: 0.1299 | S26: 0.81 | T26: 0.0884 | V26: 0.1632 | W26: 0.82 | X26: 0.0889 | Z26: 0.1505 | AA26: 0.78 | AB26: 0.0842 | AD26: 0.1445 | AE26: 0.79 | AF26: 0.0855 | AH26: 0.1378 | AI26: 0.75 | AJ26: 0.0838 | AL26: 0.135 | AM26: 0.77 | AN26: 0.0835 | AP26: 0.15 | AQ26: 0.78 | AR26: 0.0822 | AT26: 0.1415 | AU26: 0.84 | AV26: 0.0838 | AX26: 0.1457 | AY26: 0.79 | AZ26: 0.084
B27: FT-transformer | C27: =D26/D27-1 -> 1.0063703 | D27: =(N27+R27+V27+Z27+AD27+AH27+AL27+AP27+AT27+AX27)/10 -> 0.07221 | E27: =SQRT(((N27-D27)^2+(R27-D27)^2+(V27-D27)^2+(Z27-D27)^2+(AD27-D27)^2+(AH27-D27)^2+(AL27-D27)^2+(AP27-D27)^2+(AT27-D27)^2+(AX27-D27)^2)/10) -> 0.028507208 | F27: =E27/D27 -> 0.394782 | G27: =(O27+S27+W27+AA27+AE27+AI27+AM27+AQ27+AU27+AY27)/10 -> 0.326 | H27: =SQRT(((O27-G27)^2+(S27-G27)^2+(W27-G27)^2+(AA27-G27)^2+(AE27-G27)^2+(AI27-G27)^2+(AM27-G27)^2+(AQ27-G27)^2+(AU27-G27)^2+(AY27-G27)^2)/10) -> 0.36584696 | I27: =H27/G27 -> 1.1222299 | J27: =(P27+T27+X27+AB27+AF27+AJ27+AN27+AR27+AV27+AZ27)/10 -> 0.06797 | K27: =SQRT(((P27-J27)^2+(T27-J27)^2+(X27-J27)^2+(AB27-J27)^2+(AF27-J27)^2+(AJ27-J27)^2+(AN27-J27)^2+(AR27-J27)^2+(AV27-J27)^2+(AZ27-J27)^2)/10) -> 0.061533926 | L27: =K27/J27 -> 0.90531008 | N27: 0.102 | O27: 1 | P27: 0.0218 | R27: 0.1282 | S27: 1 | T27: 0.0218 | V27: 0.0669 | W27: 0 | X27: 0 | Z27: 0.0739 | AA27: 0.43 | AB27: 0.1004 | AD27: 0.0688 | AE27: 0 | AF27: 0 | AH27: 0.0864 | AI27: 0.12 | AJ27: 0.1558 | AL27: 0.0597 | AM27: 0.11 | AN27: 0.1058 | AP27: 0.0624 | AQ27: 0.23 | AR27: 0.1373 | AT27: 0.0133 | AU27: 0 | AV27: 0 | AX27: 0.0605 | AY27: 0.37 | AZ27: 0.1368
B28: CatBoost | C28: =D26/D28-1 -> 0.43105492 | D28: =(N28+R28+V28+Z28+AD28+AH28+AL28+AP28+AT28+AX28)/10 -> 0.10124 | E28: =SQRT(((N28-D28)^2+(R28-D28)^2+(V28-D28)^2+(Z28-D28)^2+(AD28-D28)^2+(AH28-D28)^2+(AL28-D28)^2+(AP28-D28)^2+(AT28-D28)^2+(AX28-D28)^2)/10) -> 0.012253914 | F28: =E28/D28 -> 0.12103826 | G28: =(O28+S28+W28+AA28+AE28+AI28+AM28+AQ28+AU28+AY28)/10 -> 0.463 | H28: =SQRT(((O28-G28)^2+(S28-G28)^2+(W28-G28)^2+(AA28-G28)^2+(AE28-G28)^2+(AI28-G28)^2+(AM28-G28)^2+(AQ28-G28)^2+(AU28-G28)^2+(AY28-G28)^2)/10) -> 0.15244999 | I28: =H28/G28 -> 0.32926564 | J28: =(P28+T28+X28+AB28+AF28+AJ28+AN28+AR28+AV28+AZ28)/10 -> 0.12503 | K28: =SQRT(((P28-J28)^2+(T28-J28)^2+(X28-J28)^2+(AB28-J28)^2+(AF28-J28)^2+(AJ28-J28)^2+(AN28-J28)^2+(AR28-J28)^2+(AV28-J28)^2+(AZ28-J28)^2)/10) -> 0.015465578 | L28: =K28/J28 -> 0.12369494 | N28: 0.0949 | O28: 0.56 | P28: 0.1142 | R28: 0.1083 | S28: 0.41 | T28: 0.1297 | V28: 0.1179 | W28: 0.61 | X28: 0.1064 | Z28: 0.094 | AA28: 0.47 | AB28: 0.1269 | AD28: 0.0946 | AE28: 0.31 | AF28: 0.1435 | AH28: 0.1171 | AI28: 0.57 | AJ28: 0.1194 | AL28: 0.0822 | AM28: 0.25 | AN28: 0.1506 | AP28: 0.0844 | AQ28: 0.21 | AR28: 0.1386 | AT28: 0.1082 | AU28: 0.57 | AV28: 0.1221 | AX28: 0.1108 | AY28: 0.67 | AZ28: 0.0989
B29: SCARF | C29: =D26/D29-1 -> 13.859487 | D29: =(N29+R29+V29+Z29+AD29+AH29+AL29+AP29+AT29+AX29)/10 -> 0.00975 | E29: =SQRT(((N29-D29)^2+(R29-D29)^2+(V29-D29)^2+(Z29-D29)^2+(AD29-D29)^2+(AH29-D29)^2+(AL29-D29)^2+(AP29-D29)^2+(AT29-D29)^2+(AX29-D29)^2)/10) -> 0.00054267854 | F29: =E29/D29 -> 0.055659338 | G29: =(O29+S29+W29+AA29+AE29+AI29+AM29+AQ29+AU29+AY29)/10 -> 0.299 | H29: =SQRT(((O29-G29)^2+(S29-G29)^2+(W29-G29)^2+(AA29-G29)^2+(AE29-G29)^2+(AI29-G29)^2+(AM29-G29)^2+(AQ29-G29)^2+(AU29-G29)^2+(AY29-G29)^2)/10) -> 0.056824291 | I29: =H29/G29 -> 0.19004779 | J29: =(P29+T29+X29+AB29+AF29+AJ29+AN29+AR29+AV29+AZ29)/10 -> 0.01673 | K29: =SQRT(((P29-J29)^2+(T29-J29)^2+(X29-J29)^2+(AB29-J29)^2+(AF29-J29)^2+(AJ29-J29)^2+(AN29-J29)^2+(AR29-J29)^2+(AV29-J29)^2+(AZ29-J29)^2)/10) -> 0.002446242 | L29: =K29/J29 -> 0.14621889 | N29: 0.0101 | O29: 0.43 | P29: 0.0201 | R29: 0.0091 | S29: 0.25 | T29: 0.0139 | V29: 0.0095 | W29: 0.29 | X29: 0.017 | Z29: 0.0101 | AA29: 0.35 | AB29: 0.0205 | AD29: 0.0101 | AE29: 0.31 | AF29: 0.0179 | AH29: 0.0098 | AI29: 0.25 | AJ29: 0.0152 | AL29: 0.0099 | AM29: 0.32 | AN29: 0.0174 | AP29: 0.0095 | AQ29: 0.27 | AR29: 0.015 | AT29: 0.0087 | AU29: 0.22 | AV29: 0.0125 | AX29: 0.0107 | AY29: 0.3 | AZ29: 0.0178
C31: effect, % | D31: AUPRC | G31: Recall | J31: F1 | N31: AUPRC | O31: For reference | R31: AUPRC | S31: For reference | V31: AUPRC | W31: For reference | Z31: AUPRC | AA31: For reference | AD31: AUPRC | AE31: For reference | AH31: AUPRC | AI31: For reference | AL31: AUPRC | AM31: For reference | AP31: AUPRC | AQ31: For reference | AT31: AUPRC | AU31: For reference | AX31: AUPRC | AY31: For reference
D32: mean | E32: σ | F32: CV | G32: mean | H32: σ | I32: CV | J32: mean | K32: σ | L32: CV | O32: Recall | P32: F1 | S32: Recall | T32: F1 | W32: Recall | X32: F1 | AA32: Recall | AB32: F1 | AE32: Recall | AF32: F1 | AI32: Recall | AJ32: F1 | AM32: Recall | AN32: F1 | AQ32: Recall | AR32: F1 | AU32: Recall | AV32: F1 | AY32: Recall | AZ32: F1
B33: LR | C33: =D34/D33-1 -> 0.64143653 | D33: =(N33+R33+V33+Z33+AD33+AH33+AL33+AP33+AT33+AX33)/10 -> 0.08799 | E33: =SQRT(((N33-D33)^2+(R33-D33)^2+(V33-D33)^2+(Z33-D33)^2+(AD33-D33)^2+(AH33-D33)^2+(AL33-D33)^2+(AP33-D33)^2+(AT33-D33)^2+(AX33-D33)^2)/10) -> 0.0013087781 | F33: =E33/D33 -> 0.014874168 | G33: =(O33+S33+W33+AA33+AE33+AI33+AM33+AQ33+AU33+AY33)/10 -> 0.795 | H33: =SQRT(((O33-G33)^2+(S33-G33)^2+(W33-G33)^2+(AA33-G33)^2+(AE33-G33)^2+(AI33-G33)^2+(AM33-G33)^2+(AQ33-G33)^2+(AU33-G33)^2+(AY33-G33)^2)/10) -> 0.0092195445 | I33: =H33/G33 -> 0.011596911 | J33: =(P33+T33+X33+AB33+AF33+AJ33+AN33+AR33+AV33+AZ33)/10 -> 0.07204 | K33: =SQRT(((P33-J33)^2+(T33-J33)^2+(X33-J33)^2+(AB33-J33)^2+(AF33-J33)^2+(AJ33-J33)^2+(AN33-J33)^2+(AR33-J33)^2+(AV33-J33)^2+(AZ33-J33)^2)/10) -> 0.00081264999 | L33: =K33/J33 -> 0.011280538 | N33: 0.0869 | O33: 0.8 | P33: 0.0726 | R33: 0.0868 | S33: 0.8 | T33: 0.0725 | V33: 0.0869 | W33: 0.8 | X33: 0.0726 | Z33: 0.0902 | AA33: 0.77 | AB33: 0.07 | AD33: 0.0897 | AE33: 0.79 | AF33: 0.0714 | AH33: 0.0868 | AI33: 0.8 | AJ33: 0.0725 | AL33: 0.0869 | AM33: 0.8 | AN33: 0.0726 | AP33: 0.088 | AQ33: 0.8 | AR33: 0.0724 | AT33: 0.0897 | AU33: 0.79 | AV33: 0.0714 | AX33: 0.088 | AY33: 0.8 | AZ33: 0.0724
B34: CLT-TAB without CATA and SQP | D34: =(N34+R34+V34+Z34+AD34+AH34+AL34+AP34+AT34+AX34)/10 -> 0.14443 | E34: =SQRT(((N34-D34)^2+(R34-D34)^2+(V34-D34)^2+(Z34-D34)^2+(AD34-D34)^2+(AH34-D34)^2+(AL34-D34)^2+(AP34-D34)^2+(AT34-D34)^2+(AX34-D34)^2)/10) -> 0.0097148392 | F34: =E34/D34 -> 0.067263305 | G34: =(O34+S34+W34+AA34+AE34+AI34+AM34+AQ34+AU34+AY34)/10 -> 0.79 | H34: =SQRT(((O34-G34)^2+(S34-G34)^2+(W34-G34)^2+(AA34-G34)^2+(AE34-G34)^2+(AI34-G34)^2+(AM34-G34)^2+(AQ34-G34)^2+(AU34-G34)^2+(AY34-G34)^2)/10) -> 0.017888544 | I34: =H34/G34 -> 0.022643726 | J34: =(P34+T34+X34+AB34+AF34+AJ34+AN34+AR34+AV34+AZ34)/10 -> 0.08272 | K34: =SQRT(((P34-J34)^2+(T34-J34)^2+(X34-J34)^2+(AB34-J34)^2+(AF34-J34)^2+(AJ34-J34)^2+(AN34-J34)^2+(AR34-J34)^2+(AV34-J34)^2+(AZ34-J34)^2)/10) -> 0.0026820887 | L34: =K34/J34 -> 0.032423703 | N34: 0.143 | O34: 0.81 | P34: 0.0824 | R34: 0.1339 | S34: 0.76 | T34: 0.08 | V34: 0.1408 | W34: 0.79 | X34: 0.0802 | Z34: 0.132 | AA34: 0.78 | AB34: 0.0837 | AD34: 0.1564 | AE34: 0.81 | AF34: 0.0864 | AH34: 0.1536 | AI34: 0.79 | AJ34: 0.0794 | AL34: 0.1404 | AM34: 0.8 | AN34: 0.0813 | AP34: 0.1335 | AQ34: 0.76 | AR34: 0.081 | AT34: 0.1609 | AU34: 0.79 | AV34: 0.0859 | AX34: 0.1498 | AY34: 0.81 | AZ34: 0.0869
B35: FT-transformer | C35: =D34/D35-1 -> 1.0001385 | D35: =(N35+R35+V35+Z35+AD35+AH35+AL35+AP35+AT35+AX35)/10 -> 0.07221 | E35: =SQRT(((N35-D35)^2+(R35-D35)^2+(V35-D35)^2+(Z35-D35)^2+(AD35-D35)^2+(AH35-D35)^2+(AL35-D35)^2+(AP35-D35)^2+(AT35-D35)^2+(AX35-D35)^2)/10) -> 0.028507208 | F35: =E35/D35 -> 0.394782 | G35: =(O35+S35+W35+AA35+AE35+AI35+AM35+AQ35+AU35+AY35)/10 -> 0.326 | H35: =SQRT(((O35-G35)^2+(S35-G35)^2+(W35-G35)^2+(AA35-G35)^2+(AE35-G35)^2+(AI35-G35)^2+(AM35-G35)^2+(AQ35-G35)^2+(AU35-G35)^2+(AY35-G35)^2)/10) -> 0.36584696 | I35: =H35/G35 -> 1.1222299 | J35: =(P35+T35+X35+AB35+AF35+AJ35+AN35+AR35+AV35+AZ35)/10 -> 0.06797 | K35: =SQRT(((P35-J35)^2+(T35-J35)^2+(X35-J35)^2+(AB35-J35)^2+(AF35-J35)^2+(AJ35-J35)^2+(AN35-J35)^2+(AR35-J35)^2+(AV35-J35)^2+(AZ35-J35)^2)/10) -> 0.061533926 | L35: =K35/J35 -> 0.90531008 | N35: 0.102 | O35: 1 | P35: 0.0218 | R35: 0.1282 | S35: 1 | T35: 0.0218 | V35: 0.0669 | W35: 0 | X35: 0 | Z35: 0.0739 | AA35: 0.43 | AB35: 0.1004 | AD35: 0.0688 | AE35: 0 | AF35: 0 | AH35: 0.0864 | AI35: 0.12 | AJ35: 0.1558 | AL35: 0.0597 | AM35: 0.11 | AN35: 0.1058 | AP35: 0.0624 | AQ35: 0.23 | AR35: 0.1373 | AT35: 0.0133 | AU35: 0 | AV35: 0 | AX35: 0.0605 | AY35: 0.37 | AZ35: 0.1368
B36: CatBoost | C36: =D34/D36-1 -> 0.42661004 | D36: =(N36+R36+V36+Z36+AD36+AH36+AL36+AP36+AT36+AX36)/10 -> 0.10124 | E36: =SQRT(((N36-D36)^2+(R36-D36)^2+(V36-D36)^2+(Z36-D36)^2+(AD36-D36)^2+(AH36-D36)^2+(AL36-D36)^2+(AP36-D36)^2+(AT36-D36)^2+(AX36-D36)^2)/10) -> 0.012253914 | F36: =E36/D36 -> 0.12103826 | G36: =(O36+S36+W36+AA36+AE36+AI36+AM36+AQ36+AU36+AY36)/10 -> 0.463 | H36: =SQRT(((O36-G36)^2+(S36-G36)^2+(W36-G36)^2+(AA36-G36)^2+(AE36-G36)^2+(AI36-G36)^2+(AM36-G36)^2+(AQ36-G36)^2+(AU36-G36)^2+(AY36-G36)^2)/10) -> 0.15244999 | I36: =H36/G36 -> 0.32926564 | J36: =(P36+T36+X36+AB36+AF36+AJ36+AN36+AR36+AV36+AZ36)/10 -> 0.12503 | K36: =SQRT(((P36-J36)^2+(T36-J36)^2+(X36-J36)^2+(AB36-J36)^2+(AF36-J36)^2+(AJ36-J36)^2+(AN36-J36)^2+(AR36-J36)^2+(AV36-J36)^2+(AZ36-J36)^2)/10) -> 0.015465578 | L36: =K36/J36 -> 0.12369494 | N36: 0.0949 | O36: 0.56 | P36: 0.1142 | R36: 0.1083 | S36: 0.41 | T36: 0.1297 | V36: 0.1179 | W36: 0.61 | X36: 0.1064 | Z36: 0.094 | AA36: 0.47 | AB36: 0.1269 | AD36: 0.0946 | AE36: 0.31 | AF36: 0.1435 | AH36: 0.1171 | AI36: 0.57 | AJ36: 0.1194 | AL36: 0.0822 | AM36: 0.25 | AN36: 0.1506 | AP36: 0.0844 | AQ36: 0.21 | AR36: 0.1386 | AT36: 0.1082 | AU36: 0.57 | AV36: 0.1221 | AX36: 0.1108 | AY36: 0.67 | AZ36: 0.0989
B37: SCARF | C37: =D34/D37-1 -> 13.813333 | D37: =(N37+R37+V37+Z37+AD37+AH37+AL37+AP37+AT37+AX37)/10 -> 0.00975 | E37: =SQRT(((N37-D37)^2+(R37-D37)^2+(V37-D37)^2+(Z37-D37)^2+(AD37-D37)^2+(AH37-D37)^2+(AL37-D37)^2+(AP37-D37)^2+(AT37-D37)^2+(AX37-D37)^2)/10) -> 0.00054267854 | F37: =E37/D37 -> 0.055659338 | G37: =(O37+S37+W37+AA37+AE37+AI37+AM37+AQ37+AU37+AY37)/10 -> 0.299 | H37: =SQRT(((O37-G37)^2+(S37-G37)^2+(W37-G37)^2+(AA37-G37)^2+(AE37-G37)^2+(AI37-G37)^2+(AM37-G37)^2+(AQ37-G37)^2+(AU37-G37)^2+(AY37-G37)^2)/10) -> 0.056824291 | I37: =H37/G37 -> 0.19004779 | J37: =(P37+T37+X37+AB37+AF37+AJ37+AN37+AR37+AV37+AZ37)/10 -> 0.01673 | K37: =SQRT(((P37-J37)^2+(T37-J37)^2+(X37-J37)^2+(AB37-J37)^2+(AF37-J37)^2+(AJ37-J37)^2+(AN37-J37)^2+(AR37-J37)^2+(AV37-J37)^2+(AZ37-J37)^2)/10) -> 0.002446242 | L37: =K37/J37 -> 0.14621889 | N37: 0.0101 | O37: 0.43 | P37: 0.0201 | R37: 0.0091 | S37: 0.25 | T37: 0.0139 | V37: 0.0095 | W37: 0.29 | X37: 0.017 | Z37: 0.0101 | AA37: 0.35 | AB37: 0.0205 | AD37: 0.0101 | AE37: 0.31 | AF37: 0.0179 | AH37: 0.0098 | AI37: 0.25 | AJ37: 0.0152 | AL37: 0.0099 | AM37: 0.32 | AN37: 0.0174 | AP37: 0.0095 | AQ37: 0.27 | AR37: 0.015 | AT37: 0.0087 | AU37: 0.22 | AV37: 0.0125 | AX37: 0.0107 | AY37: 0.3 | AZ37: 0.0178

Sheet Fraud Detection
B1: Overview
B2: The Credit Card Fraud Detection dataset is a widely used benchmark for anomaly detection in financial transactions, made publicly available through a Kaggle competition. It consists of credit card transactions made by European cardholders in September 2013 over a two‑day period. The dataset contains 284,807 transactions, of which 492 are fraudulent, giving a fraud rate of approximately 0.172 %. To protect cardholders’ privacy, the 28 numerical features V1 … V28 are the result of a Principal Component Analysis (PCA) transformation. Two features were left untransformed: the transaction Amount and the Time elapsed since the first recorded transaction. The target variable is Class (also named Label in some versions), where 1 indicates fraud and 0 a legitimate transaction. Due to the strong class imbalance, the dataset is particularly challenging for standard classifiers; models often require resampling techniques (e.g., SMOTE) or cost‑sensitive learning to achieve good performance. Despite its imbalance, the dataset has become a reference benchmark for evaluating fraud detection algorithms, ranging from logistic regression and tree‑based ensembles to deep learning architectures.
B3: We used the Credit Card Fraud Detection dataset, which contains 283 726 instances with a 0,17 % anomaly rate. It comprises 30 numerical and 0 categorical features. The data were used after preprocessing (missing values, duplicates, and constant features were removed). F1 and Recall scores were obtained with a threshold of 0.5. We used 59 984 instances for finetuning, of which 100 were anomalies, and the same number (59 984 instances, 100 anomalies) for testing.
B5: Random AUPRC | C5: 0.0017 | N5: Seed
G6: For reference | N6: 42 | R6: 43 | V6: 44 | Z6: 45 | AD6: 46 | AH6: 47 | AL6: 48 | AP6: 49 | AT6: 50 | AX6: 51
C7: effect, % | D7: AUPRC | G7: Recall | J7: F1 | N7: AUPRC | O7: For reference | R7: AUPRC | S7: For reference | V7: AUPRC | W7: For reference | Z7: AUPRC | AA7: For reference | AD7: AUPRC | AE7: For reference | AH7: AUPRC | AI7: For reference | AL7: AUPRC | AM7: For reference | AP7: AUPRC | AQ7: For reference | AT7: AUPRC | AU7: For reference | AX7: AUPRC | AY7: For reference
D8: mean | E8: σ | F8: CV | G8: mean | H8: σ | I8: CV | J8: mean | K8: σ | L8: CV | O8: Recall | P8: F1 | S8: Recall | T8: F1 | W8: Recall | X8: F1 | AA8: Recall | AB8: F1 | AE8: Recall | AF8: F1 | AI8: Recall | AJ8: F1 | AM8: Recall | AN8: F1 | AQ8: Recall | AR8: F1 | AU8: Recall | AV8: F1 | AY8: Recall | AZ8: F1
B9: LR | C9: =D10/D9-1 -> -0.06335751 | D9: =(N9+R9+V9+Z9+AD9+AH9+AL9+AP9+AT9+AX9)/10 -> 0.6618 | E9: =SQRT(((N9-D9)^2+(R9-D9)^2+(V9-D9)^2+(Z9-D9)^2+(AD9-D9)^2+(AH9-D9)^2+(AL9-D9)^2+(AP9-D9)^2+(AT9-D9)^2+(AX9-D9)^2)/10) -> 1.110223e-16 | F9: =E9/D9 -> 1.6775809e-16 | G9: =(O9+S9+W9+AA9+AE9+AI9+AM9+AQ9+AU9+AY9)/10 -> 0.88 | H9: =SQRT(((O9-G9)^2+(S9-G9)^2+(W9-G9)^2+(AA9-G9)^2+(AE9-G9)^2+(AI9-G9)^2+(AM9-G9)^2+(AQ9-G9)^2+(AU9-G9)^2+(AY9-G9)^2)/10) -> 1.110223e-16 | I9: =H9/G9 -> 1.2616171e-16 | J9: =(P9+T9+X9+AB9+AF9+AJ9+AN9+AR9+AV9+AZ9)/10 -> 0.1099 | K9: =SQRT(((P9-J9)^2+(T9-J9)^2+(X9-J9)^2+(AB9-J9)^2+(AF9-J9)^2+(AJ9-J9)^2+(AN9-J9)^2+(AR9-J9)^2+(AV9-J9)^2+(AZ9-J9)^2)/10) -> 0 | L9: =K9/J9 -> 0 | N9: 0.6618 | O9: 0.88 | P9: 0.1099 | R9: 0.6618 | S9: 0.88 | T9: 0.1099 | V9: 0.6618 | W9: 0.88 | X9: 0.1099 | Z9: 0.6618 | AA9: 0.88 | AB9: 0.1099 | AD9: 0.6618 | AE9: 0.88 | AF9: 0.1099 | AH9: 0.6618 | AI9: 0.88 | AJ9: 0.1099 | AL9: 0.6618 | AM9: 0.88 | AN9: 0.1099 | AP9: 0.6618 | AQ9: 0.88 | AR9: 0.1099 | AT9: 0.6618 | AU9: 0.88 | AV9: 0.1099 | AX9: 0.6618 | AY9: 0.88 | AZ9: 0.1099
B10: CLT-TAB | D10: =(N10+R10+V10+Z10+AD10+AH10+AL10+AP10+AT10+AX10)/10 -> 0.61987 | E10: =SQRT(((N10-D10)^2+(R10-D10)^2+(V10-D10)^2+(Z10-D10)^2+(AD10-D10)^2+(AH10-D10)^2+(AL10-D10)^2+(AP10-D10)^2+(AT10-D10)^2+(AX10-D10)^2)/10) -> 0.058983863 | F10: =E10/D10 -> 0.095155215 | G10: =(O10+S10+W10+AA10+AE10+AI10+AM10+AQ10+AU10+AY10)/10 -> 0.875 | H10: =SQRT(((O10-G10)^2+(S10-G10)^2+(W10-G10)^2+(AA10-G10)^2+(AE10-G10)^2+(AI10-G10)^2+(AM10-G10)^2+(AQ10-G10)^2+(AU10-G10)^2+(AY10-G10)^2)/10) -> 0.014317821 | I10: =H10/G10 -> 0.016363224 | J10: =(P10+T10+X10+AB10+AF10+AJ10+AN10+AR10+AV10+AZ10)/10 -> 0.0902 | K10: =SQRT(((P10-J10)^2+(T10-J10)^2+(X10-J10)^2+(AB10-J10)^2+(AF10-J10)^2+(AJ10-J10)^2+(AN10-J10)^2+(AR10-J10)^2+(AV10-J10)^2+(AZ10-J10)^2)/10) -> 0.0066947741 | L10: =K10/J10 -> 0.074221442 | N10: 0.7009 | O10: 0.9 | P10: 0.0979 | R10: 0.6434 | S10: 0.89 | T10: 0.1009 | V10: 0.6507 | W10: 0.88 | X10: 0.0902 | Z10: 0.6778 | AA10: 0.86 | AB10: 0.0829 | AD10: 0.4878 | AE10: 0.88 | AF10: 0.0907 | AH10: 0.5753 | AI10: 0.86 | AJ10: 0.0975 | AL10: 0.6246 | AM10: 0.87 | AN10: 0.0853 | AP10: 0.6578 | AQ10: 0.89 | AR10: 0.0925 | AT10: 0.6091 | AU10: 0.86 | AV10: 0.0837 | AX10: 0.5713 | AY10: 0.86 | AZ10: 0.0804
B11: FT-transformer | C11: =D10/D11-1 -> 22.979497 | D11: =(N11+R11+V11+Z11+AD11+AH11+AL11+AP11+AT11+AX11)/10 -> 0.02585 | E11: =SQRT(((N11-D11)^2+(R11-D11)^2+(V11-D11)^2+(Z11-D11)^2+(AD11-D11)^2+(AH11-D11)^2+(AL11-D11)^2+(AP11-D11)^2+(AT11-D11)^2+(AX11-D11)^2)/10) -> 0.035236891 | F11: =E11/D11 -> 1.3631293 | G11: =(O11+S11+W11+AA11+AE11+AI11+AM11+AQ11+AU11+AY11)/10 -> 0 | H11: =SQRT(((O11-G11)^2+(S11-G11)^2+(W11-G11)^2+(AA11-G11)^2+(AE11-G11)^2+(AI11-G11)^2+(AM11-G11)^2+(AQ11-G11)^2+(AU11-G11)^2+(AY11-G11)^2)/10) -> 0 | I11: =H11/G11 -> #DIV/0! | J11: =(P11+T11+X11+AB11+AF11+AJ11+AN11+AR11+AV11+AZ11)/10 -> 0 | K11: =SQRT(((P11-J11)^2+(T11-J11)^2+(X11-J11)^2+(AB11-J11)^2+(AF11-J11)^2+(AJ11-J11)^2+(AN11-J11)^2+(AR11-J11)^2+(AV11-J11)^2+(AZ11-J11)^2)/10) -> 0 | L11: =K11/J11 -> #DIV/0! | N11: 0.0067 | O11: 0 | P11: 0 | R11: 0.0182 | S11: 0 | T11: 0 | V11: 0.0511 | W11: 0 | X11: 0 | Z11: 0.107 | AA11: 0 | AB11: 0 | AD11: 0.0016 | AE11: 0 | AF11: 0 | AH11: 0.0017 | AI11: 0 | AJ11: 0 | AL11: 0.0682 | AM11: 0 | AN11: 0 | AP11: 0.0013 | AQ11: 0 | AR11: 0 | AT11: 0.001 | AU11: 0 | AV11: 0 | AX11: 0.0017 | AY11: 0 | AZ11: 0
B12: CatBoost | C12: =D10/D12-1 -> -0.12051475 | D12: =(N12+R12+V12+Z12+AD12+AH12+AL12+AP12+AT12+AX12)/10 -> 0.70481 | E12: =SQRT(((N12-D12)^2+(R12-D12)^2+(V12-D12)^2+(Z12-D12)^2+(AD12-D12)^2+(AH12-D12)^2+(AL12-D12)^2+(AP12-D12)^2+(AT12-D12)^2+(AX12-D12)^2)/10) -> 0.040313086 | F12: =E12/D12 -> 0.057197097 | G12: =(O12+S12+W12+AA12+AE12+AI12+AM12+AQ12+AU12+AY12)/10 -> 0.765 | H12: =SQRT(((O12-G12)^2+(S12-G12)^2+(W12-G12)^2+(AA12-G12)^2+(AE12-G12)^2+(AI12-G12)^2+(AM12-G12)^2+(AQ12-G12)^2+(AU12-G12)^2+(AY12-G12)^2)/10) -> 0.01118034 | I12: =H12/G12 -> 0.014614823 | J12: =(P12+T12+X12+AB12+AF12+AJ12+AN12+AR12+AV12+AZ12)/10 -> 0.6575 | K12: =SQRT(((P12-J12)^2+(T12-J12)^2+(X12-J12)^2+(AB12-J12)^2+(AF12-J12)^2+(AJ12-J12)^2+(AN12-J12)^2+(AR12-J12)^2+(AV12-J12)^2+(AZ12-J12)^2)/10) -> 0.047885071 | L12: =K12/J12 -> 0.072829005 | N12: 0.6639 | O12: 0.76 | P12: 0.5914 | R12: 0.6903 | S12: 0.79 | T12: 0.61 | V12: 0.7504 | W12: 0.77 | X12: 0.6937 | Z12: 0.7566 | AA12: 0.77 | AB12: 0.7196 | AD12: 0.665 | AE12: 0.77 | AF12: 0.6696 | AH12: 0.7209 | AI12: 0.75 | AJ12: 0.6522 | AL12: 0.6684 | AM12: 0.76 | AN12: 0.6032 | AP12: 0.6987 | AQ12: 0.76 | AR12: 0.6972 | AT12: 0.7722 | AU12: 0.75 | AV12: 0.7246 | AX12: 0.6617 | AY12: 0.77 | AZ12: 0.6135
B13: SCARF | C13: =D10/D13-1 -> 589.35238 | D13: =(N13+R13+V13+Z13+AD13+AH13+AL13+AP13+AT13+AX13)/10 -> 0.00105 | E13: =SQRT(((N13-D13)^2+(R13-D13)^2+(V13-D13)^2+(Z13-D13)^2+(AD13-D13)^2+(AH13-D13)^2+(AL13-D13)^2+(AP13-D13)^2+(AT13-D13)^2+(AX13-D13)^2)/10) -> 0.00016278821 | F13: =E13/D13 -> 0.15503639 | G13: =(O13+S13+W13+AA13+AE13+AI13+AM13+AQ13+AU13+AY13)/10 -> 0.055 | H13: =SQRT(((O13-G13)^2+(S13-G13)^2+(W13-G13)^2+(AA13-G13)^2+(AE13-G13)^2+(AI13-G13)^2+(AM13-G13)^2+(AQ13-G13)^2+(AU13-G13)^2+(AY13-G13)^2)/10) -> 0.013601471 | I13: =H13/G13 -> 0.24729946 | J13: =(P13+T13+X13+AB13+AF13+AJ13+AN13+AR13+AV13+AZ13)/10 -> 0.00071 | K13: =SQRT(((P13-J13)^2+(T13-J13)^2+(X13-J13)^2+(AB13-J13)^2+(AF13-J13)^2+(AJ13-J13)^2+(AN13-J13)^2+(AR13-J13)^2+(AV13-J13)^2+(AZ13-J13)^2)/10) -> 0.00027 | L13: =K13/J13 -> 0.38028169 | N13: 0.0009 | O13: 0.05 | P13: 0.0005 | R13: 0.0009 | S13: 0.06 | T13: 0.0006 | V13: 0.0011 | W13: 0.07 | X13: 0.0008 | Z13: 0.0013 | AA13: 0.08 | AB13: 0.0014 | AD13: 0.0013 | AE13: 0.06 | AF13: 0.0009 | AH13: 0.0009 | AI13: 0.06 | AJ13: 0.0006 | AL13: 0.0009 | AM13: 0.04 | AN13: 0.0005 | AP13: 0.0011 | AQ13: 0.05 | AR13: 0.0007 | AT13: 0.0012 | AU13: 0.05 | AV13: 0.0007 | AX13: 0.0009 | AY13: 0.03 | AZ13: 0.0004
C15: effect, % | D15: AUPRC | G15: Recall | J15: F1 | N15: AUPRC | O15: For reference | R15: AUPRC | S15: For reference | V15: AUPRC | W15: For reference | Z15: AUPRC | AA15: For reference | AD15: AUPRC | AE15: For reference | AH15: AUPRC | AI15: For reference | AL15: AUPRC | AM15: For reference | AP15: AUPRC | AQ15: For reference | AT15: AUPRC | AU15: For reference | AX15: AUPRC | AY15: For reference
D16: mean | E16: σ | F16: CV | G16: mean | H16: σ | I16: CV | J16: mean | K16: σ | L16: CV | O16: Recall | P16: F1 | S16: Recall | T16: F1 | W16: Recall | X16: F1 | AA16: Recall | AB16: F1 | AE16: Recall | AF16: F1 | AI16: Recall | AJ16: F1 | AM16: Recall | AN16: F1 | AQ16: Recall | AR16: F1 | AU16: Recall | AV16: F1 | AY16: Recall | AZ16: F1
B17: LR | C17: =D18/D17-1 -> -0.099123602 | D17: =(N17+R17+V17+Z17+AD17+AH17+AL17+AP17+AT17+AX17)/10 -> 0.6618 | E17: =SQRT(((N17-D17)^2+(R17-D17)^2+(V17-D17)^2+(Z17-D17)^2+(AD17-D17)^2+(AH17-D17)^2+(AL17-D17)^2+(AP17-D17)^2+(AT17-D17)^2+(AX17-D17)^2)/10) -> 1.110223e-16 | F17: =E17/D17 -> 1.6775809e-16 | G17: =(O17+S17+W17+AA17+AE17+AI17+AM17+AQ17+AU17+AY17)/10 -> 0.88 | H17: =SQRT(((O17-G17)^2+(S17-G17)^2+(W17-G17)^2+(AA17-G17)^2+(AE17-G17)^2+(AI17-G17)^2+(AM17-G17)^2+(AQ17-G17)^2+(AU17-G17)^2+(AY17-G17)^2)/10) -> 1.110223e-16 | I17: =H17/G17 -> 1.2616171e-16 | J17: =(P17+T17+X17+AB17+AF17+AJ17+AN17+AR17+AV17+AZ17)/10 -> 0.1099 | K17: =SQRT(((P17-J17)^2+(T17-J17)^2+(X17-J17)^2+(AB17-J17)^2+(AF17-J17)^2+(AJ17-J17)^2+(AN17-J17)^2+(AR17-J17)^2+(AV17-J17)^2+(AZ17-J17)^2)/10) -> 0 | L17: =K17/J17 -> 0 | N17: 0.6618 | O17: 0.88 | P17: 0.1099 | R17: 0.6618 | S17: 0.88 | T17: 0.1099 | V17: 0.6618 | W17: 0.88 | X17: 0.1099 | Z17: 0.6618 | AA17: 0.88 | AB17: 0.1099 | AD17: 0.6618 | AE17: 0.88 | AF17: 0.1099 | AH17: 0.6618 | AI17: 0.88 | AJ17: 0.1099 | AL17: 0.6618 | AM17: 0.88 | AN17: 0.1099 | AP17: 0.6618 | AQ17: 0.88 | AR17: 0.1099 | AT17: 0.6618 | AU17: 0.88 | AV17: 0.1099 | AX17: 0.6618 | AY17: 0.88 | AZ17: 0.1099
B18: CLT-TAB without CATA | D18: =(N18+R18+V18+Z18+AD18+AH18+AL18+AP18+AT18+AX18)/10 -> 0.5962 | E18: =SQRT(((N18-D18)^2+(R18-D18)^2+(V18-D18)^2+(Z18-D18)^2+(AD18-D18)^2+(AH18-D18)^2+(AL18-D18)^2+(AP18-D18)^2+(AT18-D18)^2+(AX18-D18)^2)/10) -> 0.056313373 | F18: =E18/D18 -> 0.09445383 | G18: =(O18+S18+W18+AA18+AE18+AI18+AM18+AQ18+AU18+AY18)/10 -> 0.866 | H18: =SQRT(((O18-G18)^2+(S18-G18)^2+(W18-G18)^2+(AA18-G18)^2+(AE18-G18)^2+(AI18-G18)^2+(AM18-G18)^2+(AQ18-G18)^2+(AU18-G18)^2+(AY18-G18)^2)/10) -> 0.008 | I18: =H18/G18 -> 0.0092378753 | J18: =(P18+T18+X18+AB18+AF18+AJ18+AN18+AR18+AV18+AZ18)/10 -> 0.085 | K18: =SQRT(((P18-J18)^2+(T18-J18)^2+(X18-J18)^2+(AB18-J18)^2+(AF18-J18)^2+(AJ18-J18)^2+(AN18-J18)^2+(AR18-J18)^2+(AV18-J18)^2+(AZ18-J18)^2)/10) -> 0.005623522 | L18: =K18/J18 -> 0.066159083 | N18: 0.5633 | O18: 0.86 | P18: 0.0789 | R18: 0.6661 | S18: 0.86 | T18: 0.0762 | V18: 0.5639 | W18: 0.88 | X18: 0.0826 | Z18: 0.6099 | AA18: 0.87 | AB18: 0.0884 | AD18: 0.5652 | AE18: 0.87 | AF18: 0.086 | AH18: 0.7026 | AI18: 0.85 | AJ18: 0.0827 | AL18: 0.6001 | AM18: 0.87 | AN18: 0.0904 | AP18: 0.6411 | AQ18: 0.86 | AR18: 0.0863 | AT18: 0.5289 | AU18: 0.87 | AV18: 0.0818 | AX18: 0.5209 | AY18: 0.87 | AZ18: 0.0967
B19: FT-transformer | C19: =D18/D19-1 -> 22.06383 | D19: =(N19+R19+V19+Z19+AD19+AH19+AL19+AP19+AT19+AX19)/10 -> 0.02585 | E19: =SQRT(((N19-D19)^2+(R19-D19)^2+(V19-D19)^2+(Z19-D19)^2+(AD19-D19)^2+(AH19-D19)^2+(AL19-D19)^2+(AP19-D19)^2+(AT19-D19)^2+(AX19-D19)^2)/10) -> 0.035236891 | F19: =E19/D19 -> 1.3631293 | G19: =(O19+S19+W19+AA19+AE19+AI19+AM19+AQ19+AU19+AY19)/10 -> 0 | H19: =SQRT(((O19-G19)^2+(S19-G19)^2+(W19-G19)^2+(AA19-G19)^2+(AE19-G19)^2+(AI19-G19)^2+(AM19-G19)^2+(AQ19-G19)^2+(AU19-G19)^2+(AY19-G19)^2)/10) -> 0 | I19: =H19/G19 -> #DIV/0! | J19: =(P19+T19+X19+AB19+AF19+AJ19+AN19+AR19+AV19+AZ19)/10 -> 0 | K19: =SQRT(((P19-J19)^2+(T19-J19)^2+(X19-J19)^2+(AB19-J19)^2+(AF19-J19)^2+(AJ19-J19)^2+(AN19-J19)^2+(AR19-J19)^2+(AV19-J19)^2+(AZ19-J19)^2)/10) -> 0 | L19: =K19/J19 -> #DIV/0! | N19: 0.0067 | O19: 0 | P19: 0 | R19: 0.0182 | S19: 0 | T19: 0 | V19: 0.0511 | W19: 0 | X19: 0 | Z19: 0.107 | AA19: 0 | AB19: 0 | AD19: 0.0016 | AE19: 0 | AF19: 0 | AH19: 0.0017 | AI19: 0 | AJ19: 0 | AL19: 0.0682 | AM19: 0 | AN19: 0 | AP19: 0.0013 | AQ19: 0 | AR19: 0 | AT19: 0.001 | AU19: 0 | AV19: 0 | AX19: 0.0017 | AY19: 0 | AZ19: 0
B20: CatBoost | C20: =D18/D20-1 -> -0.15409827 | D20: =(N20+R20+V20+Z20+AD20+AH20+AL20+AP20+AT20+AX20)/10 -> 0.70481 | E20: =SQRT(((N20-D20)^2+(R20-D20)^2+(V20-D20)^2+(Z20-D20)^2+(AD20-D20)^2+(AH20-D20)^2+(AL20-D20)^2+(AP20-D20)^2+(AT20-D20)^2+(AX20-D20)^2)/10) -> 0.040313086 | F20: =E20/D20 -> 0.057197097 | G20: =(O20+S20+W20+AA20+AE20+AI20+AM20+AQ20+AU20+AY20)/10 -> 0.765 | H20: =SQRT(((O20-G20)^2+(S20-G20)^2+(W20-G20)^2+(AA20-G20)^2+(AE20-G20)^2+(AI20-G20)^2+(AM20-G20)^2+(AQ20-G20)^2+(AU20-G20)^2+(AY20-G20)^2)/10) -> 0.01118034 | I20: =H20/G20 -> 0.014614823 | J20: =(P20+T20+X20+AB20+AF20+AJ20+AN20+AR20+AV20+AZ20)/10 -> 0.6575 | K20: =SQRT(((P20-J20)^2+(T20-J20)^2+(X20-J20)^2+(AB20-J20)^2+(AF20-J20)^2+(AJ20-J20)^2+(AN20-J20)^2+(AR20-J20)^2+(AV20-J20)^2+(AZ20-J20)^2)/10) -> 0.047885071 | L20: =K20/J20 -> 0.072829005 | N20: 0.6639 | O20: 0.76 | P20: 0.5914 | R20: 0.6903 | S20: 0.79 | T20: 0.61 | V20: 0.7504 | W20: 0.77 | X20: 0.6937 | Z20: 0.7566 | AA20: 0.77 | AB20: 0.7196 | AD20: 0.665 | AE20: 0.77 | AF20: 0.6696 | AH20: 0.7209 | AI20: 0.75 | AJ20: 0.6522 | AL20: 0.6684 | AM20: 0.76 | AN20: 0.6032 | AP20: 0.6987 | AQ20: 0.76 | AR20: 0.6972 | AT20: 0.7722 | AU20: 0.75 | AV20: 0.7246 | AX20: 0.6617 | AY20: 0.77 | AZ20: 0.6135
B21: SCARF | C21: =D18/D21-1 -> 566.80952 | D21: =(N21+R21+V21+Z21+AD21+AH21+AL21+AP21+AT21+AX21)/10 -> 0.00105 | E21: =SQRT(((N21-D21)^2+(R21-D21)^2+(V21-D21)^2+(Z21-D21)^2+(AD21-D21)^2+(AH21-D21)^2+(AL21-D21)^2+(AP21-D21)^2+(AT21-D21)^2+(AX21-D21)^2)/10) -> 0.00016278821 | F21: =E21/D21 -> 0.15503639 | G21: =(O21+S21+W21+AA21+AE21+AI21+AM21+AQ21+AU21+AY21)/10 -> 0.055 | H21: =SQRT(((O21-G21)^2+(S21-G21)^2+(W21-G21)^2+(AA21-G21)^2+(AE21-G21)^2+(AI21-G21)^2+(AM21-G21)^2+(AQ21-G21)^2+(AU21-G21)^2+(AY21-G21)^2)/10) -> 0.013601471 | I21: =H21/G21 -> 0.24729946 | J21: =(P21+T21+X21+AB21+AF21+AJ21+AN21+AR21+AV21+AZ21)/10 -> 0.00071 | K21: =SQRT(((P21-J21)^2+(T21-J21)^2+(X21-J21)^2+(AB21-J21)^2+(AF21-J21)^2+(AJ21-J21)^2+(AN21-J21)^2+(AR21-J21)^2+(AV21-J21)^2+(AZ21-J21)^2)/10) -> 0.00027 | L21: =K21/J21 -> 0.38028169 | N21: 0.0009 | O21: 0.05 | P21: 0.0005 | R21: 0.0009 | S21: 0.06 | T21: 0.0006 | V21: 0.0011 | W21: 0.07 | X21: 0.0008 | Z21: 0.0013 | AA21: 0.08 | AB21: 0.0014 | AD21: 0.0013 | AE21: 0.06 | AF21: 0.0009 | AH21: 0.0009 | AI21: 0.06 | AJ21: 0.0006 | AL21: 0.0009 | AM21: 0.04 | AN21: 0.0005 | AP21: 0.0011 | AQ21: 0.05 | AR21: 0.0007 | AT21: 0.0012 | AU21: 0.05 | AV21: 0.0007 | AX21: 0.0009 | AY21: 0.03 | AZ21: 0.0004
C23: effect, % | D23: AUPRC | G23: Recall | J23: F1 | N23: AUPRC | O23: For reference | R23: AUPRC | S23: For reference | V23: AUPRC | W23: For reference | Z23: AUPRC | AA23: For reference | AD23: AUPRC | AE23: For reference | AH23: AUPRC | AI23: For reference | AL23: AUPRC | AM23: For reference | AP23: AUPRC | AQ23: For reference | AT23: AUPRC | AU23: For reference | AX23: AUPRC | AY23: For reference
D24: mean | E24: σ | F24: CV | G24: mean | H24: σ | I24: CV | J24: mean | K24: σ | L24: CV | O24: Recall | P24: F1 | S24: Recall | T24: F1 | W24: Recall | X24: F1 | AA24: Recall | AB24: F1 | AE24: Recall | AF24: F1 | AI24: Recall | AJ24: F1 | AM24: Recall | AN24: F1 | AQ24: Recall | AR24: F1 | AU24: Recall | AV24: F1 | AY24: Recall | AZ24: F1
B25: LR | C25: =D26/D25-1 -> -0.10832578 | D25: =(N25+R25+V25+Z25+AD25+AH25+AL25+AP25+AT25+AX25)/10 -> 0.6618 | E25: =SQRT(((N25-D25)^2+(R25-D25)^2+(V25-D25)^2+(Z25-D25)^2+(AD25-D25)^2+(AH25-D25)^2+(AL25-D25)^2+(AP25-D25)^2+(AT25-D25)^2+(AX25-D25)^2)/10) -> 1.110223e-16 | F25: =E25/D25 -> 1.6775809e-16 | G25: =(O25+S25+W25+AA25+AE25+AI25+AM25+AQ25+AU25+AY25)/10 -> 0.88 | H25: =SQRT(((O25-G25)^2+(S25-G25)^2+(W25-G25)^2+(AA25-G25)^2+(AE25-G25)^2+(AI25-G25)^2+(AM25-G25)^2+(AQ25-G25)^2+(AU25-G25)^2+(AY25-G25)^2)/10) -> 1.110223e-16 | I25: =H25/G25 -> 1.2616171e-16 | J25: =(P25+T25+X25+AB25+AF25+AJ25+AN25+AR25+AV25+AZ25)/10 -> 0.1099 | K25: =SQRT(((P25-J25)^2+(T25-J25)^2+(X25-J25)^2+(AB25-J25)^2+(AF25-J25)^2+(AJ25-J25)^2+(AN25-J25)^2+(AR25-J25)^2+(AV25-J25)^2+(AZ25-J25)^2)/10) -> 0 | L25: =K25/J25 -> 0 | N25: 0.6618 | O25: 0.88 | P25: 0.1099 | R25: 0.6618 | S25: 0.88 | T25: 0.1099 | V25: 0.6618 | W25: 0.88 | X25: 0.1099 | Z25: 0.6618 | AA25: 0.88 | AB25: 0.1099 | AD25: 0.6618 | AE25: 0.88 | AF25: 0.1099 | AH25: 0.6618 | AI25: 0.88 | AJ25: 0.1099 | AL25: 0.6618 | AM25: 0.88 | AN25: 0.1099 | AP25: 0.6618 | AQ25: 0.88 | AR25: 0.1099 | AT25: 0.6618 | AU25: 0.88 | AV25: 0.1099 | AX25: 0.6618 | AY25: 0.88 | AZ25: 0.1099
B26: CLT-TAB without SQP | D26: =(N26+R26+V26+Z26+AD26+AH26+AL26+AP26+AT26+AX26)/10 -> 0.59011 | E26: =SQRT(((N26-D26)^2+(R26-D26)^2+(V26-D26)^2+(Z26-D26)^2+(AD26-D26)^2+(AH26-D26)^2+(AL26-D26)^2+(AP26-D26)^2+(AT26-D26)^2+(AX26-D26)^2)/10) -> 0.094846259 | F26: =E26/D26 -> 0.16072641 | G26: =(O26+S26+W26+AA26+AE26+AI26+AM26+AQ26+AU26+AY26)/10 -> 0.878 | H26: =SQRT(((O26-G26)^2+(S26-G26)^2+(W26-G26)^2+(AA26-G26)^2+(AE26-G26)^2+(AI26-G26)^2+(AM26-G26)^2+(AQ26-G26)^2+(AU26-G26)^2+(AY26-G26)^2)/10) -> 0.016613248 | I26: =H26/G26 -> 0.018921694 | J26: =(P26+T26+X26+AB26+AF26+AJ26+AN26+AR26+AV26+AZ26)/10 -> 0.08665 | K26: =SQRT(((P26-J26)^2+(T26-J26)^2+(X26-J26)^2+(AB26-J26)^2+(AF26-J26)^2+(AJ26-J26)^2+(AN26-J26)^2+(AR26-J26)^2+(AV26-J26)^2+(AZ26-J26)^2)/10) -> 0.0087625624 | L26: =K26/J26 -> 0.10112594 | N26: 0.6204 | O26: 0.86 | P26: 0.0844 | R26: 0.5418 | S26: 0.88 | T26: 0.0975 | V26: 0.7087 | W26: 0.87 | X26: 0.0696 | Z26: 0.6318 | AA26: 0.9 | AB26: 0.096 | AD26: 0.6279 | AE26: 0.87 | AF26: 0.0826 | AH26: 0.3303 | AI26: 0.91 | AJ26: 0.0769 | AL26: 0.6245 | AM26: 0.89 | AN26: 0.0986 | AP26: 0.6026 | AQ26: 0.86 | AR26: 0.0883 | AT26: 0.6135 | AU26: 0.86 | AV26: 0.0841 | AX26: 0.5996 | AY26: 0.88 | AZ26: 0.0885
B27: FT-transformer | C27: =D26/D27-1 -> 21.82824 | D27: =(N27+R27+V27+Z27+AD27+AH27+AL27+AP27+AT27+AX27)/10 -> 0.02585 | E27: =SQRT(((N27-D27)^2+(R27-D27)^2+(V27-D27)^2+(Z27-D27)^2+(AD27-D27)^2+(AH27-D27)^2+(AL27-D27)^2+(AP27-D27)^2+(AT27-D27)^2+(AX27-D27)^2)/10) -> 0.035236891 | F27: =E27/D27 -> 1.3631293 | G27: =(O27+S27+W27+AA27+AE27+AI27+AM27+AQ27+AU27+AY27)/10 -> 0 | H27: =SQRT(((O27-G27)^2+(S27-G27)^2+(W27-G27)^2+(AA27-G27)^2+(AE27-G27)^2+(AI27-G27)^2+(AM27-G27)^2+(AQ27-G27)^2+(AU27-G27)^2+(AY27-G27)^2)/10) -> 0 | I27: =H27/G27 -> #DIV/0! | J27: =(P27+T27+X27+AB27+AF27+AJ27+AN27+AR27+AV27+AZ27)/10 -> 0 | K27: =SQRT(((P27-J27)^2+(T27-J27)^2+(X27-J27)^2+(AB27-J27)^2+(AF27-J27)^2+(AJ27-J27)^2+(AN27-J27)^2+(AR27-J27)^2+(AV27-J27)^2+(AZ27-J27)^2)/10) -> 0 | L27: =K27/J27 -> #DIV/0! | N27: 0.0067 | O27: 0 | P27: 0 | R27: 0.0182 | S27: 0 | T27: 0 | V27: 0.0511 | W27: 0 | X27: 0 | Z27: 0.107 | AA27: 0 | AB27: 0 | AD27: 0.0016 | AE27: 0 | AF27: 0 | AH27: 0.0017 | AI27: 0 | AJ27: 0 | AL27: 0.0682 | AM27: 0 | AN27: 0 | AP27: 0.0013 | AQ27: 0 | AR27: 0 | AT27: 0.001 | AU27: 0 | AV27: 0 | AX27: 0.0017 | AY27: 0 | AZ27: 0
B28: CatBoost | C28: =D26/D28-1 -> -0.16273889 | D28: =(N28+R28+V28+Z28+AD28+AH28+AL28+AP28+AT28+AX28)/10 -> 0.70481 | E28: =SQRT(((N28-D28)^2+(R28-D28)^2+(V28-D28)^2+(Z28-D28)^2+(AD28-D28)^2+(AH28-D28)^2+(AL28-D28)^2+(AP28-D28)^2+(AT28-D28)^2+(AX28-D28)^2)/10) -> 0.040313086 | F28: =E28/D28 -> 0.057197097 | G28: =(O28+S28+W28+AA28+AE28+AI28+AM28+AQ28+AU28+AY28)/10 -> 0.765 | H28: =SQRT(((O28-G28)^2+(S28-G28)^2+(W28-G28)^2+(AA28-G28)^2+(AE28-G28)^2+(AI28-G28)^2+(AM28-G28)^2+(AQ28-G28)^2+(AU28-G28)^2+(AY28-G28)^2)/10) -> 0.01118034 | I28: =H28/G28 -> 0.014614823 | J28: =(P28+T28+X28+AB28+AF28+AJ28+AN28+AR28+AV28+AZ28)/10 -> 0.6575 | K28: =SQRT(((P28-J28)^2+(T28-J28)^2+(X28-J28)^2+(AB28-J28)^2+(AF28-J28)^2+(AJ28-J28)^2+(AN28-J28)^2+(AR28-J28)^2+(AV28-J28)^2+(AZ28-J28)^2)/10) -> 0.047885071 | L28: =K28/J28 -> 0.072829005 | N28: 0.6639 | O28: 0.76 | P28: 0.5914 | R28: 0.6903 | S28: 0.79 | T28: 0.61 | V28: 0.7504 | W28: 0.77 | X28: 0.6937 | Z28: 0.7566 | AA28: 0.77 | AB28: 0.7196 | AD28: 0.665 | AE28: 0.77 | AF28: 0.6696 | AH28: 0.7209 | AI28: 0.75 | AJ28: 0.6522 | AL28: 0.6684 | AM28: 0.76 | AN28: 0.6032 | AP28: 0.6987 | AQ28: 0.76 | AR28: 0.6972 | AT28: 0.7722 | AU28: 0.75 | AV28: 0.7246 | AX28: 0.6617 | AY28: 0.77 | AZ28: 0.6135
B29: SCARF | C29: =D26/D29-1 -> 561.00952 | D29: =(N29+R29+V29+Z29+AD29+AH29+AL29+AP29+AT29+AX29)/10 -> 0.00105 | E29: =SQRT(((N29-D29)^2+(R29-D29)^2+(V29-D29)^2+(Z29-D29)^2+(AD29-D29)^2+(AH29-D29)^2+(AL29-D29)^2+(AP29-D29)^2+(AT29-D29)^2+(AX29-D29)^2)/10) -> 0.00016278821 | F29: =E29/D29 -> 0.15503639 | G29: =(O29+S29+W29+AA29+AE29+AI29+AM29+AQ29+AU29+AY29)/10 -> 0.055 | H29: =SQRT(((O29-G29)^2+(S29-G29)^2+(W29-G29)^2+(AA29-G29)^2+(AE29-G29)^2+(AI29-G29)^2+(AM29-G29)^2+(AQ29-G29)^2+(AU29-G29)^2+(AY29-G29)^2)/10) -> 0.013601471 | I29: =H29/G29 -> 0.24729946 | J29: =(P29+T29+X29+AB29+AF29+AJ29+AN29+AR29+AV29+AZ29)/10 -> 0.00071 | K29: =SQRT(((P29-J29)^2+(T29-J29)^2+(X29-J29)^2+(AB29-J29)^2+(AF29-J29)^2+(AJ29-J29)^2+(AN29-J29)^2+(AR29-J29)^2+(AV29-J29)^2+(AZ29-J29)^2)/10) -> 0.00027 | L29: =K29/J29 -> 0.38028169 | N29: 0.0009 | O29: 0.05 | P29: 0.0005 | R29: 0.0009 | S29: 0.06 | T29: 0.0006 | V29: 0.0011 | W29: 0.07 | X29: 0.0008 | Z29: 0.0013 | AA29: 0.08 | AB29: 0.0014 | AD29: 0.0013 | AE29: 0.06 | AF29: 0.0009 | AH29: 0.0009 | AI29: 0.06 | AJ29: 0.0006 | AL29: 0.0009 | AM29: 0.04 | AN29: 0.0005 | AP29: 0.0011 | AQ29: 0.05 | AR29: 0.0007 | AT29: 0.0012 | AU29: 0.05 | AV29: 0.0007 | AX29: 0.0009 | AY29: 0.03 | AZ29: 0.0004
C31: effect, % | D31: AUPRC | G31: Recall | J31: F1 | N31: AUPRC | O31: For reference | R31: AUPRC | S31: For reference | V31: AUPRC | W31: For reference | Z31: AUPRC | AA31: For reference | AD31: AUPRC | AE31: For reference | AH31: AUPRC | AI31: For reference | AL31: AUPRC | AM31: For reference | AP31: AUPRC | AQ31: For reference | AT31: AUPRC | AU31: For reference | AX31: AUPRC | AY31: For reference
D32: mean | E32: σ | F32: CV | G32: mean | H32: σ | I32: CV | J32: mean | K32: σ | L32: CV | O32: Recall | P32: F1 | S32: Recall | T32: F1 | W32: Recall | X32: F1 | AA32: Recall | AB32: F1 | AE32: Recall | AF32: F1 | AI32: Recall | AJ32: F1 | AM32: Recall | AN32: F1 | AQ32: Recall | AR32: F1 | AU32: Recall | AV32: F1 | AY32: Recall | AZ32: F1
B33: LR | C33: =D34/D33-1 -> -0.13824418 | D33: =(N33+R33+V33+Z33+AD33+AH33+AL33+AP33+AT33+AX33)/10 -> 0.6618 | E33: =SQRT(((N33-D33)^2+(R33-D33)^2+(V33-D33)^2+(Z33-D33)^2+(AD33-D33)^2+(AH33-D33)^2+(AL33-D33)^2+(AP33-D33)^2+(AT33-D33)^2+(AX33-D33)^2)/10) -> 1.110223e-16 | F33: =E33/D33 -> 1.6775809e-16 | G33: =(O33+S33+W33+AA33+AE33+AI33+AM33+AQ33+AU33+AY33)/10 -> 0.88 | H33: =SQRT(((O33-G33)^2+(S33-G33)^2+(W33-G33)^2+(AA33-G33)^2+(AE33-G33)^2+(AI33-G33)^2+(AM33-G33)^2+(AQ33-G33)^2+(AU33-G33)^2+(AY33-G33)^2)/10) -> 1.110223e-16 | I33: =H33/G33 -> 1.2616171e-16 | J33: =(P33+T33+X33+AB33+AF33+AJ33+AN33+AR33+AV33+AZ33)/10 -> 0.1099 | K33: =SQRT(((P33-J33)^2+(T33-J33)^2+(X33-J33)^2+(AB33-J33)^2+(AF33-J33)^2+(AJ33-J33)^2+(AN33-J33)^2+(AR33-J33)^2+(AV33-J33)^2+(AZ33-J33)^2)/10) -> 0 | L33: =K33/J33 -> 0 | N33: 0.6618 | O33: 0.88 | P33: 0.1099 | R33: 0.6618 | S33: 0.88 | T33: 0.1099 | V33: 0.6618 | W33: 0.88 | X33: 0.1099 | Z33: 0.6618 | AA33: 0.88 | AB33: 0.1099 | AD33: 0.6618 | AE33: 0.88 | AF33: 0.1099 | AH33: 0.6618 | AI33: 0.88 | AJ33: 0.1099 | AL33: 0.6618 | AM33: 0.88 | AN33: 0.1099 | AP33: 0.6618 | AQ33: 0.88 | AR33: 0.1099 | AT33: 0.6618 | AU33: 0.88 | AV33: 0.1099 | AX33: 0.6618 | AY33: 0.88 | AZ33: 0.1099
B34: CLT-TAB without CATA and SQP | D34: =(N34+R34+V34+Z34+AD34+AH34+AL34+AP34+AT34+AX34)/10 -> 0.57031 | E34: =SQRT(((N34-D34)^2+(R34-D34)^2+(V34-D34)^2+(Z34-D34)^2+(AD34-D34)^2+(AH34-D34)^2+(AL34-D34)^2+(AP34-D34)^2+(AT34-D34)^2+(AX34-D34)^2)/10) -> 0.094800585 | F34: =E34/D34 -> 0.16622641 | G34: =(O34+S34+W34+AA34+AE34+AI34+AM34+AQ34+AU34+AY34)/10 -> 0.873 | H34: =SQRT(((O34-G34)^2+(S34-G34)^2+(W34-G34)^2+(AA34-G34)^2+(AE34-G34)^2+(AI34-G34)^2+(AM34-G34)^2+(AQ34-G34)^2+(AU34-G34)^2+(AY34-G34)^2)/10) -> 0.014866069 | I34: =H34/G34 -> 0.017028716 | J34: =(P34+T34+X34+AB34+AF34+AJ34+AN34+AR34+AV34+AZ34)/10 -> 0.08891 | K34: =SQRT(((P34-J34)^2+(T34-J34)^2+(X34-J34)^2+(AB34-J34)^2+(AF34-J34)^2+(AJ34-J34)^2+(AN34-J34)^2+(AR34-J34)^2+(AV34-J34)^2+(AZ34-J34)^2)/10) -> 0.010053402 | L34: =K34/J34 -> 0.11307392 | N34: 0.4837 | O34: 0.88 | P34: 0.0943 | R34: 0.5387 | S34: 0.89 | T34: 0.0707 | V34: 0.6329 | W34: 0.87 | X34: 0.083 | Z34: 0.6351 | AA34: 0.88 | AB34: 0.1001 | AD34: 0.6746 | AE34: 0.89 | AF34: 0.0856 | AH34: 0.5447 | AI34: 0.87 | AJ34: 0.0835 | AL34: 0.6271 | AM34: 0.89 | AN34: 0.0895 | AP34: 0.3404 | AQ34: 0.85 | AR34: 0.0899 | AT34: 0.6446 | AU34: 0.85 | AV34: 0.1093 | AX34: 0.5813 | AY34: 0.86 | AZ34: 0.0832
B35: FT-transformer | C35: =D34/D35-1 -> 21.062282 | D35: =(N35+R35+V35+Z35+AD35+AH35+AL35+AP35+AT35+AX35)/10 -> 0.02585 | E35: =SQRT(((N35-D35)^2+(R35-D35)^2+(V35-D35)^2+(Z35-D35)^2+(AD35-D35)^2+(AH35-D35)^2+(AL35-D35)^2+(AP35-D35)^2+(AT35-D35)^2+(AX35-D35)^2)/10) -> 0.035236891 | F35: =E35/D35 -> 1.3631293 | G35: =(O35+S35+W35+AA35+AE35+AI35+AM35+AQ35+AU35+AY35)/10 -> 0 | H35: =SQRT(((O35-G35)^2+(S35-G35)^2+(W35-G35)^2+(AA35-G35)^2+(AE35-G35)^2+(AI35-G35)^2+(AM35-G35)^2+(AQ35-G35)^2+(AU35-G35)^2+(AY35-G35)^2)/10) -> 0 | I35: =H35/G35 -> #DIV/0! | J35: =(P35+T35+X35+AB35+AF35+AJ35+AN35+AR35+AV35+AZ35)/10 -> 0 | K35: =SQRT(((P35-J35)^2+(T35-J35)^2+(X35-J35)^2+(AB35-J35)^2+(AF35-J35)^2+(AJ35-J35)^2+(AN35-J35)^2+(AR35-J35)^2+(AV35-J35)^2+(AZ35-J35)^2)/10) -> 0 | L35: =K35/J35 -> #DIV/0! | N35: 0.0067 | O35: 0 | P35: 0 | R35: 0.0182 | S35: 0 | T35: 0 | V35: 0.0511 | W35: 0 | X35: 0 | Z35: 0.107 | AA35: 0 | AB35: 0 | AD35: 0.0016 | AE35: 0 | AF35: 0 | AH35: 0.0017 | AI35: 0 | AJ35: 0 | AL35: 0.0682 | AM35: 0 | AN35: 0 | AP35: 0.0013 | AQ35: 0 | AR35: 0 | AT35: 0.001 | AU35: 0 | AV35: 0 | AX35: 0.0017 | AY35: 0 | AZ35: 0
B36: CatBoost | C36: =D34/D36-1 -> -0.19083157 | D36: =(N36+R36+V36+Z36+AD36+AH36+AL36+AP36+AT36+AX36)/10 -> 0.70481 | E36: =SQRT(((N36-D36)^2+(R36-D36)^2+(V36-D36)^2+(Z36-D36)^2+(AD36-D36)^2+(AH36-D36)^2+(AL36-D36)^2+(AP36-D36)^2+(AT36-D36)^2+(AX36-D36)^2)/10) -> 0.040313086 | F36: =E36/D36 -> 0.057197097 | G36: =(O36+S36+W36+AA36+AE36+AI36+AM36+AQ36+AU36+AY36)/10 -> 0.765 | H36: =SQRT(((O36-G36)^2+(S36-G36)^2+(W36-G36)^2+(AA36-G36)^2+(AE36-G36)^2+(AI36-G36)^2+(AM36-G36)^2+(AQ36-G36)^2+(AU36-G36)^2+(AY36-G36)^2)/10) -> 0.01118034 | I36: =H36/G36 -> 0.014614823 | J36: =(P36+T36+X36+AB36+AF36+AJ36+AN36+AR36+AV36+AZ36)/10 -> 0.6575 | K36: =SQRT(((P36-J36)^2+(T36-J36)^2+(X36-J36)^2+(AB36-J36)^2+(AF36-J36)^2+(AJ36-J36)^2+(AN36-J36)^2+(AR36-J36)^2+(AV36-J36)^2+(AZ36-J36)^2)/10) -> 0.047885071 | L36: =K36/J36 -> 0.072829005 | N36: 0.6639 | O36: 0.76 | P36: 0.5914 | R36: 0.6903 | S36: 0.79 | T36: 0.61 | V36: 0.7504 | W36: 0.77 | X36: 0.6937 | Z36: 0.7566 | AA36: 0.77 | AB36: 0.7196 | AD36: 0.665 | AE36: 0.77 | AF36: 0.6696 | AH36: 0.7209 | AI36: 0.75 | AJ36: 0.6522 | AL36: 0.6684 | AM36: 0.76 | AN36: 0.6032 | AP36: 0.6987 | AQ36: 0.76 | AR36: 0.6972 | AT36: 0.7722 | AU36: 0.75 | AV36: 0.7246 | AX36: 0.6617 | AY36: 0.77 | AZ36: 0.6135
B37: SCARF | C37: =D34/D37-1 -> 542.15238 | D37: =(N37+R37+V37+Z37+AD37+AH37+AL37+AP37+AT37+AX37)/10 -> 0.00105 | E37: =SQRT(((N37-D37)^2+(R37-D37)^2+(V37-D37)^2+(Z37-D37)^2+(AD37-D37)^2+(AH37-D37)^2+(AL37-D37)^2+(AP37-D37)^2+(AT37-D37)^2+(AX37-D37)^2)/10) -> 0.00016278821 | F37: =E37/D37 -> 0.15503639 | G37: =(O37+S37+W37+AA37+AE37+AI37+AM37+AQ37+AU37+AY37)/10 -> 0.055 | H37: =SQRT(((O37-G37)^2+(S37-G37)^2+(W37-G37)^2+(AA37-G37)^2+(AE37-G37)^2+(AI37-G37)^2+(AM37-G37)^2+(AQ37-G37)^2+(AU37-G37)^2+(AY37-G37)^2)/10) -> 0.013601471 | I37: =H37/G37 -> 0.24729946 | J37: =(P37+T37+X37+AB37+AF37+AJ37+AN37+AR37+AV37+AZ37)/10 -> 0.00071 | K37: =SQRT(((P37-J37)^2+(T37-J37)^2+(X37-J37)^2+(AB37-J37)^2+(AF37-J37)^2+(AJ37-J37)^2+(AN37-J37)^2+(AR37-J37)^2+(AV37-J37)^2+(AZ37-J37)^2)/10) -> 0.00027 | L37: =K37/J37 -> 0.38028169 | N37: 0.0009 | O37: 0.05 | P37: 0.0005 | R37: 0.0009 | S37: 0.06 | T37: 0.0006 | V37: 0.0011 | W37: 0.07 | X37: 0.0008 | Z37: 0.0013 | AA37: 0.08 | AB37: 0.0014 | AD37: 0.0013 | AE37: 0.06 | AF37: 0.0009 | AH37: 0.0009 | AI37: 0.06 | AJ37: 0.0006 | AL37: 0.0009 | AM37: 0.04 | AN37: 0.0005 | AP37: 0.0011 | AQ37: 0.05 | AR37: 0.0007 | AT37: 0.0012 | AU37: 0.05 | AV37: 0.0007 | AX37: 0.0009 | AY37: 0.03 | AZ37: 0.0004

Sheet Road_safety
B1: Overview
B2: The Road Safety dataset is a widely used benchmark for classification and traffic accident analysis, compiled from official police reports on personal injury road accidents in Great Britain. The dataset is part of a collection managed by the UK Department for Transport, with records spanning from 1979 up to 2015. It contains detailed information about the circumstances of each accident, including: - Accident characteristics: date, time, location, weather conditions, road surface, and light conditions. - Vehicle information: type of vehicle, manoeuvre, and whether the vehicle was left-hand drive. - Casualty and driver details: age and sex of driver and casualty, and the severity of the injury. Because the dataset is entirely based on real-world reported incidents, it includes a mix of numerical and high-cardinality categorical features. It is often used to benchmark models that handle both types of data, such as tree-based ensembles, logistic regression, and various deep learning architectures.
B3: We used the Road Safety dataset, which contains 111 419 instances with a 50,0 % anomaly rate. It comprises 25 numerical and 4 categorical features (Removed: 'Vehicle_Reference_df_res', 'Vehicle_Reference_df', 'Casualty_Reference'. Target: 'Sex_of_Driver'). The data were used after preprocessing (missing values, duplicates, and constant features were removed). F1 and Recall scores were obtained with a threshold of 0.5. We used 200 instances for finetuning, of which 100 were anomalies, and the same number (200 instances, 100 anomalies) for testing.
B5: Random AUPRC | C5: 0.5 | N5: Seed
G6: For reference | N6: 42 | R6: 43 | V6: 44 | Z6: 45 | AD6: 46 | AH6: 47 | AL6: 48 | AP6: 49 | AT6: 50 | AX6: 51
C7: effect, % | D7: AUPRC | G7: Recall | J7: F1 | N7: AUPRC | O7: For reference | R7: AUPRC | S7: For reference | V7: AUPRC | W7: For reference | Z7: AUPRC | AA7: For reference | AD7: AUPRC | AE7: For reference | AH7: AUPRC | AI7: For reference | AL7: AUPRC | AM7: For reference | AP7: AUPRC | AQ7: For reference | AT7: AUPRC | AU7: For reference | AX7: AUPRC | AY7: For reference
D8: mean | E8: σ | F8: CV | G8: mean | H8: σ | I8: CV | J8: mean | K8: σ | L8: CV | O8: Recall | P8: F1 | S8: Recall | T8: F1 | W8: Recall | X8: F1 | AA8: Recall | AB8: F1 | AE8: Recall | AF8: F1 | AI8: Recall | AJ8: F1 | AM8: Recall | AN8: F1 | AQ8: Recall | AR8: F1 | AU8: Recall | AV8: F1 | AY8: Recall | AZ8: F1
B9: LR | C9: =D10/D9-1 -> 0.076698985 | D9: =(N9+R9+V9+Z9+AD9+AH9+AL9+AP9+AT9+AX9)/10 -> 0.65907 | E9: =SQRT(((N9-D9)^2+(R9-D9)^2+(V9-D9)^2+(Z9-D9)^2+(AD9-D9)^2+(AH9-D9)^2+(AL9-D9)^2+(AP9-D9)^2+(AT9-D9)^2+(AX9-D9)^2)/10) -> 0.0027996607 | F9: =E9/D9 -> 0.0042478958 | G9: =(O9+S9+W9+AA9+AE9+AI9+AM9+AQ9+AU9+AY9)/10 -> 0.598 | H9: =SQRT(((O9-G9)^2+(S9-G9)^2+(W9-G9)^2+(AA9-G9)^2+(AE9-G9)^2+(AI9-G9)^2+(AM9-G9)^2+(AQ9-G9)^2+(AU9-G9)^2+(AY9-G9)^2)/10) -> 0.006 | I9: =H9/G9 -> 0.010033445 | J9: =(P9+T9+X9+AB9+AF9+AJ9+AN9+AR9+AV9+AZ9)/10 -> 0.59944 | K9: =SQRT(((P9-J9)^2+(T9-J9)^2+(X9-J9)^2+(AB9-J9)^2+(AF9-J9)^2+(AJ9-J9)^2+(AN9-J9)^2+(AR9-J9)^2+(AV9-J9)^2+(AZ9-J9)^2)/10) -> 0.008760274 | L9: =K9/J9 -> 0.014614096 | N9: 0.6544 | O9: 0.58 | P9: 0.5734 | R9: 0.6609 | S9: 0.6 | T9: 0.603 | V9: 0.6609 | W9: 0.6 | X9: 0.603 | Z9: 0.6609 | AA9: 0.6 | AB9: 0.603 | AD9: 0.655 | AE9: 0.6 | AF9: 0.6 | AH9: 0.655 | AI9: 0.6 | AJ9: 0.6 | AL9: 0.6609 | AM9: 0.6 | AN9: 0.603 | AP9: 0.6609 | AQ9: 0.6 | AR9: 0.603 | AT9: 0.6609 | AU9: 0.6 | AV9: 0.603 | AX9: 0.6609 | AY9: 0.6 | AZ9: 0.603
B10: CLT-TAB | D10: =(N10+R10+V10+Z10+AD10+AH10+AL10+AP10+AT10+AX10)/10 -> 0.70962 | E10: =SQRT(((N10-D10)^2+(R10-D10)^2+(V10-D10)^2+(Z10-D10)^2+(AD10-D10)^2+(AH10-D10)^2+(AL10-D10)^2+(AP10-D10)^2+(AT10-D10)^2+(AX10-D10)^2)/10) -> 0.015283965 | F10: =E10/D10 -> 0.021538239 | G10: =(O10+S10+W10+AA10+AE10+AI10+AM10+AQ10+AU10+AY10)/10 -> 0.623 | H10: =SQRT(((O10-G10)^2+(S10-G10)^2+(W10-G10)^2+(AA10-G10)^2+(AE10-G10)^2+(AI10-G10)^2+(AM10-G10)^2+(AQ10-G10)^2+(AU10-G10)^2+(AY10-G10)^2)/10) -> 0.032878564 | I10: =H10/G10 -> 0.052774582 | J10: =(P10+T10+X10+AB10+AF10+AJ10+AN10+AR10+AV10+AZ10)/10 -> 0.61626 | K10: =SQRT(((P10-J10)^2+(T10-J10)^2+(X10-J10)^2+(AB10-J10)^2+(AF10-J10)^2+(AJ10-J10)^2+(AN10-J10)^2+(AR10-J10)^2+(AV10-J10)^2+(AZ10-J10)^2)/10) -> 0.023372043 | L10: =K10/J10 -> 0.037925621 | N10: 0.7052 | O10: 0.58 | P10: 0.5829 | R10: 0.7176 | S10: 0.63 | T10: 0.6238 | V10: 0.6867 | W10: 0.66 | X10: 0.6226 | Z10: 0.7057 | AA10: 0.66 | AB10: 0.6502 | AD10: 0.7211 | AE10: 0.58 | AF10: 0.5949 | AH10: 0.7333 | AI10: 0.59 | AJ10: 0.596 | AL10: 0.6895 | AM10: 0.65 | AN10: 0.628 | AP10: 0.6949 | AQ10: 0.59 | AR10: 0.59 | AT10: 0.7293 | AU10: 0.66 | AV10: 0.6535 | AX10: 0.7129 | AY10: 0.63 | AZ10: 0.6207
B11: FT-transformer | C11: =D10/D11-1 -> 0.050930794 | D11: =(N11+R11+V11+Z11+AD11+AH11+AL11+AP11+AT11+AX11)/10 -> 0.67523 | E11: =SQRT(((N11-D11)^2+(R11-D11)^2+(V11-D11)^2+(Z11-D11)^2+(AD11-D11)^2+(AH11-D11)^2+(AL11-D11)^2+(AP11-D11)^2+(AT11-D11)^2+(AX11-D11)^2)/10) -> 0.033669305 | F11: =E11/D11 -> 0.049863461 | G11: =(O11+S11+W11+AA11+AE11+AI11+AM11+AQ11+AU11+AY11)/10 -> 0.66 | H11: =SQRT(((O11-G11)^2+(S11-G11)^2+(W11-G11)^2+(AA11-G11)^2+(AE11-G11)^2+(AI11-G11)^2+(AM11-G11)^2+(AQ11-G11)^2+(AU11-G11)^2+(AY11-G11)^2)/10) -> 0.030983867 | I11: =H11/G11 -> 0.046945253 | J11: =(P11+T11+X11+AB11+AF11+AJ11+AN11+AR11+AV11+AZ11)/10 -> 0.64449 | K11: =SQRT(((P11-J11)^2+(T11-J11)^2+(X11-J11)^2+(AB11-J11)^2+(AF11-J11)^2+(AJ11-J11)^2+(AN11-J11)^2+(AR11-J11)^2+(AV11-J11)^2+(AZ11-J11)^2)/10) -> 0.024539374 | L11: =K11/J11 -> 0.038075648 | N11: 0.6555 | O11: 0.66 | P11: 0.6471 | R11: 0.7301 | S11: 0.72 | T11: 0.6923 | V11: 0.6765 | W11: 0.66 | X11: 0.6439 | Z11: 0.6912 | AA11: 0.63 | AB11: 0.6176 | AD11: 0.6329 | AE11: 0.62 | AF11: 0.6108 | AH11: 0.6132 | AI11: 0.68 | AJ11: 0.6239 | AL11: 0.6949 | AM11: 0.67 | AN11: 0.6601 | AP11: 0.6567 | AQ11: 0.61 | AR11: 0.6224 | AT11: 0.6977 | AU11: 0.68 | AV11: 0.6634 | AX11: 0.7036 | AY11: 0.67 | AZ11: 0.6634
B12: CatBoost | C12: =D10/D12-1 -> 0.014714083 | D12: =(N12+R12+V12+Z12+AD12+AH12+AL12+AP12+AT12+AX12)/10 -> 0.69933 | E12: =SQRT(((N12-D12)^2+(R12-D12)^2+(V12-D12)^2+(Z12-D12)^2+(AD12-D12)^2+(AH12-D12)^2+(AL12-D12)^2+(AP12-D12)^2+(AT12-D12)^2+(AX12-D12)^2)/10) -> 0.011061017 | F12: =E12/D12 -> 0.015816592 | G12: =(O12+S12+W12+AA12+AE12+AI12+AM12+AQ12+AU12+AY12)/10 -> 0.661 | H12: =SQRT(((O12-G12)^2+(S12-G12)^2+(W12-G12)^2+(AA12-G12)^2+(AE12-G12)^2+(AI12-G12)^2+(AM12-G12)^2+(AQ12-G12)^2+(AU12-G12)^2+(AY12-G12)^2)/10) -> 0.037 | I12: =H12/G12 -> 0.055975794 | J12: =(P12+T12+X12+AB12+AF12+AJ12+AN12+AR12+AV12+AZ12)/10 -> 0.65703 | K12: =SQRT(((P12-J12)^2+(T12-J12)^2+(X12-J12)^2+(AB12-J12)^2+(AF12-J12)^2+(AJ12-J12)^2+(AN12-J12)^2+(AR12-J12)^2+(AV12-J12)^2+(AZ12-J12)^2)/10) -> 0.021986407 | L12: =K12/J12 -> 0.033463323 | N12: 0.7078 | O12: 0.65 | P12: 0.628 | R12: 0.6934 | S12: 0.66 | T12: 0.6502 | V12: 0.7166 | W12: 0.65 | X12: 0.6566 | Z12: 0.6798 | AA12: 0.65 | AB12: 0.6468 | AD12: 0.6883 | AE12: 0.72 | AF12: 0.699 | AH12: 0.6927 | AI12: 0.62 | AJ12: 0.6327 | AL12: 0.707 | AM12: 0.59 | AN12: 0.6344 | AP12: 0.7131 | AQ12: 0.7 | AR12: 0.6763 | AT12: 0.7 | AU12: 0.67 | AV12: 0.6667 | AX12: 0.6946 | AY12: 0.7 | AZ12: 0.6796
B13: SCARF | C13: =D10/D13-1 -> 0.33683735 | D13: =(N13+R13+V13+Z13+AD13+AH13+AL13+AP13+AT13+AX13)/10 -> 0.53082 | E13: =SQRT(((N13-D13)^2+(R13-D13)^2+(V13-D13)^2+(Z13-D13)^2+(AD13-D13)^2+(AH13-D13)^2+(AL13-D13)^2+(AP13-D13)^2+(AT13-D13)^2+(AX13-D13)^2)/10) -> 0.018638069 | F13: =E13/D13 -> 0.035111843 | G13: =(O13+S13+W13+AA13+AE13+AI13+AM13+AQ13+AU13+AY13)/10 -> 0.528 | H13: =SQRT(((O13-G13)^2+(S13-G13)^2+(W13-G13)^2+(AA13-G13)^2+(AE13-G13)^2+(AI13-G13)^2+(AM13-G13)^2+(AQ13-G13)^2+(AU13-G13)^2+(AY13-G13)^2)/10) -> 0.033406586 | I13: =H13/G13 -> 0.06327005 | J13: =(P13+T13+X13+AB13+AF13+AJ13+AN13+AR13+AV13+AZ13)/10 -> 0.53459 | K13: =SQRT(((P13-J13)^2+(T13-J13)^2+(X13-J13)^2+(AB13-J13)^2+(AF13-J13)^2+(AJ13-J13)^2+(AN13-J13)^2+(AR13-J13)^2+(AV13-J13)^2+(AZ13-J13)^2)/10) -> 0.025728717 | L13: =K13/J13 -> 0.048127944 | N13: 0.5357 | O13: 0.49 | P13: 0.5078 | R13: 0.4968 | S13: 0.49 | T13: 0.4975 | V13: 0.5328 | W13: 0.51 | X13: 0.5231 | Z13: 0.5491 | AA13: 0.57 | AB13: 0.57 | AD13: 0.5229 | AE13: 0.56 | AF13: 0.56 | AH13: 0.5183 | AI13: 0.51 | AJ13: 0.5204 | AL13: 0.5324 | AM13: 0.56 | AN13: 0.56 | AP13: 0.5099 | AQ13: 0.48 | AR13: 0.5026 | AT13: 0.5626 | AU13: 0.56 | AV13: 0.5517 | AX13: 0.5477 | AY13: 0.55 | AZ13: 0.5528
C15: effect, % | D15: AUPRC | G15: Recall | J15: F1 | N15: AUPRC | O15: For reference | R15: AUPRC | S15: For reference | V15: AUPRC | W15: For reference | Z15: AUPRC | AA15: For reference | AD15: AUPRC | AE15: For reference | AH15: AUPRC | AI15: For reference | AL15: AUPRC | AM15: For reference | AP15: AUPRC | AQ15: For reference | AT15: AUPRC | AU15: For reference | AX15: AUPRC | AY15: For reference
D16: mean | E16: σ | F16: CV | G16: mean | H16: σ | I16: CV | J16: mean | K16: σ | L16: CV | O16: Recall | P16: F1 | S16: Recall | T16: F1 | W16: Recall | X16: F1 | AA16: Recall | AB16: F1 | AE16: Recall | AF16: F1 | AI16: Recall | AJ16: F1 | AM16: Recall | AN16: F1 | AQ16: Recall | AR16: F1 | AU16: Recall | AV16: F1 | AY16: Recall | AZ16: F1
B17: LR | C17: =D18/D17-1 -> 0.060099838 | D17: =(N17+R17+V17+Z17+AD17+AH17+AL17+AP17+AT17+AX17)/10 -> 0.65907 | E17: =SQRT(((N17-D17)^2+(R17-D17)^2+(V17-D17)^2+(Z17-D17)^2+(AD17-D17)^2+(AH17-D17)^2+(AL17-D17)^2+(AP17-D17)^2+(AT17-D17)^2+(AX17-D17)^2)/10) -> 0.0027996607 | F17: =E17/D17 -> 0.0042478958 | G17: =(O17+S17+W17+AA17+AE17+AI17+AM17+AQ17+AU17+AY17)/10 -> 0.598 | H17: =SQRT(((O17-G17)^2+(S17-G17)^2+(W17-G17)^2+(AA17-G17)^2+(AE17-G17)^2+(AI17-G17)^2+(AM17-G17)^2+(AQ17-G17)^2+(AU17-G17)^2+(AY17-G17)^2)/10) -> 0.006 | I17: =H17/G17 -> 0.010033445 | J17: =(P17+T17+X17+AB17+AF17+AJ17+AN17+AR17+AV17+AZ17)/10 -> 0.59944 | K17: =SQRT(((P17-J17)^2+(T17-J17)^2+(X17-J17)^2+(AB17-J17)^2+(AF17-J17)^2+(AJ17-J17)^2+(AN17-J17)^2+(AR17-J17)^2+(AV17-J17)^2+(AZ17-J17)^2)/10) -> 0.008760274 | L17: =K17/J17 -> 0.014614096 | N17: 0.6544 | O17: 0.58 | P17: 0.5734 | R17: 0.6609 | S17: 0.6 | T17: 0.603 | V17: 0.6609 | W17: 0.6 | X17: 0.603 | Z17: 0.6609 | AA17: 0.6 | AB17: 0.603 | AD17: 0.655 | AE17: 0.6 | AF17: 0.6 | AH17: 0.655 | AI17: 0.6 | AJ17: 0.6 | AL17: 0.6609 | AM17: 0.6 | AN17: 0.603 | AP17: 0.6609 | AQ17: 0.6 | AR17: 0.603 | AT17: 0.6609 | AU17: 0.6 | AV17: 0.603 | AX17: 0.6609 | AY17: 0.6 | AZ17: 0.603
B18: CLT-TAB without CATA | D18: =(N18+R18+V18+Z18+AD18+AH18+AL18+AP18+AT18+AX18)/10 -> 0.69868 | E18: =SQRT(((N18-D18)^2+(R18-D18)^2+(V18-D18)^2+(Z18-D18)^2+(AD18-D18)^2+(AH18-D18)^2+(AL18-D18)^2+(AP18-D18)^2+(AT18-D18)^2+(AX18-D18)^2)/10) -> 0.0082888841 | F18: =E18/D18 -> 0.011863634 | G18: =(O18+S18+W18+AA18+AE18+AI18+AM18+AQ18+AU18+AY18)/10 -> 0.61 | H18: =SQRT(((O18-G18)^2+(S18-G18)^2+(W18-G18)^2+(AA18-G18)^2+(AE18-G18)^2+(AI18-G18)^2+(AM18-G18)^2+(AQ18-G18)^2+(AU18-G18)^2+(AY18-G18)^2)/10) -> 0.032249031 | I18: =H18/G18 -> 0.052867264 | J18: =(P18+T18+X18+AB18+AF18+AJ18+AN18+AR18+AV18+AZ18)/10 -> 0.61111 | K18: =SQRT(((P18-J18)^2+(T18-J18)^2+(X18-J18)^2+(AB18-J18)^2+(AF18-J18)^2+(AJ18-J18)^2+(AN18-J18)^2+(AR18-J18)^2+(AV18-J18)^2+(AZ18-J18)^2)/10) -> 0.020631551 | L18: =K18/J18 -> 0.033760781 | N18: 0.6884 | O18: 0.56 | P18: 0.5803 | R18: 0.6981 | S18: 0.62 | T18: 0.6139 | V18: 0.6881 | W18: 0.58 | X18: 0.5918 | Z18: 0.684 | AA18: 0.63 | AB18: 0.63 | AD18: 0.7016 | AE18: 0.58 | AF18: 0.5945 | AH18: 0.7053 | AI18: 0.64 | AJ18: 0.6368 | AL18: 0.7042 | AM18: 0.62 | AN18: 0.6139 | AP18: 0.7019 | AQ18: 0.62 | AR18: 0.6169 | AT18: 0.7084 | AU18: 0.67 | AV18: 0.6442 | AX18: 0.7068 | AY18: 0.58 | AZ18: 0.5888
B19: FT-transformer | C19: =D18/D19-1 -> 0.034728907 | D19: =(N19+R19+V19+Z19+AD19+AH19+AL19+AP19+AT19+AX19)/10 -> 0.67523 | E19: =SQRT(((N19-D19)^2+(R19-D19)^2+(V19-D19)^2+(Z19-D19)^2+(AD19-D19)^2+(AH19-D19)^2+(AL19-D19)^2+(AP19-D19)^2+(AT19-D19)^2+(AX19-D19)^2)/10) -> 0.033669305 | F19: =E19/D19 -> 0.049863461 | G19: =(O19+S19+W19+AA19+AE19+AI19+AM19+AQ19+AU19+AY19)/10 -> 0.66 | H19: =SQRT(((O19-G19)^2+(S19-G19)^2+(W19-G19)^2+(AA19-G19)^2+(AE19-G19)^2+(AI19-G19)^2+(AM19-G19)^2+(AQ19-G19)^2+(AU19-G19)^2+(AY19-G19)^2)/10) -> 0.030983867 | I19: =H19/G19 -> 0.046945253 | J19: =(P19+T19+X19+AB19+AF19+AJ19+AN19+AR19+AV19+AZ19)/10 -> 0.64449 | K19: =SQRT(((P19-J19)^2+(T19-J19)^2+(X19-J19)^2+(AB19-J19)^2+(AF19-J19)^2+(AJ19-J19)^2+(AN19-J19)^2+(AR19-J19)^2+(AV19-J19)^2+(AZ19-J19)^2)/10) -> 0.024539374 | L19: =K19/J19 -> 0.038075648 | N19: 0.6555 | O19: 0.66 | P19: 0.6471 | R19: 0.7301 | S19: 0.72 | T19: 0.6923 | V19: 0.6765 | W19: 0.66 | X19: 0.6439 | Z19: 0.6912 | AA19: 0.63 | AB19: 0.6176 | AD19: 0.6329 | AE19: 0.62 | AF19: 0.6108 | AH19: 0.6132 | AI19: 0.68 | AJ19: 0.6239 | AL19: 0.6949 | AM19: 0.67 | AN19: 0.6601 | AP19: 0.6567 | AQ19: 0.61 | AR19: 0.6224 | AT19: 0.6977 | AU19: 0.68 | AV19: 0.6634 | AX19: 0.7036 | AY19: 0.67 | AZ19: 0.6634
B20: CatBoost | C20: =D18/D20-1 -> -0.00092946106 | D20: =(N20+R20+V20+Z20+AD20+AH20+AL20+AP20+AT20+AX20)/10 -> 0.69933 | E20: =SQRT(((N20-D20)^2+(R20-D20)^2+(V20-D20)^2+(Z20-D20)^2+(AD20-D20)^2+(AH20-D20)^2+(AL20-D20)^2+(AP20-D20)^2+(AT20-D20)^2+(AX20-D20)^2)/10) -> 0.011061017 | F20: =E20/D20 -> 0.015816592 | G20: =(O20+S20+W20+AA20+AE20+AI20+AM20+AQ20+AU20+AY20)/10 -> 0.661 | H20: =SQRT(((O20-G20)^2+(S20-G20)^2+(W20-G20)^2+(AA20-G20)^2+(AE20-G20)^2+(AI20-G20)^2+(AM20-G20)^2+(AQ20-G20)^2+(AU20-G20)^2+(AY20-G20)^2)/10) -> 0.037 | I20: =H20/G20 -> 0.055975794 | J20: =(P20+T20+X20+AB20+AF20+AJ20+AN20+AR20+AV20+AZ20)/10 -> 0.65703 | K20: =SQRT(((P20-J20)^2+(T20-J20)^2+(X20-J20)^2+(AB20-J20)^2+(AF20-J20)^2+(AJ20-J20)^2+(AN20-J20)^2+(AR20-J20)^2+(AV20-J20)^2+(AZ20-J20)^2)/10) -> 0.021986407 | L20: =K20/J20 -> 0.033463323 | N20: 0.7078 | O20: 0.65 | P20: 0.628 | R20: 0.6934 | S20: 0.66 | T20: 0.6502 | V20: 0.7166 | W20: 0.65 | X20: 0.6566 | Z20: 0.6798 | AA20: 0.65 | AB20: 0.6468 | AD20: 0.6883 | AE20: 0.72 | AF20: 0.699 | AH20: 0.6927 | AI20: 0.62 | AJ20: 0.6327 | AL20: 0.707 | AM20: 0.59 | AN20: 0.6344 | AP20: 0.7131 | AQ20: 0.7 | AR20: 0.6763 | AT20: 0.7 | AU20: 0.67 | AV20: 0.6667 | AX20: 0.6946 | AY20: 0.7 | AZ20: 0.6796
B21: SCARF | C21: =D18/D21-1 -> 0.31622772 | D21: =(N21+R21+V21+Z21+AD21+AH21+AL21+AP21+AT21+AX21)/10 -> 0.53082 | E21: =SQRT(((N21-D21)^2+(R21-D21)^2+(V21-D21)^2+(Z21-D21)^2+(AD21-D21)^2+(AH21-D21)^2+(AL21-D21)^2+(AP21-D21)^2+(AT21-D21)^2+(AX21-D21)^2)/10) -> 0.018638069 | F21: =E21/D21 -> 0.035111843 | G21: =(O21+S21+W21+AA21+AE21+AI21+AM21+AQ21+AU21+AY21)/10 -> 0.528 | H21: =SQRT(((O21-G21)^2+(S21-G21)^2+(W21-G21)^2+(AA21-G21)^2+(AE21-G21)^2+(AI21-G21)^2+(AM21-G21)^2+(AQ21-G21)^2+(AU21-G21)^2+(AY21-G21)^2)/10) -> 0.033406586 | I21: =H21/G21 -> 0.06327005 | J21: =(P21+T21+X21+AB21+AF21+AJ21+AN21+AR21+AV21+AZ21)/10 -> 0.53459 | K21: =SQRT(((P21-J21)^2+(T21-J21)^2+(X21-J21)^2+(AB21-J21)^2+(AF21-J21)^2+(AJ21-J21)^2+(AN21-J21)^2+(AR21-J21)^2+(AV21-J21)^2+(AZ21-J21)^2)/10) -> 0.025728717 | L21: =K21/J21 -> 0.048127944 | N21: 0.5357 | O21: 0.49 | P21: 0.5078 | R21: 0.4968 | S21: 0.49 | T21: 0.4975 | V21: 0.5328 | W21: 0.51 | X21: 0.5231 | Z21: 0.5491 | AA21: 0.57 | AB21: 0.57 | AD21: 0.5229 | AE21: 0.56 | AF21: 0.56 | AH21: 0.5183 | AI21: 0.51 | AJ21: 0.5204 | AL21: 0.5324 | AM21: 0.56 | AN21: 0.56 | AP21: 0.5099 | AQ21: 0.48 | AR21: 0.5026 | AT21: 0.5626 | AU21: 0.56 | AV21: 0.5517 | AX21: 0.5477 | AY21: 0.55 | AZ21: 0.5528
C23: effect, % | D23: AUPRC | G23: Recall | J23: F1 | N23: AUPRC | O23: For reference | R23: AUPRC | S23: For reference | V23: AUPRC | W23: For reference | Z23: AUPRC | AA23: For reference | AD23: AUPRC | AE23: For reference | AH23: AUPRC | AI23: For reference | AL23: AUPRC | AM23: For reference | AP23: AUPRC | AQ23: For reference | AT23: AUPRC | AU23: For reference | AX23: AUPRC | AY23: For reference
D24: mean | E24: σ | F24: CV | G24: mean | H24: σ | I24: CV | J24: mean | K24: σ | L24: CV | O24: Recall | P24: F1 | S24: Recall | T24: F1 | W24: Recall | X24: F1 | AA24: Recall | AB24: F1 | AE24: Recall | AF24: F1 | AI24: Recall | AJ24: F1 | AM24: Recall | AN24: F1 | AQ24: Recall | AR24: F1 | AU24: Recall | AV24: F1 | AY24: Recall | AZ24: F1
B25: LR | C25: =D26/D25-1 -> 0.06566829 | D25: =(N25+R25+V25+Z25+AD25+AH25+AL25+AP25+AT25+AX25)/10 -> 0.65907 | E25: =SQRT(((N25-D25)^2+(R25-D25)^2+(V25-D25)^2+(Z25-D25)^2+(AD25-D25)^2+(AH25-D25)^2+(AL25-D25)^2+(AP25-D25)^2+(AT25-D25)^2+(AX25-D25)^2)/10) -> 0.0027996607 | F25: =E25/D25 -> 0.0042478958 | G25: =(O25+S25+W25+AA25+AE25+AI25+AM25+AQ25+AU25+AY25)/10 -> 0.598 | H25: =SQRT(((O25-G25)^2+(S25-G25)^2+(W25-G25)^2+(AA25-G25)^2+(AE25-G25)^2+(AI25-G25)^2+(AM25-G25)^2+(AQ25-G25)^2+(AU25-G25)^2+(AY25-G25)^2)/10) -> 0.006 | I25: =H25/G25 -> 0.010033445 | J25: =(P25+T25+X25+AB25+AF25+AJ25+AN25+AR25+AV25+AZ25)/10 -> 0.59944 | K25: =SQRT(((P25-J25)^2+(T25-J25)^2+(X25-J25)^2+(AB25-J25)^2+(AF25-J25)^2+(AJ25-J25)^2+(AN25-J25)^2+(AR25-J25)^2+(AV25-J25)^2+(AZ25-J25)^2)/10) -> 0.008760274 | L25: =K25/J25 -> 0.014614096 | N25: 0.6544 | O25: 0.58 | P25: 0.5734 | R25: 0.6609 | S25: 0.6 | T25: 0.603 | V25: 0.6609 | W25: 0.6 | X25: 0.603 | Z25: 0.6609 | AA25: 0.6 | AB25: 0.603 | AD25: 0.655 | AE25: 0.6 | AF25: 0.6 | AH25: 0.655 | AI25: 0.6 | AJ25: 0.6 | AL25: 0.6609 | AM25: 0.6 | AN25: 0.603 | AP25: 0.6609 | AQ25: 0.6 | AR25: 0.603 | AT25: 0.6609 | AU25: 0.6 | AV25: 0.603 | AX25: 0.6609 | AY25: 0.6 | AZ25: 0.603
B26: CLT-TAB without SQP | D26: =(N26+R26+V26+Z26+AD26+AH26+AL26+AP26+AT26+AX26)/10 -> 0.70235 | E26: =SQRT(((N26-D26)^2+(R26-D26)^2+(V26-D26)^2+(Z26-D26)^2+(AD26-D26)^2+(AH26-D26)^2+(AL26-D26)^2+(AP26-D26)^2+(AT26-D26)^2+(AX26-D26)^2)/10) -> 0.013324958 | F26: =E26/D26 -> 0.018971962 | G26: =(O26+S26+W26+AA26+AE26+AI26+AM26+AQ26+AU26+AY26)/10 -> 0.623 | H26: =SQRT(((O26-G26)^2+(S26-G26)^2+(W26-G26)^2+(AA26-G26)^2+(AE26-G26)^2+(AI26-G26)^2+(AM26-G26)^2+(AQ26-G26)^2+(AU26-G26)^2+(AY26-G26)^2)/10) -> 0.027586228 | I26: =H26/G26 -> 0.04427966 | J26: =(P26+T26+X26+AB26+AF26+AJ26+AN26+AR26+AV26+AZ26)/10 -> 0.62183 | K26: =SQRT(((P26-J26)^2+(T26-J26)^2+(X26-J26)^2+(AB26-J26)^2+(AF26-J26)^2+(AJ26-J26)^2+(AN26-J26)^2+(AR26-J26)^2+(AV26-J26)^2+(AZ26-J26)^2)/10) -> 0.01851983 | L26: =K26/J26 -> 0.029782786 | N26: 0.6972 | O26: 0.66 | P26: 0.6408 | R26: 0.7059 | S26: 0.6 | T26: 0.6122 | V26: 0.6805 | W26: 0.68 | X26: 0.6602 | Z26: 0.7189 | AA26: 0.63 | AB26: 0.63 | AD26: 0.6908 | AE26: 0.62 | AF26: 0.6169 | AH26: 0.714 | AI26: 0.59 | AJ26: 0.602 | AL26: 0.6927 | AM26: 0.61 | AN26: 0.6224 | AP26: 0.7262 | AQ26: 0.62 | AR26: 0.62 | AT26: 0.695 | AU26: 0.59 | AV26: 0.59 | AX26: 0.7023 | AY26: 0.63 | AZ26: 0.6238
B27: FT-transformer | C27: =D26/D27-1 -> 0.040164092 | D27: =(N27+R27+V27+Z27+AD27+AH27+AL27+AP27+AT27+AX27)/10 -> 0.67523 | E27: =SQRT(((N27-D27)^2+(R27-D27)^2+(V27-D27)^2+(Z27-D27)^2+(AD27-D27)^2+(AH27-D27)^2+(AL27-D27)^2+(AP27-D27)^2+(AT27-D27)^2+(AX27-D27)^2)/10) -> 0.033669305 | F27: =E27/D27 -> 0.049863461 | G27: =(O27+S27+W27+AA27+AE27+AI27+AM27+AQ27+AU27+AY27)/10 -> 0.66 | H27: =SQRT(((O27-G27)^2+(S27-G27)^2+(W27-G27)^2+(AA27-G27)^2+(AE27-G27)^2+(AI27-G27)^2+(AM27-G27)^2+(AQ27-G27)^2+(AU27-G27)^2+(AY27-G27)^2)/10) -> 0.030983867 | I27: =H27/G27 -> 0.046945253 | J27: =(P27+T27+X27+AB27+AF27+AJ27+AN27+AR27+AV27+AZ27)/10 -> 0.64449 | K27: =SQRT(((P27-J27)^2+(T27-J27)^2+(X27-J27)^2+(AB27-J27)^2+(AF27-J27)^2+(AJ27-J27)^2+(AN27-J27)^2+(AR27-J27)^2+(AV27-J27)^2+(AZ27-J27)^2)/10) -> 0.024539374 | L27: =K27/J27 -> 0.038075648 | N27: 0.6555 | O27: 0.66 | P27: 0.6471 | R27: 0.7301 | S27: 0.72 | T27: 0.6923 | V27: 0.6765 | W27: 0.66 | X27: 0.6439 | Z27: 0.6912 | AA27: 0.63 | AB27: 0.6176 | AD27: 0.6329 | AE27: 0.62 | AF27: 0.6108 | AH27: 0.6132 | AI27: 0.68 | AJ27: 0.6239 | AL27: 0.6949 | AM27: 0.67 | AN27: 0.6601 | AP27: 0.6567 | AQ27: 0.61 | AR27: 0.6224 | AT27: 0.6977 | AU27: 0.68 | AV27: 0.6634 | AX27: 0.7036 | AY27: 0.67 | AZ27: 0.6634
B28: CatBoost | C28: =D26/D28-1 -> 0.0043184191 | D28: =(N28+R28+V28+Z28+AD28+AH28+AL28+AP28+AT28+AX28)/10 -> 0.69933 | E28: =SQRT(((N28-D28)^2+(R28-D28)^2+(V28-D28)^2+(Z28-D28)^2+(AD28-D28)^2+(AH28-D28)^2+(AL28-D28)^2+(AP28-D28)^2+(AT28-D28)^2+(AX28-D28)^2)/10) -> 0.011061017 | F28: =E28/D28 -> 0.015816592 | G28: =(O28+S28+W28+AA28+AE28+AI28+AM28+AQ28+AU28+AY28)/10 -> 0.661 | H28: =SQRT(((O28-G28)^2+(S28-G28)^2+(W28-G28)^2+(AA28-G28)^2+(AE28-G28)^2+(AI28-G28)^2+(AM28-G28)^2+(AQ28-G28)^2+(AU28-G28)^2+(AY28-G28)^2)/10) -> 0.037 | I28: =H28/G28 -> 0.055975794 | J28: =(P28+T28+X28+AB28+AF28+AJ28+AN28+AR28+AV28+AZ28)/10 -> 0.65703 | K28: =SQRT(((P28-J28)^2+(T28-J28)^2+(X28-J28)^2+(AB28-J28)^2+(AF28-J28)^2+(AJ28-J28)^2+(AN28-J28)^2+(AR28-J28)^2+(AV28-J28)^2+(AZ28-J28)^2)/10) -> 0.021986407 | L28: =K28/J28 -> 0.033463323 | N28: 0.7078 | O28: 0.65 | P28: 0.628 | R28: 0.6934 | S28: 0.66 | T28: 0.6502 | V28: 0.7166 | W28: 0.65 | X28: 0.6566 | Z28: 0.6798 | AA28: 0.65 | AB28: 0.6468 | AD28: 0.6883 | AE28: 0.72 | AF28: 0.699 | AH28: 0.6927 | AI28: 0.62 | AJ28: 0.6327 | AL28: 0.707 | AM28: 0.59 | AN28: 0.6344 | AP28: 0.7131 | AQ28: 0.7 | AR28: 0.6763 | AT28: 0.7 | AU28: 0.67 | AV28: 0.6667 | AX28: 0.6946 | AY28: 0.7 | AZ28: 0.6796
B29: SCARF | C29: =D26/D29-1 -> 0.32314155 | D29: =(N29+R29+V29+Z29+AD29+AH29+AL29+AP29+AT29+AX29)/10 -> 0.53082 | E29: =SQRT(((N29-D29)^2+(R29-D29)^2+(V29-D29)^2+(Z29-D29)^2+(AD29-D29)^2+(AH29-D29)^2+(AL29-D29)^2+(AP29-D29)^2+(AT29-D29)^2+(AX29-D29)^2)/10) -> 0.018638069 | F29: =E29/D29 -> 0.035111843 | G29: =(O29+S29+W29+AA29+AE29+AI29+AM29+AQ29+AU29+AY29)/10 -> 0.528 | H29: =SQRT(((O29-G29)^2+(S29-G29)^2+(W29-G29)^2+(AA29-G29)^2+(AE29-G29)^2+(AI29-G29)^2+(AM29-G29)^2+(AQ29-G29)^2+(AU29-G29)^2+(AY29-G29)^2)/10) -> 0.033406586 | I29: =H29/G29 -> 0.06327005 | J29: =(P29+T29+X29+AB29+AF29+AJ29+AN29+AR29+AV29+AZ29)/10 -> 0.53459 | K29: =SQRT(((P29-J29)^2+(T29-J29)^2+(X29-J29)^2+(AB29-J29)^2+(AF29-J29)^2+(AJ29-J29)^2+(AN29-J29)^2+(AR29-J29)^2+(AV29-J29)^2+(AZ29-J29)^2)/10) -> 0.025728717 | L29: =K29/J29 -> 0.048127944 | N29: 0.5357 | O29: 0.49 | P29: 0.5078 | R29: 0.4968 | S29: 0.49 | T29: 0.4975 | V29: 0.5328 | W29: 0.51 | X29: 0.5231 | Z29: 0.5491 | AA29: 0.57 | AB29: 0.57 | AD29: 0.5229 | AE29: 0.56 | AF29: 0.56 | AH29: 0.5183 | AI29: 0.51 | AJ29: 0.5204 | AL29: 0.5324 | AM29: 0.56 | AN29: 0.56 | AP29: 0.5099 | AQ29: 0.48 | AR29: 0.5026 | AT29: 0.5626 | AU29: 0.56 | AV29: 0.5517 | AX29: 0.5477 | AY29: 0.55 | AZ29: 0.5528
C31: effect, % | D31: AUPRC | G31: Recall | J31: F1 | N31: AUPRC | O31: For reference | R31: AUPRC | S31: For reference | V31: AUPRC | W31: For reference | Z31: AUPRC | AA31: For reference | AD31: AUPRC | AE31: For reference | AH31: AUPRC | AI31: For reference | AL31: AUPRC | AM31: For reference | AP31: AUPRC | AQ31: For reference | AT31: AUPRC | AU31: For reference | AX31: AUPRC | AY31: For reference
D32: mean | E32: σ | F32: CV | G32: mean | H32: σ | I32: CV | J32: mean | K32: σ | L32: CV | O32: Recall | P32: F1 | S32: Recall | T32: F1 | W32: Recall | X32: F1 | AA32: Recall | AB32: F1 | AE32: Recall | AF32: F1 | AI32: Recall | AJ32: F1 | AM32: Recall | AN32: F1 | AQ32: Recall | AR32: F1 | AU32: Recall | AV32: F1 | AY32: Recall | AZ32: F1
B33: LR | C33: =D34/D33-1 -> 0.077108653 | D33: =(N33+R33+V33+Z33+AD33+AH33+AL33+AP33+AT33+AX33)/10 -> 0.65907 | E33: =SQRT(((N33-D33)^2+(R33-D33)^2+(V33-D33)^2+(Z33-D33)^2+(AD33-D33)^2+(AH33-D33)^2+(AL33-D33)^2+(AP33-D33)^2+(AT33-D33)^2+(AX33-D33)^2)/10) -> 0.0027996607 | F33: =E33/D33 -> 0.0042478958 | G33: =(O33+S33+W33+AA33+AE33+AI33+AM33+AQ33+AU33+AY33)/10 -> 0.598 | H33: =SQRT(((O33-G33)^2+(S33-G33)^2+(W33-G33)^2+(AA33-G33)^2+(AE33-G33)^2+(AI33-G33)^2+(AM33-G33)^2+(AQ33-G33)^2+(AU33-G33)^2+(AY33-G33)^2)/10) -> 0.006 | I33: =H33/G33 -> 0.010033445 | J33: =(P33+T33+X33+AB33+AF33+AJ33+AN33+AR33+AV33+AZ33)/10 -> 0.59944 | K33: =SQRT(((P33-J33)^2+(T33-J33)^2+(X33-J33)^2+(AB33-J33)^2+(AF33-J33)^2+(AJ33-J33)^2+(AN33-J33)^2+(AR33-J33)^2+(AV33-J33)^2+(AZ33-J33)^2)/10) -> 0.008760274 | L33: =K33/J33 -> 0.014614096 | N33: 0.6544 | O33: 0.58 | P33: 0.5734 | R33: 0.6609 | S33: 0.6 | T33: 0.603 | V33: 0.6609 | W33: 0.6 | X33: 0.603 | Z33: 0.6609 | AA33: 0.6 | AB33: 0.603 | AD33: 0.655 | AE33: 0.6 | AF33: 0.6 | AH33: 0.655 | AI33: 0.6 | AJ33: 0.6 | AL33: 0.6609 | AM33: 0.6 | AN33: 0.603 | AP33: 0.6609 | AQ33: 0.6 | AR33: 0.603 | AT33: 0.6609 | AU33: 0.6 | AV33: 0.603 | AX33: 0.6609 | AY33: 0.6 | AZ33: 0.603
B34: CLT-TAB without CATA and SQP | D34: =(N34+R34+V34+Z34+AD34+AH34+AL34+AP34+AT34+AX34)/10 -> 0.70989 | E34: =SQRT(((N34-D34)^2+(R34-D34)^2+(V34-D34)^2+(Z34-D34)^2+(AD34-D34)^2+(AH34-D34)^2+(AL34-D34)^2+(AP34-D34)^2+(AT34-D34)^2+(AX34-D34)^2)/10) -> 0.010584748 | F34: =E34/D34 -> 0.014910406 | G34: =(O34+S34+W34+AA34+AE34+AI34+AM34+AQ34+AU34+AY34)/10 -> 0.621 | H34: =SQRT(((O34-G34)^2+(S34-G34)^2+(W34-G34)^2+(AA34-G34)^2+(AE34-G34)^2+(AI34-G34)^2+(AM34-G34)^2+(AQ34-G34)^2+(AU34-G34)^2+(AY34-G34)^2)/10) -> 0.019209373 | I34: =H34/G34 -> 0.030932967 | J34: =(P34+T34+X34+AB34+AF34+AJ34+AN34+AR34+AV34+AZ34)/10 -> 0.616182 | K34: =SQRT(((P34-J34)^2+(T34-J34)^2+(X34-J34)^2+(AB34-J34)^2+(AF34-J34)^2+(AJ34-J34)^2+(AN34-J34)^2+(AR34-J34)^2+(AV34-J34)^2+(AZ34-J34)^2)/10) -> 0.013448201 | L34: =K34/J34 -> 0.021825047 | N34: 0.7039 | O34: 0.64 | P34: 0.6275 | R34: 0.7099 | S34: 0.66 | T34: 0.6408 | V34: 0.7248 | W34: 0.59 | X34: 0.60082 | Z34: 0.6886 | AA34: 0.63 | AB34: 0.6238 | AD34: 0.7138 | AE34: 0.62 | AF34: 0.6169 | AH34: 0.7187 | AI34: 0.62 | AJ34: 0.6108 | AL34: 0.7098 | AM34: 0.61 | AN34: 0.6162 | AP34: 0.7031 | AQ34: 0.6 | AR34: 0.5941 | AT34: 0.7243 | AU34: 0.63 | AV34: 0.6269 | AX34: 0.702 | AY34: 0.61 | AZ34: 0.604
B35: FT-transformer | C35: =D34/D35-1 -> 0.051330658 | D35: =(N35+R35+V35+Z35+AD35+AH35+AL35+AP35+AT35+AX35)/10 -> 0.67523 | E35: =SQRT(((N35-D35)^2+(R35-D35)^2+(V35-D35)^2+(Z35-D35)^2+(AD35-D35)^2+(AH35-D35)^2+(AL35-D35)^2+(AP35-D35)^2+(AT35-D35)^2+(AX35-D35)^2)/10) -> 0.033669305 | F35: =E35/D35 -> 0.049863461 | G35: =(O35+S35+W35+AA35+AE35+AI35+AM35+AQ35+AU35+AY35)/10 -> 0.66 | H35: =SQRT(((O35-G35)^2+(S35-G35)^2+(W35-G35)^2+(AA35-G35)^2+(AE35-G35)^2+(AI35-G35)^2+(AM35-G35)^2+(AQ35-G35)^2+(AU35-G35)^2+(AY35-G35)^2)/10) -> 0.030983867 | I35: =H35/G35 -> 0.046945253 | J35: =(P35+T35+X35+AB35+AF35+AJ35+AN35+AR35+AV35+AZ35)/10 -> 0.64449 | K35: =SQRT(((P35-J35)^2+(T35-J35)^2+(X35-J35)^2+(AB35-J35)^2+(AF35-J35)^2+(AJ35-J35)^2+(AN35-J35)^2+(AR35-J35)^2+(AV35-J35)^2+(AZ35-J35)^2)/10) -> 0.024539374 | L35: =K35/J35 -> 0.038075648 | N35: 0.6555 | O35: 0.66 | P35: 0.6471 | R35: 0.7301 | S35: 0.72 | T35: 0.6923 | V35: 0.6765 | W35: 0.66 | X35: 0.6439 | Z35: 0.6912 | AA35: 0.63 | AB35: 0.6176 | AD35: 0.6329 | AE35: 0.62 | AF35: 0.6108 | AH35: 0.6132 | AI35: 0.68 | AJ35: 0.6239 | AL35: 0.6949 | AM35: 0.67 | AN35: 0.6601 | AP35: 0.6567 | AQ35: 0.61 | AR35: 0.6224 | AT35: 0.6977 | AU35: 0.68 | AV35: 0.6634 | AX35: 0.7036 | AY35: 0.67 | AZ35: 0.6634
B36: CatBoost | C36: =D34/D36-1 -> 0.015100167 | D36: =(N36+R36+V36+Z36+AD36+AH36+AL36+AP36+AT36+AX36)/10 -> 0.69933 | E36: =SQRT(((N36-D36)^2+(R36-D36)^2+(V36-D36)^2+(Z36-D36)^2+(AD36-D36)^2+(AH36-D36)^2+(AL36-D36)^2+(AP36-D36)^2+(AT36-D36)^2+(AX36-D36)^2)/10) -> 0.011061017 | F36: =E36/D36 -> 0.015816592 | G36: =(O36+S36+W36+AA36+AE36+AI36+AM36+AQ36+AU36+AY36)/10 -> 0.661 | H36: =SQRT(((O36-G36)^2+(S36-G36)^2+(W36-G36)^2+(AA36-G36)^2+(AE36-G36)^2+(AI36-G36)^2+(AM36-G36)^2+(AQ36-G36)^2+(AU36-G36)^2+(AY36-G36)^2)/10) -> 0.037 | I36: =H36/G36 -> 0.055975794 | J36: =(P36+T36+X36+AB36+AF36+AJ36+AN36+AR36+AV36+AZ36)/10 -> 0.65703 | K36: =SQRT(((P36-J36)^2+(T36-J36)^2+(X36-J36)^2+(AB36-J36)^2+(AF36-J36)^2+(AJ36-J36)^2+(AN36-J36)^2+(AR36-J36)^2+(AV36-J36)^2+(AZ36-J36)^2)/10) -> 0.021986407 | L36: =K36/J36 -> 0.033463323 | N36: 0.7078 | O36: 0.65 | P36: 0.628 | R36: 0.6934 | S36: 0.66 | T36: 0.6502 | V36: 0.7166 | W36: 0.65 | X36: 0.6566 | Z36: 0.6798 | AA36: 0.65 | AB36: 0.6468 | AD36: 0.6883 | AE36: 0.72 | AF36: 0.699 | AH36: 0.6927 | AI36: 0.62 | AJ36: 0.6327 | AL36: 0.707 | AM36: 0.59 | AN36: 0.6344 | AP36: 0.7131 | AQ36: 0.7 | AR36: 0.6763 | AT36: 0.7 | AU36: 0.67 | AV36: 0.6667 | AX36: 0.6946 | AY36: 0.7 | AZ36: 0.6796
B37: SCARF | C37: =D34/D37-1 -> 0.33734599 | D37: =(N37+R37+V37+Z37+AD37+AH37+AL37+AP37+AT37+AX37)/10 -> 0.53082 | E37: =SQRT(((N37-D37)^2+(R37-D37)^2+(V37-D37)^2+(Z37-D37)^2+(AD37-D37)^2+(AH37-D37)^2+(AL37-D37)^2+(AP37-D37)^2+(AT37-D37)^2+(AX37-D37)^2)/10) -> 0.018638069 | F37: =E37/D37 -> 0.035111843 | G37: =(O37+S37+W37+AA37+AE37+AI37+AM37+AQ37+AU37+AY37)/10 -> 0.528 | H37: =SQRT(((O37-G37)^2+(S37-G37)^2+(W37-G37)^2+(AA37-G37)^2+(AE37-G37)^2+(AI37-G37)^2+(AM37-G37)^2+(AQ37-G37)^2+(AU37-G37)^2+(AY37-G37)^2)/10) -> 0.033406586 | I37: =H37/G37 -> 0.06327005 | J37: =(P37+T37+X37+AB37+AF37+AJ37+AN37+AR37+AV37+AZ37)/10 -> 0.53459 | K37: =SQRT(((P37-J37)^2+(T37-J37)^2+(X37-J37)^2+(AB37-J37)^2+(AF37-J37)^2+(AJ37-J37)^2+(AN37-J37)^2+(AR37-J37)^2+(AV37-J37)^2+(AZ37-J37)^2)/10) -> 0.025728717 | L37: =K37/J37 -> 0.048127944 | N37: 0.5357 | O37: 0.49 | P37: 0.5078 | R37: 0.4968 | S37: 0.49 | T37: 0.4975 | V37: 0.5328 | W37: 0.51 | X37: 0.5231 | Z37: 0.5491 | AA37: 0.57 | AB37: 0.57 | AD37: 0.5229 | AE37: 0.56 | AF37: 0.56 | AH37: 0.5183 | AI37: 0.51 | AJ37: 0.5204 | AL37: 0.5324 | AM37: 0.56 | AN37: 0.56 | AP37: 0.5099 | AQ37: 0.48 | AR37: 0.5026 | AT37: 0.5626 | AU37: 0.56 | AV37: 0.5517 | AX37: 0.5477 | AY37: 0.55 | AZ37: 0.5528

Sheet NIDS
B1: Overview
B2: The NIDS_Network_Benchmark_APT dataset is a recent (2025) flow‑level benchmark for intrusion detection, specifically designed to overcome the limitations of older network datasets such as CICIDS‑2017, CICIDS‑2019, CIC‑IDS‑2018, and UNSW‑NB15. Its main goal is to provide a clean, reproducible, and up‑to‑date dataset for training and evaluating AI‑based Network Intrusion Detection Systems (NIDS). The dataset comprises 49,000 labelled network flows spanning 13 traffic classes, where the majority are various types of attacks and one is normal traffic (BENIGN). A key novelty is the inclusion of two attack classes absent from previous datasets: Encrypted HTTPS‑based Command & Control (C2) beaconing, which mimics real‑world Advanced Persistent Threat (APT) lateral movement. IoT MQTT broker flood attacks on port 1883. All features are flow‑based, computed from PCAP traffic. The dataset provides 90 features in total: 84 CICFlowMeter‑compatible features that allow direct comparison with older datasets, plus 6 novel derived features (Byte_Entropy, IAT_Coefficient_Variation, TLS_Encrypted_Flag, Payload_Ratio_Fwd, Burstiness_Index, Pkt_Size_Skewness). The dataset is deliberately designed to be free of NaN and Infinity values – a known issue in CICIDS‑2017 – and comes with full Python generation scripts to ensure reproducibility. The primary file is NIDS_Network_Benchmark_APT_2025.csv (≈26 MB) and is distributed under a CC BY 4.0 open‑access license. The recommended stratified split is 70 % training / 15 % validation / 15 % test. A simple Random Forest baseline on this dataset achieves a 97.9 % macro F1‑score, confirming that the dataset is learnable and suitable for benchmarking [3†L35-L36]. Because of its balanced attack representation and absence of data‑quality issues, NIDS_Network_Benchmark_APT is well‑suited for evaluating machine‑learning‑based intrusion detection systems, especially those focusing on modern encrypted and IoT‑targeted threats.
B3: We used the NIDS dataset, which contains 72 000 instances with a 48,0 % anomaly rate. It comprises 54 numerical and 12 categorical features (Removed: 'timestamp' (timestamp); 'fwd_urg_flags', 'urg_flag_cnt', 'ece_flag_cnt' (constant features). The data were used after preprocessing (missing values, duplicates, and constant features were removed). F1 and Recall scores were obtained with a threshold of 0.5. We used 208 instances for finetuning, of which 100 were anomalies, and the same number (208 instances, 100 anomalies) for testing.
B5: Random AUPRC | C5: 0.4808 | N5: Seed
G6: For reference | N6: 42 | R6: 43 | V6: 44 | Z6: 45 | AD6: 46 | AH6: 47 | AL6: 48 | AP6: 49 | AT6: 50 | AX6: 51
C7: effect, % | D7: AUPRC | G7: Recall | J7: F1 | N7: AUPRC | O7: For reference | R7: AUPRC | S7: For reference | V7: AUPRC | W7: For reference | Z7: AUPRC | AA7: For reference | AD7: AUPRC | AE7: For reference | AH7: AUPRC | AI7: For reference | AL7: AUPRC | AM7: For reference | AP7: AUPRC | AQ7: For reference | AT7: AUPRC | AU7: For reference | AX7: AUPRC | AY7: For reference
D8: mean | E8: σ | F8: CV | G8: mean | H8: σ | I8: CV | J8: mean | K8: σ | L8: CV | O8: Recall | P8: F1 | S8: Recall | T8: F1 | W8: Recall | X8: F1 | AA8: Recall | AB8: F1 | AE8: Recall | AF8: F1 | AI8: Recall | AJ8: F1 | AM8: Recall | AN8: F1 | AQ8: Recall | AR8: F1 | AU8: Recall | AV8: F1 | AY8: Recall | AZ8: F1
B9: LR | C9: =D10/D9-1 -> 0.027527461 | D9: =(N9+R9+V9+Z9+AD9+AH9+AL9+AP9+AT9+AX9)/10 -> 0.97321 | E9: =SQRT(((N9-D9)^2+(R9-D9)^2+(V9-D9)^2+(Z9-D9)^2+(AD9-D9)^2+(AH9-D9)^2+(AL9-D9)^2+(AP9-D9)^2+(AT9-D9)^2+(AX9-D9)^2)/10) -> 0.0027620463 | F9: =E9/D9 -> 0.0028380785 | G9: =(O9+S9+W9+AA9+AE9+AI9+AM9+AQ9+AU9+AY9)/10 -> 0.918 | H9: =SQRT(((O9-G9)^2+(S9-G9)^2+(W9-G9)^2+(AA9-G9)^2+(AE9-G9)^2+(AI9-G9)^2+(AM9-G9)^2+(AQ9-G9)^2+(AU9-G9)^2+(AY9-G9)^2)/10) -> 0.0087177979 | I9: =H9/G9 -> 0.0094965119 | J9: =(P9+T9+X9+AB9+AF9+AJ9+AN9+AR9+AV9+AZ9)/10 -> 0.94058 | K9: =SQRT(((P9-J9)^2+(T9-J9)^2+(X9-J9)^2+(AB9-J9)^2+(AF9-J9)^2+(AJ9-J9)^2+(AN9-J9)^2+(AR9-J9)^2+(AV9-J9)^2+(AZ9-J9)^2)/10) -> 0.0045369153 | L9: =K9/J9 -> 0.0048235294 | N9: 0.9749 | O9: 0.91 | P9: 0.9381 | R9: 0.9766 | S9: 0.91 | T9: 0.943 | V9: 0.9675 | W9: 0.92 | X9: 0.9293 | Z9: 0.9766 | AA9: 0.91 | AB9: 0.943 | AD9: 0.9712 | AE9: 0.93 | AF9: 0.9442 | AH9: 0.9749 | AI9: 0.91 | AJ9: 0.9381 | AL9: 0.9712 | AM9: 0.93 | AN9: 0.9442 | AP9: 0.9712 | AQ9: 0.93 | AR9: 0.9442 | AT9: 0.9731 | AU9: 0.92 | AV9: 0.9436 | AX9: 0.9749 | AY9: 0.91 | AZ9: 0.9381
B10: CLT-TAB | D10: =(N10+R10+V10+Z10+AD10+AH10+AL10+AP10+AT10+AX10)/10 -> 1 | E10: =SQRT(((N10-D10)^2+(R10-D10)^2+(V10-D10)^2+(Z10-D10)^2+(AD10-D10)^2+(AH10-D10)^2+(AL10-D10)^2+(AP10-D10)^2+(AT10-D10)^2+(AX10-D10)^2)/10) -> 0 | F10: =E10/D10 -> 0 | G10: =(O10+S10+W10+AA10+AE10+AI10+AM10+AQ10+AU10+AY10)/10 -> 1 | H10: =SQRT(((O10-G10)^2+(S10-G10)^2+(W10-G10)^2+(AA10-G10)^2+(AE10-G10)^2+(AI10-G10)^2+(AM10-G10)^2+(AQ10-G10)^2+(AU10-G10)^2+(AY10-G10)^2)/10) -> 0 | I10: =H10/G10 -> 0 | J10: =(P10+T10+X10+AB10+AF10+AJ10+AN10+AR10+AV10+AZ10)/10 -> 1 | K10: =SQRT(((P10-J10)^2+(T10-J10)^2+(X10-J10)^2+(AB10-J10)^2+(AF10-J10)^2+(AJ10-J10)^2+(AN10-J10)^2+(AR10-J10)^2+(AV10-J10)^2+(AZ10-J10)^2)/10) -> 0 | L10: =K10/J10 -> 0 | N10: 1 | O10: 1 | P10: 1 | R10: 1 | S10: 1 | T10: 1 | V10: 1 | W10: 1 | X10: 1 | Z10: 1 | AA10: 1 | AB10: 1 | AD10: 1 | AE10: 1 | AF10: 1 | AH10: 1 | AI10: 1 | AJ10: 1 | AL10: 1 | AM10: 1 | AN10: 1 | AP10: 1 | AQ10: 1 | AR10: 1 | AT10: 1 | AU10: 1 | AV10: 1 | AX10: 1 | AY10: 1 | AZ10: 1
B11: FT-transformer | C11: =D10/D11-1 -> 0.0023053022 | D11: =(N11+R11+V11+Z11+AD11+AH11+AL11+AP11+AT11+AX11)/10 -> 0.9977 | E11: =SQRT(((N11-D11)^2+(R11-D11)^2+(V11-D11)^2+(Z11-D11)^2+(AD11-D11)^2+(AH11-D11)^2+(AL11-D11)^2+(AP11-D11)^2+(AT11-D11)^2+(AX11-D11)^2)/10) -> 0.001150652 | F11: =E11/D11 -> 0.0011533046 | G11: =(O11+S11+W11+AA11+AE11+AI11+AM11+AQ11+AU11+AY11)/10 -> 0.957 | H11: =SQRT(((O11-G11)^2+(S11-G11)^2+(W11-G11)^2+(AA11-G11)^2+(AE11-G11)^2+(AI11-G11)^2+(AM11-G11)^2+(AQ11-G11)^2+(AU11-G11)^2+(AY11-G11)^2)/10) -> 0.013453624 | I11: =H11/G11 -> 0.014058123 | J11: =(P11+T11+X11+AB11+AF11+AJ11+AN11+AR11+AV11+AZ11)/10 -> 0.97156 | K11: =SQRT(((P11-J11)^2+(T11-J11)^2+(X11-J11)^2+(AB11-J11)^2+(AF11-J11)^2+(AJ11-J11)^2+(AN11-J11)^2+(AR11-J11)^2+(AV11-J11)^2+(AZ11-J11)^2)/10) -> 0.0047628143 | L11: =K11/J11 -> 0.0049022338 | N11: 0.9983 | O11: 0.98 | P11: 0.9751 | R11: 0.9979 | S11: 0.94 | T11: 0.9691 | V11: 0.9984 | W11: 0.94 | X11: 0.9641 | Z11: 0.9983 | AA11: 0.96 | AB11: 0.9796 | AD11: 0.9977 | AE11: 0.95 | AF11: 0.9694 | AH11: 0.9979 | AI11: 0.97 | AJ11: 0.9749 | AL11: 0.9988 | AM11: 0.96 | AN11: 0.9746 | AP11: 0.9948 | AQ11: 0.94 | AR11: 0.9691 | AT11: 0.9964 | AU11: 0.96 | AV11: 0.9648 | AX11: 0.9985 | AY11: 0.97 | AZ11: 0.9749
B12: CatBoost | C12: =D10/D12-1 -> 0.0013718795 | D12: =(N12+R12+V12+Z12+AD12+AH12+AL12+AP12+AT12+AX12)/10 -> 0.99863 | E12: =SQRT(((N12-D12)^2+(R12-D12)^2+(V12-D12)^2+(Z12-D12)^2+(AD12-D12)^2+(AH12-D12)^2+(AL12-D12)^2+(AP12-D12)^2+(AT12-D12)^2+(AX12-D12)^2)/10) -> 0.0018401359 | F12: =E12/D12 -> 0.0018426603 | G12: =(O12+S12+W12+AA12+AE12+AI12+AM12+AQ12+AU12+AY12)/10 -> 0.946 | H12: =SQRT(((O12-G12)^2+(S12-G12)^2+(W12-G12)^2+(AA12-G12)^2+(AE12-G12)^2+(AI12-G12)^2+(AM12-G12)^2+(AQ12-G12)^2+(AU12-G12)^2+(AY12-G12)^2)/10) -> 0.028354894 | I12: =H12/G12 -> 0.029973461 | J12: =(P12+T12+X12+AB12+AF12+AJ12+AN12+AR12+AV12+AZ12)/10 -> 0.97205 | K12: =SQRT(((P12-J12)^2+(T12-J12)^2+(X12-J12)^2+(AB12-J12)^2+(AF12-J12)^2+(AJ12-J12)^2+(AN12-J12)^2+(AR12-J12)^2+(AV12-J12)^2+(AZ12-J12)^2)/10) -> 0.015176841 | L12: =K12/J12 -> 0.015613231 | N12: 0.9988 | O12: 0.97 | P12: 0.9848 | R12: 1 | S12: 0.97 | T12: 0.9848 | V12: 0.9993 | W12: 0.94 | X12: 0.9691 | Z12: 0.9975 | AA12: 0.95 | AB12: 0.9744 | AD12: 1 | AE12: 0.98 | AF12: 0.9899 | AH12: 0.9986 | AI12: 0.89 | AJ12: 0.9418 | AL12: 0.9997 | AM12: 0.96 | AN12: 0.9796 | AP12: 0.9936 | AQ12: 0.9 | AR12: 0.9474 | AT12: 0.9988 | AU12: 0.94 | AV12: 0.9691 | AX12: 1 | AY12: 0.96 | AZ12: 0.9796
B13: SCARF | C13: =D10/D13-1 -> 1.0190192 | D13: =(N13+R13+V13+Z13+AD13+AH13+AL13+AP13+AT13+AX13)/10 -> 0.49529 | E13: =SQRT(((N13-D13)^2+(R13-D13)^2+(V13-D13)^2+(Z13-D13)^2+(AD13-D13)^2+(AH13-D13)^2+(AL13-D13)^2+(AP13-D13)^2+(AT13-D13)^2+(AX13-D13)^2)/10) -> 0.069659665 | F13: =E13/D13 -> 0.1406442 | G13: =(O13+S13+W13+AA13+AE13+AI13+AM13+AQ13+AU13+AY13)/10 -> 0.517 | H13: =SQRT(((O13-G13)^2+(S13-G13)^2+(W13-G13)^2+(AA13-G13)^2+(AE13-G13)^2+(AI13-G13)^2+(AM13-G13)^2+(AQ13-G13)^2+(AU13-G13)^2+(AY13-G13)^2)/10) -> 0.044056782 | I13: =H13/G13 -> 0.085216212 | J13: =(P13+T13+X13+AB13+AF13+AJ13+AN13+AR13+AV13+AZ13)/10 -> 0.47686 | K13: =SQRT(((P13-J13)^2+(T13-J13)^2+(X13-J13)^2+(AB13-J13)^2+(AF13-J13)^2+(AJ13-J13)^2+(AN13-J13)^2+(AR13-J13)^2+(AV13-J13)^2+(AZ13-J13)^2)/10) -> 0.032867072 | L13: =K13/J13 -> 0.068923943 | N13: 0.4624 | O13: 0.55 | P13: 0.4955 | R13: 0.6069 | S13: 0.5 | T13: 0.4908 | V13: 0.6332 | W13: 0.42 | X13: 0.4 | Z13: 0.4683 | AA13: 0.56 | AB13: 0.4956 | AD13: 0.529 | AE13: 0.56 | AF13: 0.4934 | AH13: 0.4645 | AI13: 0.52 | AJ13: 0.486 | AL13: 0.4285 | AM13: 0.55 | AN13: 0.5093 | AP13: 0.4951 | AQ13: 0.48 | AR13: 0.4593 | AT13: 0.4124 | AU13: 0.48 | AV13: 0.4364 | AX13: 0.4526 | AY13: 0.55 | AZ13: 0.5023
C15: effect, % | D15: AUPRC | G15: Recall | J15: F1 | N15: AUPRC | O15: For reference | R15: AUPRC | S15: For reference | V15: AUPRC | W15: For reference | Z15: AUPRC | AA15: For reference | AD15: AUPRC | AE15: For reference | AH15: AUPRC | AI15: For reference | AL15: AUPRC | AM15: For reference | AP15: AUPRC | AQ15: For reference | AT15: AUPRC | AU15: For reference | AX15: AUPRC | AY15: For reference
D16: mean | E16: σ | F16: CV | G16: mean | H16: σ | I16: CV | J16: mean | K16: σ | L16: CV | O16: Recall | P16: F1 | S16: Recall | T16: F1 | W16: Recall | X16: F1 | AA16: Recall | AB16: F1 | AE16: Recall | AF16: F1 | AI16: Recall | AJ16: F1 | AM16: Recall | AN16: F1 | AQ16: Recall | AR16: F1 | AU16: Recall | AV16: F1 | AY16: Recall | AZ16: F1
B17: LR | C17: =D18/D17-1 -> 0.027527461 | D17: =(N17+R17+V17+Z17+AD17+AH17+AL17+AP17+AT17+AX17)/10 -> 0.97321 | E17: =SQRT(((N17-D17)^2+(R17-D17)^2+(V17-D17)^2+(Z17-D17)^2+(AD17-D17)^2+(AH17-D17)^2+(AL17-D17)^2+(AP17-D17)^2+(AT17-D17)^2+(AX17-D17)^2)/10) -> 0.0027620463 | F17: =E17/D17 -> 0.0028380785 | G17: =(O17+S17+W17+AA17+AE17+AI17+AM17+AQ17+AU17+AY17)/10 -> 0.918 | H17: =SQRT(((O17-G17)^2+(S17-G17)^2+(W17-G17)^2+(AA17-G17)^2+(AE17-G17)^2+(AI17-G17)^2+(AM17-G17)^2+(AQ17-G17)^2+(AU17-G17)^2+(AY17-G17)^2)/10) -> 0.0087177979 | I17: =H17/G17 -> 0.0094965119 | J17: =(P17+T17+X17+AB17+AF17+AJ17+AN17+AR17+AV17+AZ17)/10 -> 0.94058 | K17: =SQRT(((P17-J17)^2+(T17-J17)^2+(X17-J17)^2+(AB17-J17)^2+(AF17-J17)^2+(AJ17-J17)^2+(AN17-J17)^2+(AR17-J17)^2+(AV17-J17)^2+(AZ17-J17)^2)/10) -> 0.0045369153 | L17: =K17/J17 -> 0.0048235294 | N17: 0.9749 | O17: 0.91 | P17: 0.9381 | R17: 0.9766 | S17: 0.91 | T17: 0.943 | V17: 0.9675 | W17: 0.92 | X17: 0.9293 | Z17: 0.9766 | AA17: 0.91 | AB17: 0.943 | AD17: 0.9712 | AE17: 0.93 | AF17: 0.9442 | AH17: 0.9749 | AI17: 0.91 | AJ17: 0.9381 | AL17: 0.9712 | AM17: 0.93 | AN17: 0.9442 | AP17: 0.9712 | AQ17: 0.93 | AR17: 0.9442 | AT17: 0.9731 | AU17: 0.92 | AV17: 0.9436 | AX17: 0.9749 | AY17: 0.91 | AZ17: 0.9381
B18: CLT-TAB without CATA | D18: =(N18+R18+V18+Z18+AD18+AH18+AL18+AP18+AT18+AX18)/10 -> 1 | E18: =SQRT(((N18-D18)^2+(R18-D18)^2+(V18-D18)^2+(Z18-D18)^2+(AD18-D18)^2+(AH18-D18)^2+(AL18-D18)^2+(AP18-D18)^2+(AT18-D18)^2+(AX18-D18)^2)/10) -> 0 | F18: =E18/D18 -> 0 | G18: =(O18+S18+W18+AA18+AE18+AI18+AM18+AQ18+AU18+AY18)/10 -> 1 | H18: =SQRT(((O18-G18)^2+(S18-G18)^2+(W18-G18)^2+(AA18-G18)^2+(AE18-G18)^2+(AI18-G18)^2+(AM18-G18)^2+(AQ18-G18)^2+(AU18-G18)^2+(AY18-G18)^2)/10) -> 0 | I18: =H18/G18 -> 0 | J18: =(P18+T18+X18+AB18+AF18+AJ18+AN18+AR18+AV18+AZ18)/10 -> 1 | K18: =SQRT(((P18-J18)^2+(T18-J18)^2+(X18-J18)^2+(AB18-J18)^2+(AF18-J18)^2+(AJ18-J18)^2+(AN18-J18)^2+(AR18-J18)^2+(AV18-J18)^2+(AZ18-J18)^2)/10) -> 0 | L18: =K18/J18 -> 0 | N18: 1 | O18: 1 | P18: 1 | R18: 1 | S18: 1 | T18: 1 | V18: 1 | W18: 1 | X18: 1 | Z18: 1 | AA18: 1 | AB18: 1 | AD18: 1 | AE18: 1 | AF18: 1 | AH18: 1 | AI18: 1 | AJ18: 1 | AL18: 1 | AM18: 1 | AN18: 1 | AP18: 1 | AQ18: 1 | AR18: 1 | AT18: 1 | AU18: 1 | AV18: 1 | AX18: 1 | AY18: 1 | AZ18: 1
B19: FT-transformer | C19: =D18/D19-1 -> 0.0023053022 | D19: =(N19+R19+V19+Z19+AD19+AH19+AL19+AP19+AT19+AX19)/10 -> 0.9977 | E19: =SQRT(((N19-D19)^2+(R19-D19)^2+(V19-D19)^2+(Z19-D19)^2+(AD19-D19)^2+(AH19-D19)^2+(AL19-D19)^2+(AP19-D19)^2+(AT19-D19)^2+(AX19-D19)^2)/10) -> 0.001150652 | F19: =E19/D19 -> 0.0011533046 | G19: =(O19+S19+W19+AA19+AE19+AI19+AM19+AQ19+AU19+AY19)/10 -> 0.957 | H19: =SQRT(((O19-G19)^2+(S19-G19)^2+(W19-G19)^2+(AA19-G19)^2+(AE19-G19)^2+(AI19-G19)^2+(AM19-G19)^2+(AQ19-G19)^2+(AU19-G19)^2+(AY19-G19)^2)/10) -> 0.013453624 | I19: =H19/G19 -> 0.014058123 | J19: =(P19+T19+X19+AB19+AF19+AJ19+AN19+AR19+AV19+AZ19)/10 -> 0.97156 | K19: =SQRT(((P19-J19)^2+(T19-J19)^2+(X19-J19)^2+(AB19-J19)^2+(AF19-J19)^2+(AJ19-J19)^2+(AN19-J19)^2+(AR19-J19)^2+(AV19-J19)^2+(AZ19-J19)^2)/10) -> 0.0047628143 | L19: =K19/J19 -> 0.0049022338 | N19: 0.9983 | O19: 0.98 | P19: 0.9751 | R19: 0.9979 | S19: 0.94 | T19: 0.9691 | V19: 0.9984 | W19: 0.94 | X19: 0.9641 | Z19: 0.9983 | AA19: 0.96 | AB19: 0.9796 | AD19: 0.9977 | AE19: 0.95 | AF19: 0.9694 | AH19: 0.9979 | AI19: 0.97 | AJ19: 0.9749 | AL19: 0.9988 | AM19: 0.96 | AN19: 0.9746 | AP19: 0.9948 | AQ19: 0.94 | AR19: 0.9691 | AT19: 0.9964 | AU19: 0.96 | AV19: 0.9648 | AX19: 0.9985 | AY19: 0.97 | AZ19: 0.9749
B20: CatBoost | C20: =D18/D20-1 -> 0.0013718795 | D20: =(N20+R20+V20+Z20+AD20+AH20+AL20+AP20+AT20+AX20)/10 -> 0.99863 | E20: =SQRT(((N20-D20)^2+(R20-D20)^2+(V20-D20)^2+(Z20-D20)^2+(AD20-D20)^2+(AH20-D20)^2+(AL20-D20)^2+(AP20-D20)^2+(AT20-D20)^2+(AX20-D20)^2)/10) -> 0.0018401359 | F20: =E20/D20 -> 0.0018426603 | G20: =(O20+S20+W20+AA20+AE20+AI20+AM20+AQ20+AU20+AY20)/10 -> 0.946 | H20: =SQRT(((O20-G20)^2+(S20-G20)^2+(W20-G20)^2+(AA20-G20)^2+(AE20-G20)^2+(AI20-G20)^2+(AM20-G20)^2+(AQ20-G20)^2+(AU20-G20)^2+(AY20-G20)^2)/10) -> 0.028354894 | I20: =H20/G20 -> 0.029973461 | J20: =(P20+T20+X20+AB20+AF20+AJ20+AN20+AR20+AV20+AZ20)/10 -> 0.97205 | K20: =SQRT(((P20-J20)^2+(T20-J20)^2+(X20-J20)^2+(AB20-J20)^2+(AF20-J20)^2+(AJ20-J20)^2+(AN20-J20)^2+(AR20-J20)^2+(AV20-J20)^2+(AZ20-J20)^2)/10) -> 0.015176841 | L20: =K20/J20 -> 0.015613231 | N20: 0.9988 | O20: 0.97 | P20: 0.9848 | R20: 1 | S20: 0.97 | T20: 0.9848 | V20: 0.9993 | W20: 0.94 | X20: 0.9691 | Z20: 0.9975 | AA20: 0.95 | AB20: 0.9744 | AD20: 1 | AE20: 0.98 | AF20: 0.9899 | AH20: 0.9986 | AI20: 0.89 | AJ20: 0.9418 | AL20: 0.9997 | AM20: 0.96 | AN20: 0.9796 | AP20: 0.9936 | AQ20: 0.9 | AR20: 0.9474 | AT20: 0.9988 | AU20: 0.94 | AV20: 0.9691 | AX20: 1 | AY20: 0.96 | AZ20: 0.9796
B21: SCARF | C21: =D18/D21-1 -> 1.0190192 | D21: =(N21+R21+V21+Z21+AD21+AH21+AL21+AP21+AT21+AX21)/10 -> 0.49529 | E21: =SQRT(((N21-D21)^2+(R21-D21)^2+(V21-D21)^2+(Z21-D21)^2+(AD21-D21)^2+(AH21-D21)^2+(AL21-D21)^2+(AP21-D21)^2+(AT21-D21)^2+(AX21-D21)^2)/10) -> 0.069659665 | F21: =E21/D21 -> 0.1406442 | G21: =(O21+S21+W21+AA21+AE21+AI21+AM21+AQ21+AU21+AY21)/10 -> 0.517 | H21: =SQRT(((O21-G21)^2+(S21-G21)^2+(W21-G21)^2+(AA21-G21)^2+(AE21-G21)^2+(AI21-G21)^2+(AM21-G21)^2+(AQ21-G21)^2+(AU21-G21)^2+(AY21-G21)^2)/10) -> 0.044056782 | I21: =H21/G21 -> 0.085216212 | J21: =(P21+T21+X21+AB21+AF21+AJ21+AN21+AR21+AV21+AZ21)/10 -> 0.47686 | K21: =SQRT(((P21-J21)^2+(T21-J21)^2+(X21-J21)^2+(AB21-J21)^2+(AF21-J21)^2+(AJ21-J21)^2+(AN21-J21)^2+(AR21-J21)^2+(AV21-J21)^2+(AZ21-J21)^2)/10) -> 0.032867072 | L21: =K21/J21 -> 0.068923943 | N21: 0.4624 | O21: 0.55 | P21: 0.4955 | R21: 0.6069 | S21: 0.5 | T21: 0.4908 | V21: 0.6332 | W21: 0.42 | X21: 0.4 | Z21: 0.4683 | AA21: 0.56 | AB21: 0.4956 | AD21: 0.529 | AE21: 0.56 | AF21: 0.4934 | AH21: 0.4645 | AI21: 0.52 | AJ21: 0.486 | AL21: 0.4285 | AM21: 0.55 | AN21: 0.5093 | AP21: 0.4951 | AQ21: 0.48 | AR21: 0.4593 | AT21: 0.4124 | AU21: 0.48 | AV21: 0.4364 | AX21: 0.4526 | AY21: 0.55 | AZ21: 0.5023
C23: effect, % | D23: AUPRC | G23: Recall | J23: F1 | N23: AUPRC | O23: For reference | R23: AUPRC | S23: For reference | V23: AUPRC | W23: For reference | Z23: AUPRC | AA23: For reference | AD23: AUPRC | AE23: For reference | AH23: AUPRC | AI23: For reference | AL23: AUPRC | AM23: For reference | AP23: AUPRC | AQ23: For reference | AT23: AUPRC | AU23: For reference | AX23: AUPRC | AY23: For reference
D24: mean | E24: σ | F24: CV | G24: mean | H24: σ | I24: CV | J24: mean | K24: σ | L24: CV | O24: Recall | P24: F1 | S24: Recall | T24: F1 | W24: Recall | X24: F1 | AA24: Recall | AB24: F1 | AE24: Recall | AF24: F1 | AI24: Recall | AJ24: F1 | AM24: Recall | AN24: F1 | AQ24: Recall | AR24: F1 | AU24: Recall | AV24: F1 | AY24: Recall | AZ24: F1
B25: LR | C25: =D26/D25-1 -> 0.027527461 | D25: =(N25+R25+V25+Z25+AD25+AH25+AL25+AP25+AT25+AX25)/10 -> 0.97321 | E25: =SQRT(((N25-D25)^2+(R25-D25)^2+(V25-D25)^2+(Z25-D25)^2+(AD25-D25)^2+(AH25-D25)^2+(AL25-D25)^2+(AP25-D25)^2+(AT25-D25)^2+(AX25-D25)^2)/10) -> 0.0027620463 | F25: =E25/D25 -> 0.0028380785 | G25: =(O25+S25+W25+AA25+AE25+AI25+AM25+AQ25+AU25+AY25)/10 -> 0.918 | H25: =SQRT(((O25-G25)^2+(S25-G25)^2+(W25-G25)^2+(AA25-G25)^2+(AE25-G25)^2+(AI25-G25)^2+(AM25-G25)^2+(AQ25-G25)^2+(AU25-G25)^2+(AY25-G25)^2)/10) -> 0.0087177979 | I25: =H25/G25 -> 0.0094965119 | J25: =(P25+T25+X25+AB25+AF25+AJ25+AN25+AR25+AV25+AZ25)/10 -> 0.94058 | K25: =SQRT(((P25-J25)^2+(T25-J25)^2+(X25-J25)^2+(AB25-J25)^2+(AF25-J25)^2+(AJ25-J25)^2+(AN25-J25)^2+(AR25-J25)^2+(AV25-J25)^2+(AZ25-J25)^2)/10) -> 0.0045369153 | L25: =K25/J25 -> 0.0048235294 | N25: 0.9749 | O25: 0.91 | P25: 0.9381 | R25: 0.9766 | S25: 0.91 | T25: 0.943 | V25: 0.9675 | W25: 0.92 | X25: 0.9293 | Z25: 0.9766 | AA25: 0.91 | AB25: 0.943 | AD25: 0.9712 | AE25: 0.93 | AF25: 0.9442 | AH25: 0.9749 | AI25: 0.91 | AJ25: 0.9381 | AL25: 0.9712 | AM25: 0.93 | AN25: 0.9442 | AP25: 0.9712 | AQ25: 0.93 | AR25: 0.9442 | AT25: 0.9731 | AU25: 0.92 | AV25: 0.9436 | AX25: 0.9749 | AY25: 0.91 | AZ25: 0.9381
B26: CLT-TAB without SQP | D26: =(N26+R26+V26+Z26+AD26+AH26+AL26+AP26+AT26+AX26)/10 -> 1 | E26: =SQRT(((N26-D26)^2+(R26-D26)^2+(V26-D26)^2+(Z26-D26)^2+(AD26-D26)^2+(AH26-D26)^2+(AL26-D26)^2+(AP26-D26)^2+(AT26-D26)^2+(AX26-D26)^2)/10) -> 0 | F26: =E26/D26 -> 0 | G26: =(O26+S26+W26+AA26+AE26+AI26+AM26+AQ26+AU26+AY26)/10 -> 1 | H26: =SQRT(((O26-G26)^2+(S26-G26)^2+(W26-G26)^2+(AA26-G26)^2+(AE26-G26)^2+(AI26-G26)^2+(AM26-G26)^2+(AQ26-G26)^2+(AU26-G26)^2+(AY26-G26)^2)/10) -> 0 | I26: =H26/G26 -> 0 | J26: =(P26+T26+X26+AB26+AF26+AJ26+AN26+AR26+AV26+AZ26)/10 -> 1 | K26: =SQRT(((P26-J26)^2+(T26-J26)^2+(X26-J26)^2+(AB26-J26)^2+(AF26-J26)^2+(AJ26-J26)^2+(AN26-J26)^2+(AR26-J26)^2+(AV26-J26)^2+(AZ26-J26)^2)/10) -> 0 | L26: =K26/J26 -> 0 | N26: 1 | O26: 1 | P26: 1 | R26: 1 | S26: 1 | T26: 1 | V26: 1 | W26: 1 | X26: 1 | Z26: 1 | AA26: 1 | AB26: 1 | AD26: 1 | AE26: 1 | AF26: 1 | AH26: 1 | AI26: 1 | AJ26: 1 | AL26: 1 | AM26: 1 | AN26: 1 | AP26: 1 | AQ26: 1 | AR26: 1 | AT26: 1 | AU26: 1 | AV26: 1 | AX26: 1 | AY26: 1 | AZ26: 1
B27: FT-transformer | C27: =D26/D27-1 -> 0.0023053022 | D27: =(N27+R27+V27+Z27+AD27+AH27+AL27+AP27+AT27+AX27)/10 -> 0.9977 | E27: =SQRT(((N27-D27)^2+(R27-D27)^2+(V27-D27)^2+(Z27-D27)^2+(AD27-D27)^2+(AH27-D27)^2+(AL27-D27)^2+(AP27-D27)^2+(AT27-D27)^2+(AX27-D27)^2)/10) -> 0.001150652 | F27: =E27/D27 -> 0.0011533046 | G27: =(O27+S27+W27+AA27+AE27+AI27+AM27+AQ27+AU27+AY27)/10 -> 0.957 | H27: =SQRT(((O27-G27)^2+(S27-G27)^2+(W27-G27)^2+(AA27-G27)^2+(AE27-G27)^2+(AI27-G27)^2+(AM27-G27)^2+(AQ27-G27)^2+(AU27-G27)^2+(AY27-G27)^2)/10) -> 0.013453624 | I27: =H27/G27 -> 0.014058123 | J27: =(P27+T27+X27+AB27+AF27+AJ27+AN27+AR27+AV27+AZ27)/10 -> 0.97156 | K27: =SQRT(((P27-J27)^2+(T27-J27)^2+(X27-J27)^2+(AB27-J27)^2+(AF27-J27)^2+(AJ27-J27)^2+(AN27-J27)^2+(AR27-J27)^2+(AV27-J27)^2+(AZ27-J27)^2)/10) -> 0.0047628143 | L27: =K27/J27 -> 0.0049022338 | N27: 0.9983 | O27: 0.98 | P27: 0.9751 | R27: 0.9979 | S27: 0.94 | T27: 0.9691 | V27: 0.9984 | W27: 0.94 | X27: 0.9641 | Z27: 0.9983 | AA27: 0.96 | AB27: 0.9796 | AD27: 0.9977 | AE27: 0.95 | AF27: 0.9694 | AH27: 0.9979 | AI27: 0.97 | AJ27: 0.9749 | AL27: 0.9988 | AM27: 0.96 | AN27: 0.9746 | AP27: 0.9948 | AQ27: 0.94 | AR27: 0.9691 | AT27: 0.9964 | AU27: 0.96 | AV27: 0.9648 | AX27: 0.9985 | AY27: 0.97 | AZ27: 0.9749
B28: CatBoost | C28: =D26/D28-1 -> 0.0013718795 | D28: =(N28+R28+V28+Z28+AD28+AH28+AL28+AP28+AT28+AX28)/10 -> 0.99863 | E28: =SQRT(((N28-D28)^2+(R28-D28)^2+(V28-D28)^2+(Z28-D28)^2+(AD28-D28)^2+(AH28-D28)^2+(AL28-D28)^2+(AP28-D28)^2+(AT28-D28)^2+(AX28-D28)^2)/10) -> 0.0018401359 | F28: =E28/D28 -> 0.0018426603 | G28: =(O28+S28+W28+AA28+AE28+AI28+AM28+AQ28+AU28+AY28)/10 -> 0.946 | H28: =SQRT(((O28-G28)^2+(S28-G28)^2+(W28-G28)^2+(AA28-G28)^2+(AE28-G28)^2+(AI28-G28)^2+(AM28-G28)^2+(AQ28-G28)^2+(AU28-G28)^2+(AY28-G28)^2)/10) -> 0.028354894 | I28: =H28/G28 -> 0.029973461 | J28: =(P28+T28+X28+AB28+AF28+AJ28+AN28+AR28+AV28+AZ28)/10 -> 0.97205 | K28: =SQRT(((P28-J28)^2+(T28-J28)^2+(X28-J28)^2+(AB28-J28)^2+(AF28-J28)^2+(AJ28-J28)^2+(AN28-J28)^2+(AR28-J28)^2+(AV28-J28)^2+(AZ28-J28)^2)/10) -> 0.015176841 | L28: =K28/J28 -> 0.015613231 | N28: 0.9988 | O28: 0.97 | P28: 0.9848 | R28: 1 | S28: 0.97 | T28: 0.9848 | V28: 0.9993 | W28: 0.94 | X28: 0.9691 | Z28: 0.9975 | AA28: 0.95 | AB28: 0.9744 | AD28: 1 | AE28: 0.98 | AF28: 0.9899 | AH28: 0.9986 | AI28: 0.89 | AJ28: 0.9418 | AL28: 0.9997 | AM28: 0.96 | AN28: 0.9796 | AP28: 0.9936 | AQ28: 0.9 | AR28: 0.9474 | AT28: 0.9988 | AU28: 0.94 | AV28: 0.9691 | AX28: 1 | AY28: 0.96 | AZ28: 0.9796
B29: SCARF | C29: =D26/D29-1 -> 1.0190192 | D29: =(N29+R29+V29+Z29+AD29+AH29+AL29+AP29+AT29+AX29)/10 -> 0.49529 | E29: =SQRT(((N29-D29)^2+(R29-D29)^2+(V29-D29)^2+(Z29-D29)^2+(AD29-D29)^2+(AH29-D29)^2+(AL29-D29)^2+(AP29-D29)^2+(AT29-D29)^2+(AX29-D29)^2)/10) -> 0.069659665 | F29: =E29/D29 -> 0.1406442 | G29: =(O29+S29+W29+AA29+AE29+AI29+AM29+AQ29+AU29+AY29)/10 -> 0.517 | H29: =SQRT(((O29-G29)^2+(S29-G29)^2+(W29-G29)^2+(AA29-G29)^2+(AE29-G29)^2+(AI29-G29)^2+(AM29-G29)^2+(AQ29-G29)^2+(AU29-G29)^2+(AY29-G29)^2)/10) -> 0.044056782 | I29: =H29/G29 -> 0.085216212 | J29: =(P29+T29+X29+AB29+AF29+AJ29+AN29+AR29+AV29+AZ29)/10 -> 0.47686 | K29: =SQRT(((P29-J29)^2+(T29-J29)^2+(X29-J29)^2+(AB29-J29)^2+(AF29-J29)^2+(AJ29-J29)^2+(AN29-J29)^2+(AR29-J29)^2+(AV29-J29)^2+(AZ29-J29)^2)/10) -> 0.032867072 | L29: =K29/J29 -> 0.068923943 | N29: 0.4624 | O29: 0.55 | P29: 0.4955 | R29: 0.6069 | S29: 0.5 | T29: 0.4908 | V29: 0.6332 | W29: 0.42 | X29: 0.4 | Z29: 0.4683 | AA29: 0.56 | AB29: 0.4956 | AD29: 0.529 | AE29: 0.56 | AF29: 0.4934 | AH29: 0.4645 | AI29: 0.52 | AJ29: 0.486 | AL29: 0.4285 | AM29: 0.55 | AN29: 0.5093 | AP29: 0.4951 | AQ29: 0.48 | AR29: 0.4593 | AT29: 0.4124 | AU29: 0.48 | AV29: 0.4364 | AX29: 0.4526 | AY29: 0.55 | AZ29: 0.5023
C31: effect, % | D31: AUPRC | G31: Recall | J31: F1 | N31: AUPRC | O31: For reference | R31: AUPRC | S31: For reference | V31: AUPRC | W31: For reference | Z31: AUPRC | AA31: For reference | AD31: AUPRC | AE31: For reference | AH31: AUPRC | AI31: For reference | AL31: AUPRC | AM31: For reference | AP31: AUPRC | AQ31: For reference | AT31: AUPRC | AU31: For reference | AX31: AUPRC | AY31: For reference
D32: mean | E32: σ | F32: CV | G32: mean | H32: σ | I32: CV | J32: mean | K32: σ | L32: CV | O32: Recall | P32: F1 | S32: Recall | T32: F1 | W32: Recall | X32: F1 | AA32: Recall | AB32: F1 | AE32: Recall | AF32: F1 | AI32: Recall | AJ32: F1 | AM32: Recall | AN32: F1 | AQ32: Recall | AR32: F1 | AU32: Recall | AV32: F1 | AY32: Recall | AZ32: F1
B33: LR | C33: =D34/D33-1 -> 0.027527461 | D33: =(N33+R33+V33+Z33+AD33+AH33+AL33+AP33+AT33+AX33)/10 -> 0.97321 | E33: =SQRT(((N33-D33)^2+(R33-D33)^2+(V33-D33)^2+(Z33-D33)^2+(AD33-D33)^2+(AH33-D33)^2+(AL33-D33)^2+(AP33-D33)^2+(AT33-D33)^2+(AX33-D33)^2)/10) -> 0.0027620463 | F33: =E33/D33 -> 0.0028380785 | G33: =(O33+S33+W33+AA33+AE33+AI33+AM33+AQ33+AU33+AY33)/10 -> 0.918 | H33: =SQRT(((O33-G33)^2+(S33-G33)^2+(W33-G33)^2+(AA33-G33)^2+(AE33-G33)^2+(AI33-G33)^2+(AM33-G33)^2+(AQ33-G33)^2+(AU33-G33)^2+(AY33-G33)^2)/10) -> 0.0087177979 | I33: =H33/G33 -> 0.0094965119 | J33: =(P33+T33+X33+AB33+AF33+AJ33+AN33+AR33+AV33+AZ33)/10 -> 0.94058 | K33: =SQRT(((P33-J33)^2+(T33-J33)^2+(X33-J33)^2+(AB33-J33)^2+(AF33-J33)^2+(AJ33-J33)^2+(AN33-J33)^2+(AR33-J33)^2+(AV33-J33)^2+(AZ33-J33)^2)/10) -> 0.0045369153 | L33: =K33/J33 -> 0.0048235294 | N33: 0.9749 | O33: 0.91 | P33: 0.9381 | R33: 0.9766 | S33: 0.91 | T33: 0.943 | V33: 0.9675 | W33: 0.92 | X33: 0.9293 | Z33: 0.9766 | AA33: 0.91 | AB33: 0.943 | AD33: 0.9712 | AE33: 0.93 | AF33: 0.9442 | AH33: 0.9749 | AI33: 0.91 | AJ33: 0.9381 | AL33: 0.9712 | AM33: 0.93 | AN33: 0.9442 | AP33: 0.9712 | AQ33: 0.93 | AR33: 0.9442 | AT33: 0.9731 | AU33: 0.92 | AV33: 0.9436 | AX33: 0.9749 | AY33: 0.91 | AZ33: 0.9381
B34: CLT-TAB without CATA and SQP | D34: =(N34+R34+V34+Z34+AD34+AH34+AL34+AP34+AT34+AX34)/10 -> 1 | E34: =SQRT(((N34-D34)^2+(R34-D34)^2+(V34-D34)^2+(Z34-D34)^2+(AD34-D34)^2+(AH34-D34)^2+(AL34-D34)^2+(AP34-D34)^2+(AT34-D34)^2+(AX34-D34)^2)/10) -> 0 | F34: =E34/D34 -> 0 | G34: =(O34+S34+W34+AA34+AE34+AI34+AM34+AQ34+AU34+AY34)/10 -> 1 | H34: =SQRT(((O34-G34)^2+(S34-G34)^2+(W34-G34)^2+(AA34-G34)^2+(AE34-G34)^2+(AI34-G34)^2+(AM34-G34)^2+(AQ34-G34)^2+(AU34-G34)^2+(AY34-G34)^2)/10) -> 0 | I34: =H34/G34 -> 0 | J34: =(P34+T34+X34+AB34+AF34+AJ34+AN34+AR34+AV34+AZ34)/10 -> 1 | K34: =SQRT(((P34-J34)^2+(T34-J34)^2+(X34-J34)^2+(AB34-J34)^2+(AF34-J34)^2+(AJ34-J34)^2+(AN34-J34)^2+(AR34-J34)^2+(AV34-J34)^2+(AZ34-J34)^2)/10) -> 0 | L34: =K34/J34 -> 0 | N34: 1 | O34: 1 | P34: 1 | R34: 1 | S34: 1 | T34: 1 | V34: 1 | W34: 1 | X34: 1 | Z34: 1 | AA34: 1 | AB34: 1 | AD34: 1 | AE34: 1 | AF34: 1 | AH34: 1 | AI34: 1 | AJ34: 1 | AL34: 1 | AM34: 1 | AN34: 1 | AP34: 1 | AQ34: 1 | AR34: 1 | AT34: 1 | AU34: 1 | AV34: 1 | AX34: 1 | AY34: 1 | AZ34: 1
B35: FT-transformer | C35: =D34/D35-1 -> 0.0023053022 | D35: =(N35+R35+V35+Z35+AD35+AH35+AL35+AP35+AT35+AX35)/10 -> 0.9977 | E35: =SQRT(((N35-D35)^2+(R35-D35)^2+(V35-D35)^2+(Z35-D35)^2+(AD35-D35)^2+(AH35-D35)^2+(AL35-D35)^2+(AP35-D35)^2+(AT35-D35)^2+(AX35-D35)^2)/10) -> 0.001150652 | F35: =E35/D35 -> 0.0011533046 | G35: =(O35+S35+W35+AA35+AE35+AI35+AM35+AQ35+AU35+AY35)/10 -> 0.957 | H35: =SQRT(((O35-G35)^2+(S35-G35)^2+(W35-G35)^2+(AA35-G35)^2+(AE35-G35)^2+(AI35-G35)^2+(AM35-G35)^2+(AQ35-G35)^2+(AU35-G35)^2+(AY35-G35)^2)/10) -> 0.013453624 | I35: =H35/G35 -> 0.014058123 | J35: =(P35+T35+X35+AB35+AF35+AJ35+AN35+AR35+AV35+AZ35)/10 -> 0.97156 | K35: =SQRT(((P35-J35)^2+(T35-J35)^2+(X35-J35)^2+(AB35-J35)^2+(AF35-J35)^2+(AJ35-J35)^2+(AN35-J35)^2+(AR35-J35)^2+(AV35-J35)^2+(AZ35-J35)^2)/10) -> 0.0047628143 | L35: =K35/J35 -> 0.0049022338 | N35: 0.9983 | O35: 0.98 | P35: 0.9751 | R35: 0.9979 | S35: 0.94 | T35: 0.9691 | V35: 0.9984 | W35: 0.94 | X35: 0.9641 | Z35: 0.9983 | AA35: 0.96 | AB35: 0.9796 | AD35: 0.9977 | AE35: 0.95 | AF35: 0.9694 | AH35: 0.9979 | AI35: 0.97 | AJ35: 0.9749 | AL35: 0.9988 | AM35: 0.96 | AN35: 0.9746 | AP35: 0.9948 | AQ35: 0.94 | AR35: 0.9691 | AT35: 0.9964 | AU35: 0.96 | AV35: 0.9648 | AX35: 0.9985 | AY35: 0.97 | AZ35: 0.9749
B36: CatBoost | C36: =D34/D36-1 -> 0.0013718795 | D36: =(N36+R36+V36+Z36+AD36+AH36+AL36+AP36+AT36+AX36)/10 -> 0.99863 | E36: =SQRT(((N36-D36)^2+(R36-D36)^2+(V36-D36)^2+(Z36-D36)^2+(AD36-D36)^2+(AH36-D36)^2+(AL36-D36)^2+(AP36-D36)^2+(AT36-D36)^2+(AX36-D36)^2)/10) -> 0.0018401359 | F36: =E36/D36 -> 0.0018426603 | G36: =(O36+S36+W36+AA36+AE36+AI36+AM36+AQ36+AU36+AY36)/10 -> 0.946 | H36: =SQRT(((O36-G36)^2+(S36-G36)^2+(W36-G36)^2+(AA36-G36)^2+(AE36-G36)^2+(AI36-G36)^2+(AM36-G36)^2+(AQ36-G36)^2+(AU36-G36)^2+(AY36-G36)^2)/10) -> 0.028354894 | I36: =H36/G36 -> 0.029973461 | J36: =(P36+T36+X36+AB36+AF36+AJ36+AN36+AR36+AV36+AZ36)/10 -> 0.97205 | K36: =SQRT(((P36-J36)^2+(T36-J36)^2+(X36-J36)^2+(AB36-J36)^2+(AF36-J36)^2+(AJ36-J36)^2+(AN36-J36)^2+(AR36-J36)^2+(AV36-J36)^2+(AZ36-J36)^2)/10) -> 0.015176841 | L36: =K36/J36 -> 0.015613231 | N36: 0.9988 | O36: 0.97 | P36: 0.9848 | R36: 1 | S36: 0.97 | T36: 0.9848 | V36: 0.9993 | W36: 0.94 | X36: 0.9691 | Z36: 0.9975 | AA36: 0.95 | AB36: 0.9744 | AD36: 1 | AE36: 0.98 | AF36: 0.9899 | AH36: 0.9986 | AI36: 0.89 | AJ36: 0.9418 | AL36: 0.9997 | AM36: 0.96 | AN36: 0.9796 | AP36: 0.9936 | AQ36: 0.9 | AR36: 0.9474 | AT36: 0.9988 | AU36: 0.94 | AV36: 0.9691 | AX36: 1 | AY36: 0.96 | AZ36: 0.9796
B37: SCARF | C37: =D34/D37-1 -> 1.0190192 | D37: =(N37+R37+V37+Z37+AD37+AH37+AL37+AP37+AT37+AX37)/10 -> 0.49529 | E37: =SQRT(((N37-D37)^2+(R37-D37)^2+(V37-D37)^2+(Z37-D37)^2+(AD37-D37)^2+(AH37-D37)^2+(AL37-D37)^2+(AP37-D37)^2+(AT37-D37)^2+(AX37-D37)^2)/10) -> 0.069659665 | F37: =E37/D37 -> 0.1406442 | G37: =(O37+S37+W37+AA37+AE37+AI37+AM37+AQ37+AU37+AY37)/10 -> 0.517 | H37: =SQRT(((O37-G37)^2+(S37-G37)^2+(W37-G37)^2+(AA37-G37)^2+(AE37-G37)^2+(AI37-G37)^2+(AM37-G37)^2+(AQ37-G37)^2+(AU37-G37)^2+(AY37-G37)^2)/10) -> 0.044056782 | I37: =H37/G37 -> 0.085216212 | J37: =(P37+T37+X37+AB37+AF37+AJ37+AN37+AR37+AV37+AZ37)/10 -> 0.47686 | K37: =SQRT(((P37-J37)^2+(T37-J37)^2+(X37-J37)^2+(AB37-J37)^2+(AF37-J37)^2+(AJ37-J37)^2+(AN37-J37)^2+(AR37-J37)^2+(AV37-J37)^2+(AZ37-J37)^2)/10) -> 0.032867072 | L37: =K37/J37 -> 0.068923943 | N37: 0.4624 | O37: 0.55 | P37: 0.4955 | R37: 0.6069 | S37: 0.5 | T37: 0.4908 | V37: 0.6332 | W37: 0.42 | X37: 0.4 | Z37: 0.4683 | AA37: 0.56 | AB37: 0.4956 | AD37: 0.529 | AE37: 0.56 | AF37: 0.4934 | AH37: 0.4645 | AI37: 0.52 | AJ37: 0.486 | AL37: 0.4285 | AM37: 0.55 | AN37: 0.5093 | AP37: 0.4951 | AQ37: 0.48 | AR37: 0.4593 | AT37: 0.4124 | AU37: 0.48 | AV37: 0.4364 | AX37: 0.4526 | AY37: 0.55 | AZ37: 0.5023

Sheet Epsilon30
B1: Overview
B2: The Epsilon dataset is a synthetic binary classification benchmark originally introduced for the PASCAL Large Scale Learning Challenge (2008). It was designed to evaluate the performance of machine learning algorithms on high‑dimensional, noisy, and highly nonlinear data, simulating a complex classification task where the decision boundary is intricate and difficult to learn. The dataset was generated using a random non‑linear transformation of a 2,000‑dimensional input space, with a binary target that is derived from a hidden function, making it a challenging testbed for both linear and non‑linear models. It has since become a standard benchmark for assessing scalability and robustness of modern machine learning methods, including kernel methods, gradient‑boosted trees, and deep learning architectures, particularly in large‑scale and high‑dimensional settings.
B3: We used the Epsilon dataset (the first 30 features were selected), which contains 50 000 instances (random sample from the train set) with a 49,9 % anomaly rate. It comprises 30 numerical and 0 categorical features. The data were used after preprocessing (missing values, duplicates, and constant features were removed). F1 and Recall scores were obtained with a threshold of 0.5. We used 200 instances for finetuning, of which 100 were anomalies, and the same number (200 instances, 100 anomalies) for testing.
B5: Random AUPRC | C5: 0.5 | N5: Seed
G6: For reference | N6: 42 | R6: 43 | V6: 44 | Z6: 45 | AD6: 46 | AH6: 47 | AL6: 48 | AP6: 49 | AT6: 50 | AX6: 51
C7: effect, % | D7: AUPRC | G7: Recall | J7: F1 | N7: AUPRC | O7: For reference | R7: AUPRC | S7: For reference | V7: AUPRC | W7: For reference | Z7: AUPRC | AA7: For reference | AD7: AUPRC | AE7: For reference | AH7: AUPRC | AI7: For reference | AL7: AUPRC | AM7: For reference | AP7: AUPRC | AQ7: For reference | AT7: AUPRC | AU7: For reference | AX7: AUPRC | AY7: For reference
D8: mean | E8: σ | F8: CV | G8: mean | H8: σ | I8: CV | J8: mean | K8: σ | L8: CV | O8: Recall | P8: F1 | S8: Recall | T8: F1 | W8: Recall | X8: F1 | AA8: Recall | AB8: F1 | AE8: Recall | AF8: F1 | AI8: Recall | AJ8: F1 | AM8: Recall | AN8: F1 | AQ8: Recall | AR8: F1 | AU8: Recall | AV8: F1 | AY8: Recall | AZ8: F1
B9: LR | C9: =D10/D9-1 -> 0.039208222 | D9: =(N9+R9+V9+Z9+AD9+AH9+AL9+AP9+AT9+AX9)/10 -> 0.55167 | E9: =SQRT(((N9-D9)^2+(R9-D9)^2+(V9-D9)^2+(Z9-D9)^2+(AD9-D9)^2+(AH9-D9)^2+(AL9-D9)^2+(AP9-D9)^2+(AT9-D9)^2+(AX9-D9)^2)/10) -> 0.0032177787 | F9: =E9/D9 -> 0.0058327963 | G9: =(O9+S9+W9+AA9+AE9+AI9+AM9+AQ9+AU9+AY9)/10 -> 0.443 | H9: =SQRT(((O9-G9)^2+(S9-G9)^2+(W9-G9)^2+(AA9-G9)^2+(AE9-G9)^2+(AI9-G9)^2+(AM9-G9)^2+(AQ9-G9)^2+(AU9-G9)^2+(AY9-G9)^2)/10) -> 0.011 | I9: =H9/G9 -> 0.0248307 | J9: =(P9+T9+X9+AB9+AF9+AJ9+AN9+AR9+AV9+AZ9)/10 -> 0.48331 | K9: =SQRT(((P9-J9)^2+(T9-J9)^2+(X9-J9)^2+(AB9-J9)^2+(AF9-J9)^2+(AJ9-J9)^2+(AN9-J9)^2+(AR9-J9)^2+(AV9-J9)^2+(AZ9-J9)^2)/10) -> 0.0071832374 | L9: =K9/J9 -> 0.014862588 | N9: 0.5532 | O9: 0.44 | P9: 0.4783 | R9: 0.5542 | S9: 0.44 | T9: 0.4835 | V9: 0.5486 | W9: 0.46 | X9: 0.4946 | Z9: 0.5545 | AA9: 0.44 | AB9: 0.4862 | AD9: 0.5486 | AE9: 0.46 | AF9: 0.4946 | AH9: 0.5542 | AI9: 0.44 | AJ9: 0.4835 | AL9: 0.5554 | AM9: 0.44 | AN9: 0.4809 | AP9: 0.5453 | AQ9: 0.42 | AR9: 0.4693 | AT9: 0.5495 | AU9: 0.45 | AV9: 0.4839 | AX9: 0.5532 | AY9: 0.44 | AZ9: 0.4783
B10: CLT-TAB | D10: =(N10+R10+V10+Z10+AD10+AH10+AL10+AP10+AT10+AX10)/10 -> 0.5733 | E10: =SQRT(((N10-D10)^2+(R10-D10)^2+(V10-D10)^2+(Z10-D10)^2+(AD10-D10)^2+(AH10-D10)^2+(AL10-D10)^2+(AP10-D10)^2+(AT10-D10)^2+(AX10-D10)^2)/10) -> 0.018746733 | F10: =E10/D10 -> 0.032699691 | G10: =(O10+S10+W10+AA10+AE10+AI10+AM10+AQ10+AU10+AY10)/10 -> 0.511 | H10: =SQRT(((O10-G10)^2+(S10-G10)^2+(W10-G10)^2+(AA10-G10)^2+(AE10-G10)^2+(AI10-G10)^2+(AM10-G10)^2+(AQ10-G10)^2+(AU10-G10)^2+(AY10-G10)^2)/10) -> 0.022113344 | I10: =H10/G10 -> 0.043274647 | J10: =(P10+T10+X10+AB10+AF10+AJ10+AN10+AR10+AV10+AZ10)/10 -> 0.53385 | K10: =SQRT(((P10-J10)^2+(T10-J10)^2+(X10-J10)^2+(AB10-J10)^2+(AF10-J10)^2+(AJ10-J10)^2+(AN10-J10)^2+(AR10-J10)^2+(AV10-J10)^2+(AZ10-J10)^2)/10) -> 0.01955762 | L10: =K10/J10 -> 0.036635047 | N10: 0.5688 | O10: 0.55 | P10: 0.5641 | R10: 0.5785 | S10: 0.53 | T10: 0.5492 | V10: 0.5806 | W10: 0.5 | X10: 0.5266 | Z10: 0.573 | AA10: 0.49 | AB10: 0.5128 | AD10: 0.6039 | AE10: 0.5 | AF10: 0.5291 | AH10: 0.5735 | AI10: 0.52 | AJ10: 0.5445 | AL10: 0.5941 | AM10: 0.54 | AN10: 0.5654 | AP10: 0.5295 | AQ10: 0.49 | AR10: 0.5158 | AT10: 0.5673 | AU10: 0.48 | AV10: 0.5106 | AX10: 0.5638 | AY10: 0.51 | AZ10: 0.5204
B11: FT-transformer | C11: =D10/D11-1 -> 0.050134633 | D11: =(N11+R11+V11+Z11+AD11+AH11+AL11+AP11+AT11+AX11)/10 -> 0.54593 | E11: =SQRT(((N11-D11)^2+(R11-D11)^2+(V11-D11)^2+(Z11-D11)^2+(AD11-D11)^2+(AH11-D11)^2+(AL11-D11)^2+(AP11-D11)^2+(AT11-D11)^2+(AX11-D11)^2)/10) -> 0.025933031 | F11: =E11/D11 -> 0.047502484 | G11: =(O11+S11+W11+AA11+AE11+AI11+AM11+AQ11+AU11+AY11)/10 -> 0.454 | H11: =SQRT(((O11-G11)^2+(S11-G11)^2+(W11-G11)^2+(AA11-G11)^2+(AE11-G11)^2+(AI11-G11)^2+(AM11-G11)^2+(AQ11-G11)^2+(AU11-G11)^2+(AY11-G11)^2)/10) -> 0.040792156 | I11: =H11/G11 -> 0.089850564 | J11: =(P11+T11+X11+AB11+AF11+AJ11+AN11+AR11+AV11+AZ11)/10 -> 0.48775 | K11: =SQRT(((P11-J11)^2+(T11-J11)^2+(X11-J11)^2+(AB11-J11)^2+(AF11-J11)^2+(AJ11-J11)^2+(AN11-J11)^2+(AR11-J11)^2+(AV11-J11)^2+(AZ11-J11)^2)/10) -> 0.032761296 | L11: =K11/J11 -> 0.067168213 | N11: 0.5676 | O11: 0.5 | P11: 0.5102 | R11: 0.5608 | S11: 0.48 | T11: 0.5106 | V11: 0.5518 | W11: 0.46 | X11: 0.4973 | Z11: 0.5452 | AA11: 0.48 | AB11: 0.5106 | AD11: 0.5091 | AE11: 0.46 | AF11: 0.4792 | AH11: 0.5435 | AI11: 0.5 | AJ11: 0.5291 | AL11: 0.5377 | AM11: 0.42 | AN11: 0.4719 | AP11: 0.5776 | AQ11: 0.38 | AR11: 0.4343 | AT11: 0.5732 | AU11: 0.47 | AV11: 0.5081 | AX11: 0.4928 | AY11: 0.39 | AZ11: 0.4262
B12: CatBoost | C12: =D10/D12-1 -> 0.11339846 | D12: =(N12+R12+V12+Z12+AD12+AH12+AL12+AP12+AT12+AX12)/10 -> 0.51491 | E12: =SQRT(((N12-D12)^2+(R12-D12)^2+(V12-D12)^2+(Z12-D12)^2+(AD12-D12)^2+(AH12-D12)^2+(AL12-D12)^2+(AP12-D12)^2+(AT12-D12)^2+(AX12-D12)^2)/10) -> 0.027687522 | F12: =E12/D12 -> 0.053771577 | G12: =(O12+S12+W12+AA12+AE12+AI12+AM12+AQ12+AU12+AY12)/10 -> 0.475 | H12: =SQRT(((O12-G12)^2+(S12-G12)^2+(W12-G12)^2+(AA12-G12)^2+(AE12-G12)^2+(AI12-G12)^2+(AM12-G12)^2+(AQ12-G12)^2+(AU12-G12)^2+(AY12-G12)^2)/10) -> 0.037749172 | I12: =H12/G12 -> 0.079471941 | J12: =(P12+T12+X12+AB12+AF12+AJ12+AN12+AR12+AV12+AZ12)/10 -> 0.47674 | K12: =SQRT(((P12-J12)^2+(T12-J12)^2+(X12-J12)^2+(AB12-J12)^2+(AF12-J12)^2+(AJ12-J12)^2+(AN12-J12)^2+(AR12-J12)^2+(AV12-J12)^2+(AZ12-J12)^2)/10) -> 0.030325046 | L12: =K12/J12 -> 0.063609191 | N12: 0.5273 | O12: 0.45 | P12: 0.4592 | R12: 0.5417 | S12: 0.5 | T12: 0.5128 | V12: 0.4961 | W12: 0.44 | X12: 0.4444 | Z12: 0.4497 | AA12: 0.44 | AB12: 0.4607 | AD12: 0.5032 | AE12: 0.41 | AF12: 0.4184 | AH12: 0.5032 | AI12: 0.52 | AJ12: 0.5123 | AL12: 0.5158 | AM12: 0.53 | AN12: 0.5121 | AP12: 0.5537 | AQ12: 0.47 | AR12: 0.4724 | AT12: 0.5287 | AU12: 0.51 | AV12: 0.4951 | AX12: 0.5297 | AY12: 0.48 | AZ12: 0.48
B13: SCARF | C13: =D10/D13-1 -> 0.072250173 | D13: =(N13+R13+V13+Z13+AD13+AH13+AL13+AP13+AT13+AX13)/10 -> 0.53467 | E13: =SQRT(((N13-D13)^2+(R13-D13)^2+(V13-D13)^2+(Z13-D13)^2+(AD13-D13)^2+(AH13-D13)^2+(AL13-D13)^2+(AP13-D13)^2+(AT13-D13)^2+(AX13-D13)^2)/10) -> 0.015332583 | F13: =E13/D13 -> 0.028676722 | G13: =(O13+S13+W13+AA13+AE13+AI13+AM13+AQ13+AU13+AY13)/10 -> 0.481 | H13: =SQRT(((O13-G13)^2+(S13-G13)^2+(W13-G13)^2+(AA13-G13)^2+(AE13-G13)^2+(AI13-G13)^2+(AM13-G13)^2+(AQ13-G13)^2+(AU13-G13)^2+(AY13-G13)^2)/10) -> 0.036180105 | I13: =H13/G13 -> 0.075218514 | J13: =(P13+T13+X13+AB13+AF13+AJ13+AN13+AR13+AV13+AZ13)/10 -> 0.48773 | K13: =SQRT(((P13-J13)^2+(T13-J13)^2+(X13-J13)^2+(AB13-J13)^2+(AF13-J13)^2+(AJ13-J13)^2+(AN13-J13)^2+(AR13-J13)^2+(AV13-J13)^2+(AZ13-J13)^2)/10) -> 0.024504614 | L13: =K13/J13 -> 0.050242171 | N13: 0.5427 | O13: 0.41 | P13: 0.4481 | R13: 0.5339 | S13: 0.5 | T13: 0.48 | V13: 0.5059 | W13: 0.43 | X13: 0.4503 | Z13: 0.5243 | AA13: 0.5 | AB13: 0.5102 | AD13: 0.5543 | AE13: 0.54 | AF13: 0.5294 | AH13: 0.5136 | AI13: 0.49 | AJ13: 0.4949 | AL13: 0.5531 | AM13: 0.47 | AN13: 0.4724 | AP13: 0.5319 | AQ13: 0.49 | AR13: 0.4949 | AT13: 0.5405 | AU13: 0.47 | AV13: 0.4896 | AX13: 0.5465 | AY13: 0.51 | AZ13: 0.5075
C15: effect, % | D15: AUPRC | G15: Recall | J15: F1 | N15: AUPRC | O15: For reference | R15: AUPRC | S15: For reference | V15: AUPRC | W15: For reference | Z15: AUPRC | AA15: For reference | AD15: AUPRC | AE15: For reference | AH15: AUPRC | AI15: For reference | AL15: AUPRC | AM15: For reference | AP15: AUPRC | AQ15: For reference | AT15: AUPRC | AU15: For reference | AX15: AUPRC | AY15: For reference
D16: mean | E16: σ | F16: CV | G16: mean | H16: σ | I16: CV | J16: mean | K16: σ | L16: CV | O16: Recall | P16: F1 | S16: Recall | T16: F1 | W16: Recall | X16: F1 | AA16: Recall | AB16: F1 | AE16: Recall | AF16: F1 | AI16: Recall | AJ16: F1 | AM16: Recall | AN16: F1 | AQ16: Recall | AR16: F1 | AU16: Recall | AV16: F1 | AY16: Recall | AZ16: F1
B17: LR | C17: =D18/D17-1 -> 0.047202132 | D17: =(N17+R17+V17+Z17+AD17+AH17+AL17+AP17+AT17+AX17)/10 -> 0.55167 | E17: =SQRT(((N17-D17)^2+(R17-D17)^2+(V17-D17)^2+(Z17-D17)^2+(AD17-D17)^2+(AH17-D17)^2+(AL17-D17)^2+(AP17-D17)^2+(AT17-D17)^2+(AX17-D17)^2)/10) -> 0.0032177787 | F17: =E17/D17 -> 0.0058327963 | G17: =(O17+S17+W17+AA17+AE17+AI17+AM17+AQ17+AU17+AY17)/10 -> 0.443 | H17: =SQRT(((O17-G17)^2+(S17-G17)^2+(W17-G17)^2+(AA17-G17)^2+(AE17-G17)^2+(AI17-G17)^2+(AM17-G17)^2+(AQ17-G17)^2+(AU17-G17)^2+(AY17-G17)^2)/10) -> 0.011 | I17: =H17/G17 -> 0.0248307 | J17: =(P17+T17+X17+AB17+AF17+AJ17+AN17+AR17+AV17+AZ17)/10 -> 0.48331 | K17: =SQRT(((P17-J17)^2+(T17-J17)^2+(X17-J17)^2+(AB17-J17)^2+(AF17-J17)^2+(AJ17-J17)^2+(AN17-J17)^2+(AR17-J17)^2+(AV17-J17)^2+(AZ17-J17)^2)/10) -> 0.0071832374 | L17: =K17/J17 -> 0.014862588 | N17: 0.5532 | O17: 0.44 | P17: 0.4783 | R17: 0.5542 | S17: 0.44 | T17: 0.4835 | V17: 0.5486 | W17: 0.46 | X17: 0.4946 | Z17: 0.5545 | AA17: 0.44 | AB17: 0.4862 | AD17: 0.5486 | AE17: 0.46 | AF17: 0.4946 | AH17: 0.5542 | AI17: 0.44 | AJ17: 0.4835 | AL17: 0.5554 | AM17: 0.44 | AN17: 0.4809 | AP17: 0.5453 | AQ17: 0.42 | AR17: 0.4693 | AT17: 0.5495 | AU17: 0.45 | AV17: 0.4839 | AX17: 0.5532 | AY17: 0.44 | AZ17: 0.4783
B18: CLT-TAB without CATA | D18: =(N18+R18+V18+Z18+AD18+AH18+AL18+AP18+AT18+AX18)/10 -> 0.57771 | E18: =SQRT(((N18-D18)^2+(R18-D18)^2+(V18-D18)^2+(Z18-D18)^2+(AD18-D18)^2+(AH18-D18)^2+(AL18-D18)^2+(AP18-D18)^2+(AT18-D18)^2+(AX18-D18)^2)/10) -> 0.017507224 | F18: =E18/D18 -> 0.03030452 | G18: =(O18+S18+W18+AA18+AE18+AI18+AM18+AQ18+AU18+AY18)/10 -> 0.504 | H18: =SQRT(((O18-G18)^2+(S18-G18)^2+(W18-G18)^2+(AA18-G18)^2+(AE18-G18)^2+(AI18-G18)^2+(AM18-G18)^2+(AQ18-G18)^2+(AU18-G18)^2+(AY18-G18)^2)/10) -> 0.016248077 | I18: =H18/G18 -> 0.032238248 | J18: =(P18+T18+X18+AB18+AF18+AJ18+AN18+AR18+AV18+AZ18)/10 -> 0.52791 | K18: =SQRT(((P18-J18)^2+(T18-J18)^2+(X18-J18)^2+(AB18-J18)^2+(AF18-J18)^2+(AJ18-J18)^2+(AN18-J18)^2+(AR18-J18)^2+(AV18-J18)^2+(AZ18-J18)^2)/10) -> 0.011308974 | L18: =K18/J18 -> 0.021422163 | N18: 0.5777 | O18: 0.51 | P18: 0.5312 | R18: 0.6046 | S18: 0.54 | T18: 0.551 | V18: 0.5755 | W18: 0.49 | X18: 0.5158 | Z18: 0.5866 | AA18: 0.51 | AB18: 0.5368 | AD18: 0.5837 | AE18: 0.48 | AF18: 0.5189 | AH18: 0.5701 | AI18: 0.5 | AJ18: 0.5181 | AL18: 0.6055 | AM18: 0.52 | AN18: 0.5417 | AP18: 0.5682 | AQ18: 0.49 | AR18: 0.5185 | AT18: 0.5481 | AU18: 0.5 | AV18: 0.5263 | AX18: 0.5571 | AY18: 0.5 | AZ18: 0.5208
B19: FT-transformer | C19: =D18/D19-1 -> 0.058212591 | D19: =(N19+R19+V19+Z19+AD19+AH19+AL19+AP19+AT19+AX19)/10 -> 0.54593 | E19: =SQRT(((N19-D19)^2+(R19-D19)^2+(V19-D19)^2+(Z19-D19)^2+(AD19-D19)^2+(AH19-D19)^2+(AL19-D19)^2+(AP19-D19)^2+(AT19-D19)^2+(AX19-D19)^2)/10) -> 0.025933031 | F19: =E19/D19 -> 0.047502484 | G19: =(O19+S19+W19+AA19+AE19+AI19+AM19+AQ19+AU19+AY19)/10 -> 0.454 | H19: =SQRT(((O19-G19)^2+(S19-G19)^2+(W19-G19)^2+(AA19-G19)^2+(AE19-G19)^2+(AI19-G19)^2+(AM19-G19)^2+(AQ19-G19)^2+(AU19-G19)^2+(AY19-G19)^2)/10) -> 0.040792156 | I19: =H19/G19 -> 0.089850564 | J19: =(P19+T19+X19+AB19+AF19+AJ19+AN19+AR19+AV19+AZ19)/10 -> 0.48775 | K19: =SQRT(((P19-J19)^2+(T19-J19)^2+(X19-J19)^2+(AB19-J19)^2+(AF19-J19)^2+(AJ19-J19)^2+(AN19-J19)^2+(AR19-J19)^2+(AV19-J19)^2+(AZ19-J19)^2)/10) -> 0.032761296 | L19: =K19/J19 -> 0.067168213 | N19: 0.5676 | O19: 0.5 | P19: 0.5102 | R19: 0.5608 | S19: 0.48 | T19: 0.5106 | V19: 0.5518 | W19: 0.46 | X19: 0.4973 | Z19: 0.5452 | AA19: 0.48 | AB19: 0.5106 | AD19: 0.5091 | AE19: 0.46 | AF19: 0.4792 | AH19: 0.5435 | AI19: 0.5 | AJ19: 0.5291 | AL19: 0.5377 | AM19: 0.42 | AN19: 0.4719 | AP19: 0.5776 | AQ19: 0.38 | AR19: 0.4343 | AT19: 0.5732 | AU19: 0.47 | AV19: 0.5081 | AX19: 0.4928 | AY19: 0.39 | AZ19: 0.4262
B20: CatBoost | C20: =D18/D20-1 -> 0.12196306 | D20: =(N20+R20+V20+Z20+AD20+AH20+AL20+AP20+AT20+AX20)/10 -> 0.51491 | E20: =SQRT(((N20-D20)^2+(R20-D20)^2+(V20-D20)^2+(Z20-D20)^2+(AD20-D20)^2+(AH20-D20)^2+(AL20-D20)^2+(AP20-D20)^2+(AT20-D20)^2+(AX20-D20)^2)/10) -> 0.027687522 | F20: =E20/D20 -> 0.053771577 | G20: =(O20+S20+W20+AA20+AE20+AI20+AM20+AQ20+AU20+AY20)/10 -> 0.475 | H20: =SQRT(((O20-G20)^2+(S20-G20)^2+(W20-G20)^2+(AA20-G20)^2+(AE20-G20)^2+(AI20-G20)^2+(AM20-G20)^2+(AQ20-G20)^2+(AU20-G20)^2+(AY20-G20)^2)/10) -> 0.037749172 | I20: =H20/G20 -> 0.079471941 | J20: =(P20+T20+X20+AB20+AF20+AJ20+AN20+AR20+AV20+AZ20)/10 -> 0.47674 | K20: =SQRT(((P20-J20)^2+(T20-J20)^2+(X20-J20)^2+(AB20-J20)^2+(AF20-J20)^2+(AJ20-J20)^2+(AN20-J20)^2+(AR20-J20)^2+(AV20-J20)^2+(AZ20-J20)^2)/10) -> 0.030325046 | L20: =K20/J20 -> 0.063609191 | N20: 0.5273 | O20: 0.45 | P20: 0.4592 | R20: 0.5417 | S20: 0.5 | T20: 0.5128 | V20: 0.4961 | W20: 0.44 | X20: 0.4444 | Z20: 0.4497 | AA20: 0.44 | AB20: 0.4607 | AD20: 0.5032 | AE20: 0.41 | AF20: 0.4184 | AH20: 0.5032 | AI20: 0.52 | AJ20: 0.5123 | AL20: 0.5158 | AM20: 0.53 | AN20: 0.5121 | AP20: 0.5537 | AQ20: 0.47 | AR20: 0.4724 | AT20: 0.5287 | AU20: 0.51 | AV20: 0.4951 | AX20: 0.5297 | AY20: 0.48 | AZ20: 0.48
B21: SCARF | C21: =D18/D21-1 -> 0.080498251 | D21: =(N21+R21+V21+Z21+AD21+AH21+AL21+AP21+AT21+AX21)/10 -> 0.53467 | E21: =SQRT(((N21-D21)^2+(R21-D21)^2+(V21-D21)^2+(Z21-D21)^2+(AD21-D21)^2+(AH21-D21)^2+(AL21-D21)^2+(AP21-D21)^2+(AT21-D21)^2+(AX21-D21)^2)/10) -> 0.015332583 | F21: =E21/D21 -> 0.028676722 | G21: =(O21+S21+W21+AA21+AE21+AI21+AM21+AQ21+AU21+AY21)/10 -> 0.481 | H21: =SQRT(((O21-G21)^2+(S21-G21)^2+(W21-G21)^2+(AA21-G21)^2+(AE21-G21)^2+(AI21-G21)^2+(AM21-G21)^2+(AQ21-G21)^2+(AU21-G21)^2+(AY21-G21)^2)/10) -> 0.036180105 | I21: =H21/G21 -> 0.075218514 | J21: =(P21+T21+X21+AB21+AF21+AJ21+AN21+AR21+AV21+AZ21)/10 -> 0.48773 | K21: =SQRT(((P21-J21)^2+(T21-J21)^2+(X21-J21)^2+(AB21-J21)^2+(AF21-J21)^2+(AJ21-J21)^2+(AN21-J21)^2+(AR21-J21)^2+(AV21-J21)^2+(AZ21-J21)^2)/10) -> 0.024504614 | L21: =K21/J21 -> 0.050242171 | N21: 0.5427 | O21: 0.41 | P21: 0.4481 | R21: 0.5339 | S21: 0.5 | T21: 0.48 | V21: 0.5059 | W21: 0.43 | X21: 0.4503 | Z21: 0.5243 | AA21: 0.5 | AB21: 0.5102 | AD21: 0.5543 | AE21: 0.54 | AF21: 0.5294 | AH21: 0.5136 | AI21: 0.49 | AJ21: 0.4949 | AL21: 0.5531 | AM21: 0.47 | AN21: 0.4724 | AP21: 0.5319 | AQ21: 0.49 | AR21: 0.4949 | AT21: 0.5405 | AU21: 0.47 | AV21: 0.4896 | AX21: 0.5465 | AY21: 0.51 | AZ21: 0.5075
C23: effect, % | D23: AUPRC | G23: Recall | J23: F1 | N23: AUPRC | O23: For reference | R23: AUPRC | S23: For reference | V23: AUPRC | W23: For reference | Z23: AUPRC | AA23: For reference | AD23: AUPRC | AE23: For reference | AH23: AUPRC | AI23: For reference | AL23: AUPRC | AM23: For reference | AP23: AUPRC | AQ23: For reference | AT23: AUPRC | AU23: For reference | AX23: AUPRC | AY23: For reference
D24: mean | E24: σ | F24: CV | G24: mean | H24: σ | I24: CV | J24: mean | K24: σ | L24: CV | O24: Recall | P24: F1 | S24: Recall | T24: F1 | W24: Recall | X24: F1 | AA24: Recall | AB24: F1 | AE24: Recall | AF24: F1 | AI24: Recall | AJ24: F1 | AM24: Recall | AN24: F1 | AQ24: Recall | AR24: F1 | AU24: Recall | AV24: F1 | AY24: Recall | AZ24: F1
B25: LR | C25: =D26/D25-1 -> 0.022259684 | D25: =(N25+R25+V25+Z25+AD25+AH25+AL25+AP25+AT25+AX25)/10 -> 0.55167 | E25: =SQRT(((N25-D25)^2+(R25-D25)^2+(V25-D25)^2+(Z25-D25)^2+(AD25-D25)^2+(AH25-D25)^2+(AL25-D25)^2+(AP25-D25)^2+(AT25-D25)^2+(AX25-D25)^2)/10) -> 0.0032177787 | F25: =E25/D25 -> 0.0058327963 | G25: =(O25+S25+W25+AA25+AE25+AI25+AM25+AQ25+AU25+AY25)/10 -> 0.443 | H25: =SQRT(((O25-G25)^2+(S25-G25)^2+(W25-G25)^2+(AA25-G25)^2+(AE25-G25)^2+(AI25-G25)^2+(AM25-G25)^2+(AQ25-G25)^2+(AU25-G25)^2+(AY25-G25)^2)/10) -> 0.011 | I25: =H25/G25 -> 0.0248307 | J25: =(P25+T25+X25+AB25+AF25+AJ25+AN25+AR25+AV25+AZ25)/10 -> 0.48331 | K25: =SQRT(((P25-J25)^2+(T25-J25)^2+(X25-J25)^2+(AB25-J25)^2+(AF25-J25)^2+(AJ25-J25)^2+(AN25-J25)^2+(AR25-J25)^2+(AV25-J25)^2+(AZ25-J25)^2)/10) -> 0.0071832374 | L25: =K25/J25 -> 0.014862588 | N25: 0.5532 | O25: 0.44 | P25: 0.4783 | R25: 0.5542 | S25: 0.44 | T25: 0.4835 | V25: 0.5486 | W25: 0.46 | X25: 0.4946 | Z25: 0.5545 | AA25: 0.44 | AB25: 0.4862 | AD25: 0.5486 | AE25: 0.46 | AF25: 0.4946 | AH25: 0.5542 | AI25: 0.44 | AJ25: 0.4835 | AL25: 0.5554 | AM25: 0.44 | AN25: 0.4809 | AP25: 0.5453 | AQ25: 0.42 | AR25: 0.4693 | AT25: 0.5495 | AU25: 0.45 | AV25: 0.4839 | AX25: 0.5532 | AY25: 0.44 | AZ25: 0.4783
B26: CLT-TAB without SQP | D26: =(N26+R26+V26+Z26+AD26+AH26+AL26+AP26+AT26+AX26)/10 -> 0.56395 | E26: =SQRT(((N26-D26)^2+(R26-D26)^2+(V26-D26)^2+(Z26-D26)^2+(AD26-D26)^2+(AH26-D26)^2+(AL26-D26)^2+(AP26-D26)^2+(AT26-D26)^2+(AX26-D26)^2)/10) -> 0.016006702 | F26: =E26/D26 -> 0.028383193 | G26: =(O26+S26+W26+AA26+AE26+AI26+AM26+AQ26+AU26+AY26)/10 -> 0.516 | H26: =SQRT(((O26-G26)^2+(S26-G26)^2+(W26-G26)^2+(AA26-G26)^2+(AE26-G26)^2+(AI26-G26)^2+(AM26-G26)^2+(AQ26-G26)^2+(AU26-G26)^2+(AY26-G26)^2)/10) -> 0.026532998 | I26: =H26/G26 -> 0.051420539 | J26: =(P26+T26+X26+AB26+AF26+AJ26+AN26+AR26+AV26+AZ26)/10 -> 0.53226 | K26: =SQRT(((P26-J26)^2+(T26-J26)^2+(X26-J26)^2+(AB26-J26)^2+(AF26-J26)^2+(AJ26-J26)^2+(AN26-J26)^2+(AR26-J26)^2+(AV26-J26)^2+(AZ26-J26)^2)/10) -> 0.019279585 | L26: =K26/J26 -> 0.036222119 | N26: 0.5627 | O26: 0.49 | P26: 0.5158 | R26: 0.5592 | S26: 0.48 | T26: 0.5053 | V26: 0.5516 | W26: 0.51 | X26: 0.5285 | Z26: 0.5746 | AA26: 0.58 | AB26: 0.5771 | AD26: 0.547 | AE26: 0.52 | AF26: 0.5361 | AH26: 0.5886 | AI26: 0.5 | AJ26: 0.5263 | AL26: 0.594 | AM26: 0.51 | AN26: 0.534 | AP26: 0.5644 | AQ26: 0.54 | AR26: 0.5538 | AT26: 0.5466 | AU26: 0.52 | AV26: 0.5226 | AX26: 0.5508 | AY26: 0.51 | AZ26: 0.5231
B27: FT-transformer | C27: =D26/D27-1 -> 0.033007895 | D27: =(N27+R27+V27+Z27+AD27+AH27+AL27+AP27+AT27+AX27)/10 -> 0.54593 | E27: =SQRT(((N27-D27)^2+(R27-D27)^2+(V27-D27)^2+(Z27-D27)^2+(AD27-D27)^2+(AH27-D27)^2+(AL27-D27)^2+(AP27-D27)^2+(AT27-D27)^2+(AX27-D27)^2)/10) -> 0.025933031 | F27: =E27/D27 -> 0.047502484 | G27: =(O27+S27+W27+AA27+AE27+AI27+AM27+AQ27+AU27+AY27)/10 -> 0.454 | H27: =SQRT(((O27-G27)^2+(S27-G27)^2+(W27-G27)^2+(AA27-G27)^2+(AE27-G27)^2+(AI27-G27)^2+(AM27-G27)^2+(AQ27-G27)^2+(AU27-G27)^2+(AY27-G27)^2)/10) -> 0.040792156 | I27: =H27/G27 -> 0.089850564 | J27: =(P27+T27+X27+AB27+AF27+AJ27+AN27+AR27+AV27+AZ27)/10 -> 0.48775 | K27: =SQRT(((P27-J27)^2+(T27-J27)^2+(X27-J27)^2+(AB27-J27)^2+(AF27-J27)^2+(AJ27-J27)^2+(AN27-J27)^2+(AR27-J27)^2+(AV27-J27)^2+(AZ27-J27)^2)/10) -> 0.032761296 | L27: =K27/J27 -> 0.067168213 | N27: 0.5676 | O27: 0.5 | P27: 0.5102 | R27: 0.5608 | S27: 0.48 | T27: 0.5106 | V27: 0.5518 | W27: 0.46 | X27: 0.4973 | Z27: 0.5452 | AA27: 0.48 | AB27: 0.5106 | AD27: 0.5091 | AE27: 0.46 | AF27: 0.4792 | AH27: 0.5435 | AI27: 0.5 | AJ27: 0.5291 | AL27: 0.5377 | AM27: 0.42 | AN27: 0.4719 | AP27: 0.5776 | AQ27: 0.38 | AR27: 0.4343 | AT27: 0.5732 | AU27: 0.47 | AV27: 0.5081 | AX27: 0.4928 | AY27: 0.39 | AZ27: 0.4262
B28: CatBoost | C28: =D26/D28-1 -> 0.095239945 | D28: =(N28+R28+V28+Z28+AD28+AH28+AL28+AP28+AT28+AX28)/10 -> 0.51491 | E28: =SQRT(((N28-D28)^2+(R28-D28)^2+(V28-D28)^2+(Z28-D28)^2+(AD28-D28)^2+(AH28-D28)^2+(AL28-D28)^2+(AP28-D28)^2+(AT28-D28)^2+(AX28-D28)^2)/10) -> 0.027687522 | F28: =E28/D28 -> 0.053771577 | G28: =(O28+S28+W28+AA28+AE28+AI28+AM28+AQ28+AU28+AY28)/10 -> 0.475 | H28: =SQRT(((O28-G28)^2+(S28-G28)^2+(W28-G28)^2+(AA28-G28)^2+(AE28-G28)^2+(AI28-G28)^2+(AM28-G28)^2+(AQ28-G28)^2+(AU28-G28)^2+(AY28-G28)^2)/10) -> 0.037749172 | I28: =H28/G28 -> 0.079471941 | J28: =(P28+T28+X28+AB28+AF28+AJ28+AN28+AR28+AV28+AZ28)/10 -> 0.47674 | K28: =SQRT(((P28-J28)^2+(T28-J28)^2+(X28-J28)^2+(AB28-J28)^2+(AF28-J28)^2+(AJ28-J28)^2+(AN28-J28)^2+(AR28-J28)^2+(AV28-J28)^2+(AZ28-J28)^2)/10) -> 0.030325046 | L28: =K28/J28 -> 0.063609191 | N28: 0.5273 | O28: 0.45 | P28: 0.4592 | R28: 0.5417 | S28: 0.5 | T28: 0.5128 | V28: 0.4961 | W28: 0.44 | X28: 0.4444 | Z28: 0.4497 | AA28: 0.44 | AB28: 0.4607 | AD28: 0.5032 | AE28: 0.41 | AF28: 0.4184 | AH28: 0.5032 | AI28: 0.52 | AJ28: 0.5123 | AL28: 0.5158 | AM28: 0.53 | AN28: 0.5121 | AP28: 0.5537 | AQ28: 0.47 | AR28: 0.4724 | AT28: 0.5287 | AU28: 0.51 | AV28: 0.4951 | AX28: 0.5297 | AY28: 0.48 | AZ28: 0.48
B29: SCARF | C29: =D26/D29-1 -> 0.054762751 | D29: =(N29+R29+V29+Z29+AD29+AH29+AL29+AP29+AT29+AX29)/10 -> 0.53467 | E29: =SQRT(((N29-D29)^2+(R29-D29)^2+(V29-D29)^2+(Z29-D29)^2+(AD29-D29)^2+(AH29-D29)^2+(AL29-D29)^2+(AP29-D29)^2+(AT29-D29)^2+(AX29-D29)^2)/10) -> 0.015332583 | F29: =E29/D29 -> 0.028676722 | G29: =(O29+S29+W29+AA29+AE29+AI29+AM29+AQ29+AU29+AY29)/10 -> 0.481 | H29: =SQRT(((O29-G29)^2+(S29-G29)^2+(W29-G29)^2+(AA29-G29)^2+(AE29-G29)^2+(AI29-G29)^2+(AM29-G29)^2+(AQ29-G29)^2+(AU29-G29)^2+(AY29-G29)^2)/10) -> 0.036180105 | I29: =H29/G29 -> 0.075218514 | J29: =(P29+T29+X29+AB29+AF29+AJ29+AN29+AR29+AV29+AZ29)/10 -> 0.48773 | K29: =SQRT(((P29-J29)^2+(T29-J29)^2+(X29-J29)^2+(AB29-J29)^2+(AF29-J29)^2+(AJ29-J29)^2+(AN29-J29)^2+(AR29-J29)^2+(AV29-J29)^2+(AZ29-J29)^2)/10) -> 0.024504614 | L29: =K29/J29 -> 0.050242171 | N29: 0.5427 | O29: 0.41 | P29: 0.4481 | R29: 0.5339 | S29: 0.5 | T29: 0.48 | V29: 0.5059 | W29: 0.43 | X29: 0.4503 | Z29: 0.5243 | AA29: 0.5 | AB29: 0.5102 | AD29: 0.5543 | AE29: 0.54 | AF29: 0.5294 | AH29: 0.5136 | AI29: 0.49 | AJ29: 0.4949 | AL29: 0.5531 | AM29: 0.47 | AN29: 0.4724 | AP29: 0.5319 | AQ29: 0.49 | AR29: 0.4949 | AT29: 0.5405 | AU29: 0.47 | AV29: 0.4896 | AX29: 0.5465 | AY29: 0.51 | AZ29: 0.5075
C31: effect, % | D31: AUPRC | G31: Recall | J31: F1 | N31: AUPRC | O31: For reference | R31: AUPRC | S31: For reference | V31: AUPRC | W31: For reference | Z31: AUPRC | AA31: For reference | AD31: AUPRC | AE31: For reference | AH31: AUPRC | AI31: For reference | AL31: AUPRC | AM31: For reference | AP31: AUPRC | AQ31: For reference | AT31: AUPRC | AU31: For reference | AX31: AUPRC | AY31: For reference
D32: mean | E32: σ | F32: CV | G32: mean | H32: σ | I32: CV | J32: mean | K32: σ | L32: CV | O32: Recall | P32: F1 | S32: Recall | T32: F1 | W32: Recall | X32: F1 | AA32: Recall | AB32: F1 | AE32: Recall | AF32: F1 | AI32: Recall | AJ32: F1 | AM32: Recall | AN32: F1 | AQ32: Recall | AR32: F1 | AU32: Recall | AV32: F1 | AY32: Recall | AZ32: F1
B33: LR | C33: =D34/D33-1 -> 0.011437997 | D33: =(N33+R33+V33+Z33+AD33+AH33+AL33+AP33+AT33+AX33)/10 -> 0.55167 | E33: =SQRT(((N33-D33)^2+(R33-D33)^2+(V33-D33)^2+(Z33-D33)^2+(AD33-D33)^2+(AH33-D33)^2+(AL33-D33)^2+(AP33-D33)^2+(AT33-D33)^2+(AX33-D33)^2)/10) -> 0.0032177787 | F33: =E33/D33 -> 0.0058327963 | G33: =(O33+S33+W33+AA33+AE33+AI33+AM33+AQ33+AU33+AY33)/10 -> 0.443 | H33: =SQRT(((O33-G33)^2+(S33-G33)^2+(W33-G33)^2+(AA33-G33)^2+(AE33-G33)^2+(AI33-G33)^2+(AM33-G33)^2+(AQ33-G33)^2+(AU33-G33)^2+(AY33-G33)^2)/10) -> 0.011 | I33: =H33/G33 -> 0.0248307 | J33: =(P33+T33+X33+AB33+AF33+AJ33+AN33+AR33+AV33+AZ33)/10 -> 0.48331 | K33: =SQRT(((P33-J33)^2+(T33-J33)^2+(X33-J33)^2+(AB33-J33)^2+(AF33-J33)^2+(AJ33-J33)^2+(AN33-J33)^2+(AR33-J33)^2+(AV33-J33)^2+(AZ33-J33)^2)/10) -> 0.0071832374 | L33: =K33/J33 -> 0.014862588 | N33: 0.5532 | O33: 0.44 | P33: 0.4783 | R33: 0.5542 | S33: 0.44 | T33: 0.4835 | V33: 0.5486 | W33: 0.46 | X33: 0.4946 | Z33: 0.5545 | AA33: 0.44 | AB33: 0.4862 | AD33: 0.5486 | AE33: 0.46 | AF33: 0.4946 | AH33: 0.5542 | AI33: 0.44 | AJ33: 0.4835 | AL33: 0.5554 | AM33: 0.44 | AN33: 0.4809 | AP33: 0.5453 | AQ33: 0.42 | AR33: 0.4693 | AT33: 0.5495 | AU33: 0.45 | AV33: 0.4839 | AX33: 0.5532 | AY33: 0.44 | AZ33: 0.4783
B34: CLT-TAB without CATA and SQP | D34: =(N34+R34+V34+Z34+AD34+AH34+AL34+AP34+AT34+AX34)/10 -> 0.55798 | E34: =SQRT(((N34-D34)^2+(R34-D34)^2+(V34-D34)^2+(Z34-D34)^2+(AD34-D34)^2+(AH34-D34)^2+(AL34-D34)^2+(AP34-D34)^2+(AT34-D34)^2+(AX34-D34)^2)/10) -> 0.017457136 | F34: =E34/D34 -> 0.031286311 | G34: =(O34+S34+W34+AA34+AE34+AI34+AM34+AQ34+AU34+AY34)/10 -> 0.514 | H34: =SQRT(((O34-G34)^2+(S34-G34)^2+(W34-G34)^2+(AA34-G34)^2+(AE34-G34)^2+(AI34-G34)^2+(AM34-G34)^2+(AQ34-G34)^2+(AU34-G34)^2+(AY34-G34)^2)/10) -> 0.026532998 | I34: =H34/G34 -> 0.051620619 | J34: =(P34+T34+X34+AB34+AF34+AJ34+AN34+AR34+AV34+AZ34)/10 -> 0.52704 | K34: =SQRT(((P34-J34)^2+(T34-J34)^2+(X34-J34)^2+(AB34-J34)^2+(AF34-J34)^2+(AJ34-J34)^2+(AN34-J34)^2+(AR34-J34)^2+(AV34-J34)^2+(AZ34-J34)^2)/10) -> 0.023154619 | L34: =K34/J34 -> 0.043933325 | N34: 0.5798 | O34: 0.53 | P34: 0.5408 | R34: 0.546 | S34: 0.51 | T34: 0.5178 | V34: 0.5227 | W34: 0.49 | X34: 0.5104 | Z34: 0.5823 | AA34: 0.56 | AB34: 0.5628 | AD34: 0.5538 | AE34: 0.55 | AF34: 0.5584 | AH34: 0.5515 | AI34: 0.48 | AJ34: 0.4873 | AL34: 0.5592 | AM34: 0.5 | AN34: 0.5155 | AP34: 0.5679 | AQ34: 0.51 | AR34: 0.534 | AT34: 0.573 | AU34: 0.48 | AV34: 0.5026 | AX34: 0.5436 | AY34: 0.53 | AZ34: 0.5408
B35: FT-transformer | C35: =D34/D35-1 -> 0.022072427 | D35: =(N35+R35+V35+Z35+AD35+AH35+AL35+AP35+AT35+AX35)/10 -> 0.54593 | E35: =SQRT(((N35-D35)^2+(R35-D35)^2+(V35-D35)^2+(Z35-D35)^2+(AD35-D35)^2+(AH35-D35)^2+(AL35-D35)^2+(AP35-D35)^2+(AT35-D35)^2+(AX35-D35)^2)/10) -> 0.025933031 | F35: =E35/D35 -> 0.047502484 | G35: =(O35+S35+W35+AA35+AE35+AI35+AM35+AQ35+AU35+AY35)/10 -> 0.454 | H35: =SQRT(((O35-G35)^2+(S35-G35)^2+(W35-G35)^2+(AA35-G35)^2+(AE35-G35)^2+(AI35-G35)^2+(AM35-G35)^2+(AQ35-G35)^2+(AU35-G35)^2+(AY35-G35)^2)/10) -> 0.040792156 | I35: =H35/G35 -> 0.089850564 | J35: =(P35+T35+X35+AB35+AF35+AJ35+AN35+AR35+AV35+AZ35)/10 -> 0.48775 | K35: =SQRT(((P35-J35)^2+(T35-J35)^2+(X35-J35)^2+(AB35-J35)^2+(AF35-J35)^2+(AJ35-J35)^2+(AN35-J35)^2+(AR35-J35)^2+(AV35-J35)^2+(AZ35-J35)^2)/10) -> 0.032761296 | L35: =K35/J35 -> 0.067168213 | N35: 0.5676 | O35: 0.5 | P35: 0.5102 | R35: 0.5608 | S35: 0.48 | T35: 0.5106 | V35: 0.5518 | W35: 0.46 | X35: 0.4973 | Z35: 0.5452 | AA35: 0.48 | AB35: 0.5106 | AD35: 0.5091 | AE35: 0.46 | AF35: 0.4792 | AH35: 0.5435 | AI35: 0.5 | AJ35: 0.5291 | AL35: 0.5377 | AM35: 0.42 | AN35: 0.4719 | AP35: 0.5776 | AQ35: 0.38 | AR35: 0.4343 | AT35: 0.5732 | AU35: 0.47 | AV35: 0.5081 | AX35: 0.4928 | AY35: 0.39 | AZ35: 0.4262
B36: CatBoost | C36: =D34/D36-1 -> 0.083645686 | D36: =(N36+R36+V36+Z36+AD36+AH36+AL36+AP36+AT36+AX36)/10 -> 0.51491 | E36: =SQRT(((N36-D36)^2+(R36-D36)^2+(V36-D36)^2+(Z36-D36)^2+(AD36-D36)^2+(AH36-D36)^2+(AL36-D36)^2+(AP36-D36)^2+(AT36-D36)^2+(AX36-D36)^2)/10) -> 0.027687522 | F36: =E36/D36 -> 0.053771577 | G36: =(O36+S36+W36+AA36+AE36+AI36+AM36+AQ36+AU36+AY36)/10 -> 0.475 | H36: =SQRT(((O36-G36)^2+(S36-G36)^2+(W36-G36)^2+(AA36-G36)^2+(AE36-G36)^2+(AI36-G36)^2+(AM36-G36)^2+(AQ36-G36)^2+(AU36-G36)^2+(AY36-G36)^2)/10) -> 0.037749172 | I36: =H36/G36 -> 0.079471941 | J36: =(P36+T36+X36+AB36+AF36+AJ36+AN36+AR36+AV36+AZ36)/10 -> 0.47674 | K36: =SQRT(((P36-J36)^2+(T36-J36)^2+(X36-J36)^2+(AB36-J36)^2+(AF36-J36)^2+(AJ36-J36)^2+(AN36-J36)^2+(AR36-J36)^2+(AV36-J36)^2+(AZ36-J36)^2)/10) -> 0.030325046 | L36: =K36/J36 -> 0.063609191 | N36: 0.5273 | O36: 0.45 | P36: 0.4592 | R36: 0.5417 | S36: 0.5 | T36: 0.5128 | V36: 0.4961 | W36: 0.44 | X36: 0.4444 | Z36: 0.4497 | AA36: 0.44 | AB36: 0.4607 | AD36: 0.5032 | AE36: 0.41 | AF36: 0.4184 | AH36: 0.5032 | AI36: 0.52 | AJ36: 0.5123 | AL36: 0.5158 | AM36: 0.53 | AN36: 0.5121 | AP36: 0.5537 | AQ36: 0.47 | AR36: 0.4724 | AT36: 0.5287 | AU36: 0.51 | AV36: 0.4951 | AX36: 0.5297 | AY36: 0.48 | AZ36: 0.48
B37: SCARF | C37: =D34/D37-1 -> 0.043596985 | D37: =(N37+R37+V37+Z37+AD37+AH37+AL37+AP37+AT37+AX37)/10 -> 0.53467 | E37: =SQRT(((N37-D37)^2+(R37-D37)^2+(V37-D37)^2+(Z37-D37)^2+(AD37-D37)^2+(AH37-D37)^2+(AL37-D37)^2+(AP37-D37)^2+(AT37-D37)^2+(AX37-D37)^2)/10) -> 0.015332583 | F37: =E37/D37 -> 0.028676722 | G37: =(O37+S37+W37+AA37+AE37+AI37+AM37+AQ37+AU37+AY37)/10 -> 0.481 | H37: =SQRT(((O37-G37)^2+(S37-G37)^2+(W37-G37)^2+(AA37-G37)^2+(AE37-G37)^2+(AI37-G37)^2+(AM37-G37)^2+(AQ37-G37)^2+(AU37-G37)^2+(AY37-G37)^2)/10) -> 0.036180105 | I37: =H37/G37 -> 0.075218514 | J37: =(P37+T37+X37+AB37+AF37+AJ37+AN37+AR37+AV37+AZ37)/10 -> 0.48773 | K37: =SQRT(((P37-J37)^2+(T37-J37)^2+(X37-J37)^2+(AB37-J37)^2+(AF37-J37)^2+(AJ37-J37)^2+(AN37-J37)^2+(AR37-J37)^2+(AV37-J37)^2+(AZ37-J37)^2)/10) -> 0.024504614 | L37: =K37/J37 -> 0.050242171 | N37: 0.5427 | O37: 0.41 | P37: 0.4481 | R37: 0.5339 | S37: 0.5 | T37: 0.48 | V37: 0.5059 | W37: 0.43 | X37: 0.4503 | Z37: 0.5243 | AA37: 0.5 | AB37: 0.5102 | AD37: 0.5543 | AE37: 0.54 | AF37: 0.5294 | AH37: 0.5136 | AI37: 0.49 | AJ37: 0.4949 | AL37: 0.5531 | AM37: 0.47 | AN37: 0.4724 | AP37: 0.5319 | AQ37: 0.49 | AR37: 0.4949 | AT37: 0.5405 | AU37: 0.47 | AV37: 0.4896 | AX37: 0.5465 | AY37: 0.51 | AZ37: 0.5075

Sheet Adult
B1: Overview
B2: The Adult Census Income dataset (also known as the Adult dataset or Census Income dataset) is a classic benchmark for binary classification tasks in social sciences and machine learning. It was designed to predict whether an individual’s annual income exceeds $50,000 based on demographic and employment‑related features extracted from the 1994 United States Census Bureau database. The dataset was created by Barry Becker and Ronny Kohavi (Data Mining and Visualization, Silicon Graphics) and has been widely used for evaluating classification algorithms, including logistic regression, decision trees, support vector machines, and fairness‑aware models
B3: We used the Adult dataset, which contains 48 785 instances with a 16,08 % anomaly rate. It comprises 5 numerical and 8 categorical features ('education-num' was removed, as it duplicates 'education'). The data were used after preprocessing (missing values, duplicates, and constant features were removed). F1 and Recall scores were obtained with a threshold of 0.5. We used 622 instances for finetuning, of which 100 were anomalies, and the same number (622 instances, 100 anomalies) for testing.
B5: Random AUPRC | C5: 0.1608 | N5: Seed
G6: For reference | N6: 42 | R6: 43 | V6: 44 | Z6: 45 | AD6: 46 | AH6: 47 | AL6: 48 | AP6: 49 | AT6: 50 | AX6: 51
C7: effect, % | D7: AUPRC | G7: Recall | J7: F1 | N7: AUPRC | O7: For reference | R7: AUPRC | S7: For reference | V7: AUPRC | W7: For reference | Z7: AUPRC | AA7: For reference | AD7: AUPRC | AE7: For reference | AH7: AUPRC | AI7: For reference | AL7: AUPRC | AM7: For reference | AP7: AUPRC | AQ7: For reference | AT7: AUPRC | AU7: For reference | AX7: AUPRC | AY7: For reference
D8: mean | E8: σ | F8: CV | G8: mean | H8: σ | I8: CV | J8: mean | K8: σ | L8: CV | O8: Recall | P8: F1 | S8: Recall | T8: F1 | W8: Recall | X8: F1 | AA8: Recall | AB8: F1 | AE8: Recall | AF8: F1 | AI8: Recall | AJ8: F1 | AM8: Recall | AN8: F1 | AQ8: Recall | AR8: F1 | AU8: Recall | AV8: F1 | AY8: Recall | AZ8: F1
B9: LR | C9: =D10/D9-1 -> 0.29279641 | D9: =(N9+R9+V9+Z9+AD9+AH9+AL9+AP9+AT9+AX9)/10 -> 0.41049 | E9: =SQRT(((N9-D9)^2+(R9-D9)^2+(V9-D9)^2+(Z9-D9)^2+(AD9-D9)^2+(AH9-D9)^2+(AL9-D9)^2+(AP9-D9)^2+(AT9-D9)^2+(AX9-D9)^2)/10) -> 0.0084127819 | F9: =E9/D9 -> 0.020494487 | G9: =(O9+S9+W9+AA9+AE9+AI9+AM9+AQ9+AU9+AY9)/10 -> 0.745 | H9: =SQRT(((O9-G9)^2+(S9-G9)^2+(W9-G9)^2+(AA9-G9)^2+(AE9-G9)^2+(AI9-G9)^2+(AM9-G9)^2+(AQ9-G9)^2+(AU9-G9)^2+(AY9-G9)^2)/10) -> 0.012845233 | I9: =H9/G9 -> 0.017241923 | J9: =(P9+T9+X9+AB9+AF9+AJ9+AN9+AR9+AV9+AZ9)/10 -> 0.46303 | K9: =SQRT(((P9-J9)^2+(T9-J9)^2+(X9-J9)^2+(AB9-J9)^2+(AF9-J9)^2+(AJ9-J9)^2+(AN9-J9)^2+(AR9-J9)^2+(AV9-J9)^2+(AZ9-J9)^2)/10) -> 0.0023413885 | L9: =K9/J9 -> 0.0050566669 | N9: 0.4184 | O9: 0.73 | P9: 0.4606 | R9: 0.4078 | S9: 0.74 | T9: 0.4596 | V9: 0.4025 | W9: 0.76 | X9: 0.4634 | Z9: 0.4241 | AA9: 0.73 | AB9: 0.4665 | AD9: 0.4078 | AE9: 0.74 | AF9: 0.4596 | AH9: 0.4025 | AI9: 0.76 | AJ9: 0.4634 | AL9: 0.4025 | AM9: 0.76 | AN9: 0.4634 | AP9: 0.4127 | AQ9: 0.74 | AR9: 0.4639 | AT9: 0.4025 | AU9: 0.76 | AV9: 0.4634 | AX9: 0.4241 | AY9: 0.73 | AZ9: 0.4665
B10: CLT-TAB | D10: =(N10+R10+V10+Z10+AD10+AH10+AL10+AP10+AT10+AX10)/10 -> 0.53068 | E10: =SQRT(((N10-D10)^2+(R10-D10)^2+(V10-D10)^2+(Z10-D10)^2+(AD10-D10)^2+(AH10-D10)^2+(AL10-D10)^2+(AP10-D10)^2+(AT10-D10)^2+(AX10-D10)^2)/10) -> 0.017105835 | F10: =E10/D10 -> 0.032233804 | G10: =(O10+S10+W10+AA10+AE10+AI10+AM10+AQ10+AU10+AY10)/10 -> 0.745 | H10: =SQRT(((O10-G10)^2+(S10-G10)^2+(W10-G10)^2+(AA10-G10)^2+(AE10-G10)^2+(AI10-G10)^2+(AM10-G10)^2+(AQ10-G10)^2+(AU10-G10)^2+(AY10-G10)^2)/10) -> 0.010246951 | I10: =H10/G10 -> 0.013754296 | J10: =(P10+T10+X10+AB10+AF10+AJ10+AN10+AR10+AV10+AZ10)/10 -> 0.49732 | K10: =SQRT(((P10-J10)^2+(T10-J10)^2+(X10-J10)^2+(AB10-J10)^2+(AF10-J10)^2+(AJ10-J10)^2+(AN10-J10)^2+(AR10-J10)^2+(AV10-J10)^2+(AZ10-J10)^2)/10) -> 0.013930815 | L10: =K10/J10 -> 0.028011773 | N10: 0.5533 | O10: 0.75 | P10: 0.4902 | R10: 0.5376 | S10: 0.74 | T10: 0.4728 | V10: 0.5614 | W10: 0.75 | X10: 0.5085 | Z10: 0.5103 | AA10: 0.75 | AB10: 0.5051 | AD10: 0.5185 | AE10: 0.76 | AF10: 0.5 | AH10: 0.5114 | AI10: 0.74 | AJ10: 0.5068 | AL10: 0.5418 | AM10: 0.76 | AN10: 0.4984 | AP10: 0.525 | AQ10: 0.73 | AR10: 0.485 | AT10: 0.5129 | AU10: 0.73 | AV10: 0.4834 | AX10: 0.5346 | AY10: 0.74 | AZ10: 0.523
B11: FT-transformer | C11: =D10/D11-1 -> 0.42414728 | D11: =(N11+R11+V11+Z11+AD11+AH11+AL11+AP11+AT11+AX11)/10 -> 0.37263 | E11: =SQRT(((N11-D11)^2+(R11-D11)^2+(V11-D11)^2+(Z11-D11)^2+(AD11-D11)^2+(AH11-D11)^2+(AL11-D11)^2+(AP11-D11)^2+(AT11-D11)^2+(AX11-D11)^2)/10) -> 0.016933166 | F11: =E11/D11 -> 0.045442304 | G11: =(O11+S11+W11+AA11+AE11+AI11+AM11+AQ11+AU11+AY11)/10 -> 0.322 | H11: =SQRT(((O11-G11)^2+(S11-G11)^2+(W11-G11)^2+(AA11-G11)^2+(AE11-G11)^2+(AI11-G11)^2+(AM11-G11)^2+(AQ11-G11)^2+(AU11-G11)^2+(AY11-G11)^2)/10) -> 0.036 | I11: =H11/G11 -> 0.11180124 | J11: =(P11+T11+X11+AB11+AF11+AJ11+AN11+AR11+AV11+AZ11)/10 -> 0.34713 | K11: =SQRT(((P11-J11)^2+(T11-J11)^2+(X11-J11)^2+(AB11-J11)^2+(AF11-J11)^2+(AJ11-J11)^2+(AN11-J11)^2+(AR11-J11)^2+(AV11-J11)^2+(AZ11-J11)^2)/10) -> 0.028374956 | L11: =K11/J11 -> 0.081741582 | N11: 0.3543 | O11: 0.26 | P11: 0.3006 | R11: 0.3923 | S11: 0.35 | T11: 0.3684 | V11: 0.3669 | W11: 0.3 | X11: 0.3371 | Z11: 0.3511 | AA11: 0.29 | AB11: 0.3169 | AD11: 0.3666 | AE11: 0.37 | AF11: 0.3756 | AH11: 0.3864 | AI11: 0.34 | AJ11: 0.3716 | AL11: 0.3668 | AM11: 0.33 | AN11: 0.3455 | AP11: 0.3599 | AQ11: 0.28 | AR11: 0.3182 | AT11: 0.3744 | AU11: 0.33 | AV11: 0.3438 | AX11: 0.4076 | AY11: 0.37 | AZ11: 0.3936
B12: CatBoost | C12: =D10/D12-1 -> 0.048277497 | D12: =(N12+R12+V12+Z12+AD12+AH12+AL12+AP12+AT12+AX12)/10 -> 0.50624 | E12: =SQRT(((N12-D12)^2+(R12-D12)^2+(V12-D12)^2+(Z12-D12)^2+(AD12-D12)^2+(AH12-D12)^2+(AL12-D12)^2+(AP12-D12)^2+(AT12-D12)^2+(AX12-D12)^2)/10) -> 0.019672885 | F12: =E12/D12 -> 0.038860787 | G12: =(O12+S12+W12+AA12+AE12+AI12+AM12+AQ12+AU12+AY12)/10 -> 0.816 | H12: =SQRT(((O12-G12)^2+(S12-G12)^2+(W12-G12)^2+(AA12-G12)^2+(AE12-G12)^2+(AI12-G12)^2+(AM12-G12)^2+(AQ12-G12)^2+(AU12-G12)^2+(AY12-G12)^2)/10) -> 0.023323808 | I12: =H12/G12 -> 0.028583098 | J12: =(P12+T12+X12+AB12+AF12+AJ12+AN12+AR12+AV12+AZ12)/10 -> 0.48718 | K12: =SQRT(((P12-J12)^2+(T12-J12)^2+(X12-J12)^2+(AB12-J12)^2+(AF12-J12)^2+(AJ12-J12)^2+(AN12-J12)^2+(AR12-J12)^2+(AV12-J12)^2+(AZ12-J12)^2)/10) -> 0.012862333 | L12: =K12/J12 -> 0.026401602 | N12: 0.5069 | O12: 0.82 | P12: 0.474 | R12: 0.5117 | S12: 0.78 | T12: 0.5049 | V12: 0.4809 | W12: 0.78 | X12: 0.4685 | Z12: 0.5079 | AA12: 0.81 | AB12: 0.4894 | AD12: 0.5024 | AE12: 0.84 | AF12: 0.48 | AH12: 0.4748 | AI12: 0.85 | AJ12: 0.4843 | AL12: 0.5176 | AM12: 0.83 | AN12: 0.4882 | AP12: 0.546 | AQ12: 0.8 | AR12: 0.5079 | AT12: 0.4916 | AU12: 0.84 | AV12: 0.4746 | AX12: 0.5226 | AY12: 0.81 | AZ12: 0.5
B13: SCARF | C13: =D10/D13-1 -> 2.6437792 | D13: =(N13+R13+V13+Z13+AD13+AH13+AL13+AP13+AT13+AX13)/10 -> 0.14564 | E13: =SQRT(((N13-D13)^2+(R13-D13)^2+(V13-D13)^2+(Z13-D13)^2+(AD13-D13)^2+(AH13-D13)^2+(AL13-D13)^2+(AP13-D13)^2+(AT13-D13)^2+(AX13-D13)^2)/10) -> 0.011757398 | F13: =E13/D13 -> 0.080729179 | G13: =(O13+S13+W13+AA13+AE13+AI13+AM13+AQ13+AU13+AY13)/10 -> 0.416 | H13: =SQRT(((O13-G13)^2+(S13-G13)^2+(W13-G13)^2+(AA13-G13)^2+(AE13-G13)^2+(AI13-G13)^2+(AM13-G13)^2+(AQ13-G13)^2+(AU13-G13)^2+(AY13-G13)^2)/10) -> 0.050635956 | I13: =H13/G13 -> 0.12172105 | J13: =(P13+T13+X13+AB13+AF13+AJ13+AN13+AR13+AV13+AZ13)/10 -> 0.21802 | K13: =SQRT(((P13-J13)^2+(T13-J13)^2+(X13-J13)^2+(AB13-J13)^2+(AF13-J13)^2+(AJ13-J13)^2+(AN13-J13)^2+(AR13-J13)^2+(AV13-J13)^2+(AZ13-J13)^2)/10) -> 0.028448051 | L13: =K13/J13 -> 0.13048368 | N13: 0.1642 | O13: 0.46 | P13: 0.2521 | R13: 0.1634 | S13: 0.5 | T13: 0.2667 | V13: 0.1343 | W13: 0.38 | X13: 0.1979 | Z13: 0.1427 | AA13: 0.46 | AB13: 0.2383 | AD13: 0.1615 | AE13: 0.48 | AF13: 0.2487 | AH13: 0.134 | AI13: 0.4 | AJ13: 0.203 | AL13: 0.1431 | AM13: 0.36 | AN13: 0.192 | AP13: 0.1363 | AQ13: 0.39 | AR13: 0.2037 | AT13: 0.1392 | AU13: 0.37 | AV13: 0.1883 | AX13: 0.1377 | AY13: 0.36 | AZ13: 0.1895
C15: effect, % | D15: AUPRC | G15: Recall | J15: F1 | N15: AUPRC | O15: For reference | R15: AUPRC | S15: For reference | V15: AUPRC | W15: For reference | Z15: AUPRC | AA15: For reference | AD15: AUPRC | AE15: For reference | AH15: AUPRC | AI15: For reference | AL15: AUPRC | AM15: For reference | AP15: AUPRC | AQ15: For reference | AT15: AUPRC | AU15: For reference | AX15: AUPRC | AY15: For reference
D16: mean | E16: σ | F16: CV | G16: mean | H16: σ | I16: CV | J16: mean | K16: σ | L16: CV | O16: Recall | P16: F1 | S16: Recall | T16: F1 | W16: Recall | X16: F1 | AA16: Recall | AB16: F1 | AE16: Recall | AF16: F1 | AI16: Recall | AJ16: F1 | AM16: Recall | AN16: F1 | AQ16: Recall | AR16: F1 | AU16: Recall | AV16: F1 | AY16: Recall | AZ16: F1
B17: LR | C17: =D18/D17-1 -> 0.29701089 | D17: =(N17+R17+V17+Z17+AD17+AH17+AL17+AP17+AT17+AX17)/10 -> 0.41049 | E17: =SQRT(((N17-D17)^2+(R17-D17)^2+(V17-D17)^2+(Z17-D17)^2+(AD17-D17)^2+(AH17-D17)^2+(AL17-D17)^2+(AP17-D17)^2+(AT17-D17)^2+(AX17-D17)^2)/10) -> 0.0084127819 | F17: =E17/D17 -> 0.020494487 | G17: =(O17+S17+W17+AA17+AE17+AI17+AM17+AQ17+AU17+AY17)/10 -> 0.745 | H17: =SQRT(((O17-G17)^2+(S17-G17)^2+(W17-G17)^2+(AA17-G17)^2+(AE17-G17)^2+(AI17-G17)^2+(AM17-G17)^2+(AQ17-G17)^2+(AU17-G17)^2+(AY17-G17)^2)/10) -> 0.012845233 | I17: =H17/G17 -> 0.017241923 | J17: =(P17+T17+X17+AB17+AF17+AJ17+AN17+AR17+AV17+AZ17)/10 -> 0.46303 | K17: =SQRT(((P17-J17)^2+(T17-J17)^2+(X17-J17)^2+(AB17-J17)^2+(AF17-J17)^2+(AJ17-J17)^2+(AN17-J17)^2+(AR17-J17)^2+(AV17-J17)^2+(AZ17-J17)^2)/10) -> 0.0023413885 | L17: =K17/J17 -> 0.0050566669 | N17: 0.4184 | O17: 0.73 | P17: 0.4606 | R17: 0.4078 | S17: 0.74 | T17: 0.4596 | V17: 0.4025 | W17: 0.76 | X17: 0.4634 | Z17: 0.4241 | AA17: 0.73 | AB17: 0.4665 | AD17: 0.4078 | AE17: 0.74 | AF17: 0.4596 | AH17: 0.4025 | AI17: 0.76 | AJ17: 0.4634 | AL17: 0.4025 | AM17: 0.76 | AN17: 0.4634 | AP17: 0.4127 | AQ17: 0.74 | AR17: 0.4639 | AT17: 0.4025 | AU17: 0.76 | AV17: 0.4634 | AX17: 0.4241 | AY17: 0.73 | AZ17: 0.4665
B18: CLT-TAB without CATA | D18: =(N18+R18+V18+Z18+AD18+AH18+AL18+AP18+AT18+AX18)/10 -> 0.53241 | E18: =SQRT(((N18-D18)^2+(R18-D18)^2+(V18-D18)^2+(Z18-D18)^2+(AD18-D18)^2+(AH18-D18)^2+(AL18-D18)^2+(AP18-D18)^2+(AT18-D18)^2+(AX18-D18)^2)/10) -> 0.018444698 | F18: =E18/D18 -> 0.034643787 | G18: =(O18+S18+W18+AA18+AE18+AI18+AM18+AQ18+AU18+AY18)/10 -> 0.733 | H18: =SQRT(((O18-G18)^2+(S18-G18)^2+(W18-G18)^2+(AA18-G18)^2+(AE18-G18)^2+(AI18-G18)^2+(AM18-G18)^2+(AQ18-G18)^2+(AU18-G18)^2+(AY18-G18)^2)/10) -> 0.019 | I18: =H18/G18 -> 0.025920873 | J18: =(P18+T18+X18+AB18+AF18+AJ18+AN18+AR18+AV18+AZ18)/10 -> 0.4958 | K18: =SQRT(((P18-J18)^2+(T18-J18)^2+(X18-J18)^2+(AB18-J18)^2+(AF18-J18)^2+(AJ18-J18)^2+(AN18-J18)^2+(AR18-J18)^2+(AV18-J18)^2+(AZ18-J18)^2)/10) -> 0.012065239 | L18: =K18/J18 -> 0.024334892 | N18: 0.5425 | O18: 0.74 | P18: 0.4837 | R18: 0.545 | S18: 0.71 | T18: 0.4913 | V18: 0.5009 | W18: 0.73 | X18: 0.4771 | Z18: 0.5242 | AA18: 0.74 | AB18: 0.5068 | AD18: 0.5051 | AE18: 0.72 | AF18: 0.4832 | AH18: 0.5212 | AI18: 0.73 | AJ18: 0.5017 | AL18: 0.5325 | AM18: 0.77 | AN18: 0.5168 | AP18: 0.5605 | AQ18: 0.7 | AR18: 0.5091 | AT18: 0.5509 | AU18: 0.75 | AV18: 0.495 | AX18: 0.5413 | AY18: 0.74 | AZ18: 0.4933
B19: FT-transformer | C19: =D18/D19-1 -> 0.42878995 | D19: =(N19+R19+V19+Z19+AD19+AH19+AL19+AP19+AT19+AX19)/10 -> 0.37263 | E19: =SQRT(((N19-D19)^2+(R19-D19)^2+(V19-D19)^2+(Z19-D19)^2+(AD19-D19)^2+(AH19-D19)^2+(AL19-D19)^2+(AP19-D19)^2+(AT19-D19)^2+(AX19-D19)^2)/10) -> 0.016933166 | F19: =E19/D19 -> 0.045442304 | G19: =(O19+S19+W19+AA19+AE19+AI19+AM19+AQ19+AU19+AY19)/10 -> 0.322 | H19: =SQRT(((O19-G19)^2+(S19-G19)^2+(W19-G19)^2+(AA19-G19)^2+(AE19-G19)^2+(AI19-G19)^2+(AM19-G19)^2+(AQ19-G19)^2+(AU19-G19)^2+(AY19-G19)^2)/10) -> 0.036 | I19: =H19/G19 -> 0.11180124 | J19: =(P19+T19+X19+AB19+AF19+AJ19+AN19+AR19+AV19+AZ19)/10 -> 0.34713 | K19: =SQRT(((P19-J19)^2+(T19-J19)^2+(X19-J19)^2+(AB19-J19)^2+(AF19-J19)^2+(AJ19-J19)^2+(AN19-J19)^2+(AR19-J19)^2+(AV19-J19)^2+(AZ19-J19)^2)/10) -> 0.028374956 | L19: =K19/J19 -> 0.081741582 | N19: 0.3543 | O19: 0.26 | P19: 0.3006 | R19: 0.3923 | S19: 0.35 | T19: 0.3684 | V19: 0.3669 | W19: 0.3 | X19: 0.3371 | Z19: 0.3511 | AA19: 0.29 | AB19: 0.3169 | AD19: 0.3666 | AE19: 0.37 | AF19: 0.3756 | AH19: 0.3864 | AI19: 0.34 | AJ19: 0.3716 | AL19: 0.3668 | AM19: 0.33 | AN19: 0.3455 | AP19: 0.3599 | AQ19: 0.28 | AR19: 0.3182 | AT19: 0.3744 | AU19: 0.33 | AV19: 0.3438 | AX19: 0.4076 | AY19: 0.37 | AZ19: 0.3936
B20: CatBoost | C20: =D18/D20-1 -> 0.051694848 | D20: =(N20+R20+V20+Z20+AD20+AH20+AL20+AP20+AT20+AX20)/10 -> 0.50624 | E20: =SQRT(((N20-D20)^2+(R20-D20)^2+(V20-D20)^2+(Z20-D20)^2+(AD20-D20)^2+(AH20-D20)^2+(AL20-D20)^2+(AP20-D20)^2+(AT20-D20)^2+(AX20-D20)^2)/10) -> 0.019672885 | F20: =E20/D20 -> 0.038860787 | G20: =(O20+S20+W20+AA20+AE20+AI20+AM20+AQ20+AU20+AY20)/10 -> 0.816 | H20: =SQRT(((O20-G20)^2+(S20-G20)^2+(W20-G20)^2+(AA20-G20)^2+(AE20-G20)^2+(AI20-G20)^2+(AM20-G20)^2+(AQ20-G20)^2+(AU20-G20)^2+(AY20-G20)^2)/10) -> 0.023323808 | I20: =H20/G20 -> 0.028583098 | J20: =(P20+T20+X20+AB20+AF20+AJ20+AN20+AR20+AV20+AZ20)/10 -> 0.48718 | K20: =SQRT(((P20-J20)^2+(T20-J20)^2+(X20-J20)^2+(AB20-J20)^2+(AF20-J20)^2+(AJ20-J20)^2+(AN20-J20)^2+(AR20-J20)^2+(AV20-J20)^2+(AZ20-J20)^2)/10) -> 0.012862333 | L20: =K20/J20 -> 0.026401602 | N20: 0.5069 | O20: 0.82 | P20: 0.474 | R20: 0.5117 | S20: 0.78 | T20: 0.5049 | V20: 0.4809 | W20: 0.78 | X20: 0.4685 | Z20: 0.5079 | AA20: 0.81 | AB20: 0.4894 | AD20: 0.5024 | AE20: 0.84 | AF20: 0.48 | AH20: 0.4748 | AI20: 0.85 | AJ20: 0.4843 | AL20: 0.5176 | AM20: 0.83 | AN20: 0.4882 | AP20: 0.546 | AQ20: 0.8 | AR20: 0.5079 | AT20: 0.4916 | AU20: 0.84 | AV20: 0.4746 | AX20: 0.5226 | AY20: 0.81 | AZ20: 0.5
B21: SCARF | C21: =D18/D21-1 -> 2.6556578 | D21: =(N21+R21+V21+Z21+AD21+AH21+AL21+AP21+AT21+AX21)/10 -> 0.14564 | E21: =SQRT(((N21-D21)^2+(R21-D21)^2+(V21-D21)^2+(Z21-D21)^2+(AD21-D21)^2+(AH21-D21)^2+(AL21-D21)^2+(AP21-D21)^2+(AT21-D21)^2+(AX21-D21)^2)/10) -> 0.011757398 | F21: =E21/D21 -> 0.080729179 | G21: =(O21+S21+W21+AA21+AE21+AI21+AM21+AQ21+AU21+AY21)/10 -> 0.416 | H21: =SQRT(((O21-G21)^2+(S21-G21)^2+(W21-G21)^2+(AA21-G21)^2+(AE21-G21)^2+(AI21-G21)^2+(AM21-G21)^2+(AQ21-G21)^2+(AU21-G21)^2+(AY21-G21)^2)/10) -> 0.050635956 | I21: =H21/G21 -> 0.12172105 | J21: =(P21+T21+X21+AB21+AF21+AJ21+AN21+AR21+AV21+AZ21)/10 -> 0.21802 | K21: =SQRT(((P21-J21)^2+(T21-J21)^2+(X21-J21)^2+(AB21-J21)^2+(AF21-J21)^2+(AJ21-J21)^2+(AN21-J21)^2+(AR21-J21)^2+(AV21-J21)^2+(AZ21-J21)^2)/10) -> 0.028448051 | L21: =K21/J21 -> 0.13048368 | N21: 0.1642 | O21: 0.46 | P21: 0.2521 | R21: 0.1634 | S21: 0.5 | T21: 0.2667 | V21: 0.1343 | W21: 0.38 | X21: 0.1979 | Z21: 0.1427 | AA21: 0.46 | AB21: 0.2383 | AD21: 0.1615 | AE21: 0.48 | AF21: 0.2487 | AH21: 0.134 | AI21: 0.4 | AJ21: 0.203 | AL21: 0.1431 | AM21: 0.36 | AN21: 0.192 | AP21: 0.1363 | AQ21: 0.39 | AR21: 0.2037 | AT21: 0.1392 | AU21: 0.37 | AV21: 0.1883 | AX21: 0.1377 | AY21: 0.36 | AZ21: 0.1895
C23: effect, % | D23: AUPRC | G23: Recall | J23: F1 | N23: AUPRC | O23: For reference | R23: AUPRC | S23: For reference | V23: AUPRC | W23: For reference | Z23: AUPRC | AA23: For reference | AD23: AUPRC | AE23: For reference | AH23: AUPRC | AI23: For reference | AL23: AUPRC | AM23: For reference | AP23: AUPRC | AQ23: For reference | AT23: AUPRC | AU23: For reference | AX23: AUPRC | AY23: For reference
D24: mean | E24: σ | F24: CV | G24: mean | H24: σ | I24: CV | J24: mean | K24: σ | L24: CV | O24: Recall | P24: F1 | S24: Recall | T24: F1 | W24: Recall | X24: F1 | AA24: Recall | AB24: F1 | AE24: Recall | AF24: F1 | AI24: Recall | AJ24: F1 | AM24: Recall | AN24: F1 | AQ24: Recall | AR24: F1 | AU24: Recall | AV24: F1 | AY24: Recall | AZ24: F1
B25: LR | C25: =D26/D25-1 -> 0.31118907 | D25: =(N25+R25+V25+Z25+AD25+AH25+AL25+AP25+AT25+AX25)/10 -> 0.41049 | E25: =SQRT(((N25-D25)^2+(R25-D25)^2+(V25-D25)^2+(Z25-D25)^2+(AD25-D25)^2+(AH25-D25)^2+(AL25-D25)^2+(AP25-D25)^2+(AT25-D25)^2+(AX25-D25)^2)/10) -> 0.0084127819 | F25: =E25/D25 -> 0.020494487 | G25: =(O25+S25+W25+AA25+AE25+AI25+AM25+AQ25+AU25+AY25)/10 -> 0.745 | H25: =SQRT(((O25-G25)^2+(S25-G25)^2+(W25-G25)^2+(AA25-G25)^2+(AE25-G25)^2+(AI25-G25)^2+(AM25-G25)^2+(AQ25-G25)^2+(AU25-G25)^2+(AY25-G25)^2)/10) -> 0.012845233 | I25: =H25/G25 -> 0.017241923 | J25: =(P25+T25+X25+AB25+AF25+AJ25+AN25+AR25+AV25+AZ25)/10 -> 0.46303 | K25: =SQRT(((P25-J25)^2+(T25-J25)^2+(X25-J25)^2+(AB25-J25)^2+(AF25-J25)^2+(AJ25-J25)^2+(AN25-J25)^2+(AR25-J25)^2+(AV25-J25)^2+(AZ25-J25)^2)/10) -> 0.0023413885 | L25: =K25/J25 -> 0.0050566669 | N25: 0.4184 | O25: 0.73 | P25: 0.4606 | R25: 0.4078 | S25: 0.74 | T25: 0.4596 | V25: 0.4025 | W25: 0.76 | X25: 0.4634 | Z25: 0.4241 | AA25: 0.73 | AB25: 0.4665 | AD25: 0.4078 | AE25: 0.74 | AF25: 0.4596 | AH25: 0.4025 | AI25: 0.76 | AJ25: 0.4634 | AL25: 0.4025 | AM25: 0.76 | AN25: 0.4634 | AP25: 0.4127 | AQ25: 0.74 | AR25: 0.4639 | AT25: 0.4025 | AU25: 0.76 | AV25: 0.4634 | AX25: 0.4241 | AY25: 0.73 | AZ25: 0.4665
B26: CLT-TAB without SQP | D26: =(N26+R26+V26+Z26+AD26+AH26+AL26+AP26+AT26+AX26)/10 -> 0.53823 | E26: =SQRT(((N26-D26)^2+(R26-D26)^2+(V26-D26)^2+(Z26-D26)^2+(AD26-D26)^2+(AH26-D26)^2+(AL26-D26)^2+(AP26-D26)^2+(AT26-D26)^2+(AX26-D26)^2)/10) -> 0.017594036 | F26: =E26/D26 -> 0.032688694 | G26: =(O26+S26+W26+AA26+AE26+AI26+AM26+AQ26+AU26+AY26)/10 -> 0.735 | H26: =SQRT(((O26-G26)^2+(S26-G26)^2+(W26-G26)^2+(AA26-G26)^2+(AE26-G26)^2+(AI26-G26)^2+(AM26-G26)^2+(AQ26-G26)^2+(AU26-G26)^2+(AY26-G26)^2)/10) -> 0.022472205 | I26: =H26/G26 -> 0.030574429 | J26: =(P26+T26+X26+AB26+AF26+AJ26+AN26+AR26+AV26+AZ26)/10 -> 0.49875 | K26: =SQRT(((P26-J26)^2+(T26-J26)^2+(X26-J26)^2+(AB26-J26)^2+(AF26-J26)^2+(AJ26-J26)^2+(AN26-J26)^2+(AR26-J26)^2+(AV26-J26)^2+(AZ26-J26)^2)/10) -> 0.01729909 | L26: =K26/J26 -> 0.034684891 | N26: 0.5656 | O26: 0.7 | P26: 0.4811 | R26: 0.5684 | S26: 0.73 | T26: 0.4916 | V26: 0.5434 | W26: 0.77 | X26: 0.522 | Z26: 0.5324 | AA26: 0.73 | AB26: 0.5069 | AD26: 0.5183 | AE26: 0.71 | AF26: 0.4702 | AH26: 0.5439 | AI26: 0.76 | AJ26: 0.5135 | AL26: 0.5425 | AM26: 0.71 | AN26: 0.4846 | AP26: 0.534 | AQ26: 0.76 | AR26: 0.5241 | AT26: 0.517 | AU26: 0.74 | AV26: 0.4884 | AX26: 0.5168 | AY26: 0.74 | AZ26: 0.5051
B27: FT-transformer | C27: =D26/D27-1 -> 0.44440866 | D27: =(N27+R27+V27+Z27+AD27+AH27+AL27+AP27+AT27+AX27)/10 -> 0.37263 | E27: =SQRT(((N27-D27)^2+(R27-D27)^2+(V27-D27)^2+(Z27-D27)^2+(AD27-D27)^2+(AH27-D27)^2+(AL27-D27)^2+(AP27-D27)^2+(AT27-D27)^2+(AX27-D27)^2)/10) -> 0.016933166 | F27: =E27/D27 -> 0.045442304 | G27: =(O27+S27+W27+AA27+AE27+AI27+AM27+AQ27+AU27+AY27)/10 -> 0.322 | H27: =SQRT(((O27-G27)^2+(S27-G27)^2+(W27-G27)^2+(AA27-G27)^2+(AE27-G27)^2+(AI27-G27)^2+(AM27-G27)^2+(AQ27-G27)^2+(AU27-G27)^2+(AY27-G27)^2)/10) -> 0.036 | I27: =H27/G27 -> 0.11180124 | J27: =(P27+T27+X27+AB27+AF27+AJ27+AN27+AR27+AV27+AZ27)/10 -> 0.34713 | K27: =SQRT(((P27-J27)^2+(T27-J27)^2+(X27-J27)^2+(AB27-J27)^2+(AF27-J27)^2+(AJ27-J27)^2+(AN27-J27)^2+(AR27-J27)^2+(AV27-J27)^2+(AZ27-J27)^2)/10) -> 0.028374956 | L27: =K27/J27 -> 0.081741582 | N27: 0.3543 | O27: 0.26 | P27: 0.3006 | R27: 0.3923 | S27: 0.35 | T27: 0.3684 | V27: 0.3669 | W27: 0.3 | X27: 0.3371 | Z27: 0.3511 | AA27: 0.29 | AB27: 0.3169 | AD27: 0.3666 | AE27: 0.37 | AF27: 0.3756 | AH27: 0.3864 | AI27: 0.34 | AJ27: 0.3716 | AL27: 0.3668 | AM27: 0.33 | AN27: 0.3455 | AP27: 0.3599 | AQ27: 0.28 | AR27: 0.3182 | AT27: 0.3744 | AU27: 0.33 | AV27: 0.3438 | AX27: 0.4076 | AY27: 0.37 | AZ27: 0.3936
B28: CatBoost | C28: =D26/D28-1 -> 0.063191372 | D28: =(N28+R28+V28+Z28+AD28+AH28+AL28+AP28+AT28+AX28)/10 -> 0.50624 | E28: =SQRT(((N28-D28)^2+(R28-D28)^2+(V28-D28)^2+(Z28-D28)^2+(AD28-D28)^2+(AH28-D28)^2+(AL28-D28)^2+(AP28-D28)^2+(AT28-D28)^2+(AX28-D28)^2)/10) -> 0.019672885 | F28: =E28/D28 -> 0.038860787 | G28: =(O28+S28+W28+AA28+AE28+AI28+AM28+AQ28+AU28+AY28)/10 -> 0.816 | H28: =SQRT(((O28-G28)^2+(S28-G28)^2+(W28-G28)^2+(AA28-G28)^2+(AE28-G28)^2+(AI28-G28)^2+(AM28-G28)^2+(AQ28-G28)^2+(AU28-G28)^2+(AY28-G28)^2)/10) -> 0.023323808 | I28: =H28/G28 -> 0.028583098 | J28: =(P28+T28+X28+AB28+AF28+AJ28+AN28+AR28+AV28+AZ28)/10 -> 0.48718 | K28: =SQRT(((P28-J28)^2+(T28-J28)^2+(X28-J28)^2+(AB28-J28)^2+(AF28-J28)^2+(AJ28-J28)^2+(AN28-J28)^2+(AR28-J28)^2+(AV28-J28)^2+(AZ28-J28)^2)/10) -> 0.012862333 | L28: =K28/J28 -> 0.026401602 | N28: 0.5069 | O28: 0.82 | P28: 0.474 | R28: 0.5117 | S28: 0.78 | T28: 0.5049 | V28: 0.4809 | W28: 0.78 | X28: 0.4685 | Z28: 0.5079 | AA28: 0.81 | AB28: 0.4894 | AD28: 0.5024 | AE28: 0.84 | AF28: 0.48 | AH28: 0.4748 | AI28: 0.85 | AJ28: 0.4843 | AL28: 0.5176 | AM28: 0.83 | AN28: 0.4882 | AP28: 0.546 | AQ28: 0.8 | AR28: 0.5079 | AT28: 0.4916 | AU28: 0.84 | AV28: 0.4746 | AX28: 0.5226 | AY28: 0.81 | AZ28: 0.5
B29: SCARF | C29: =D26/D29-1 -> 2.6956193 | D29: =(N29+R29+V29+Z29+AD29+AH29+AL29+AP29+AT29+AX29)/10 -> 0.14564 | E29: =SQRT(((N29-D29)^2+(R29-D29)^2+(V29-D29)^2+(Z29-D29)^2+(AD29-D29)^2+(AH29-D29)^2+(AL29-D29)^2+(AP29-D29)^2+(AT29-D29)^2+(AX29-D29)^2)/10) -> 0.011757398 | F29: =E29/D29 -> 0.080729179 | G29: =(O29+S29+W29+AA29+AE29+AI29+AM29+AQ29+AU29+AY29)/10 -> 0.416 | H29: =SQRT(((O29-G29)^2+(S29-G29)^2+(W29-G29)^2+(AA29-G29)^2+(AE29-G29)^2+(AI29-G29)^2+(AM29-G29)^2+(AQ29-G29)^2+(AU29-G29)^2+(AY29-G29)^2)/10) -> 0.050635956 | I29: =H29/G29 -> 0.12172105 | J29: =(P29+T29+X29+AB29+AF29+AJ29+AN29+AR29+AV29+AZ29)/10 -> 0.21802 | K29: =SQRT(((P29-J29)^2+(T29-J29)^2+(X29-J29)^2+(AB29-J29)^2+(AF29-J29)^2+(AJ29-J29)^2+(AN29-J29)^2+(AR29-J29)^2+(AV29-J29)^2+(AZ29-J29)^2)/10) -> 0.028448051 | L29: =K29/J29 -> 0.13048368 | N29: 0.1642 | O29: 0.46 | P29: 0.2521 | R29: 0.1634 | S29: 0.5 | T29: 0.2667 | V29: 0.1343 | W29: 0.38 | X29: 0.1979 | Z29: 0.1427 | AA29: 0.46 | AB29: 0.2383 | AD29: 0.1615 | AE29: 0.48 | AF29: 0.2487 | AH29: 0.134 | AI29: 0.4 | AJ29: 0.203 | AL29: 0.1431 | AM29: 0.36 | AN29: 0.192 | AP29: 0.1363 | AQ29: 0.39 | AR29: 0.2037 | AT29: 0.1392 | AU29: 0.37 | AV29: 0.1883 | AX29: 0.1377 | AY29: 0.36 | AZ29: 0.1895
C31: effect, % | D31: AUPRC | G31: Recall | J31: F1 | N31: AUPRC | O31: For reference | R31: AUPRC | S31: For reference | V31: AUPRC | W31: For reference | Z31: AUPRC | AA31: For reference | AD31: AUPRC | AE31: For reference | AH31: AUPRC | AI31: For reference | AL31: AUPRC | AM31: For reference | AP31: AUPRC | AQ31: For reference | AT31: AUPRC | AU31: For reference | AX31: AUPRC | AY31: For reference
D32: mean | E32: σ | F32: CV | G32: mean | H32: σ | I32: CV | J32: mean | K32: σ | L32: CV | O32: Recall | P32: F1 | S32: Recall | T32: F1 | W32: Recall | X32: F1 | AA32: Recall | AB32: F1 | AE32: Recall | AF32: F1 | AI32: Recall | AJ32: F1 | AM32: Recall | AN32: F1 | AQ32: Recall | AR32: F1 | AU32: Recall | AV32: F1 | AY32: Recall | AZ32: F1
B33: LR | C33: =D34/D33-1 -> 0.2796414 | D33: =(N33+R33+V33+Z33+AD33+AH33+AL33+AP33+AT33+AX33)/10 -> 0.41049 | E33: =SQRT(((N33-D33)^2+(R33-D33)^2+(V33-D33)^2+(Z33-D33)^2+(AD33-D33)^2+(AH33-D33)^2+(AL33-D33)^2+(AP33-D33)^2+(AT33-D33)^2+(AX33-D33)^2)/10) -> 0.0084127819 | F33: =E33/D33 -> 0.020494487 | G33: =(O33+S33+W33+AA33+AE33+AI33+AM33+AQ33+AU33+AY33)/10 -> 0.745 | H33: =SQRT(((O33-G33)^2+(S33-G33)^2+(W33-G33)^2+(AA33-G33)^2+(AE33-G33)^2+(AI33-G33)^2+(AM33-G33)^2+(AQ33-G33)^2+(AU33-G33)^2+(AY33-G33)^2)/10) -> 0.012845233 | I33: =H33/G33 -> 0.017241923 | J33: =(P33+T33+X33+AB33+AF33+AJ33+AN33+AR33+AV33+AZ33)/10 -> 0.46303 | K33: =SQRT(((P33-J33)^2+(T33-J33)^2+(X33-J33)^2+(AB33-J33)^2+(AF33-J33)^2+(AJ33-J33)^2+(AN33-J33)^2+(AR33-J33)^2+(AV33-J33)^2+(AZ33-J33)^2)/10) -> 0.0023413885 | L33: =K33/J33 -> 0.0050566669 | N33: 0.4184 | O33: 0.73 | P33: 0.4606 | R33: 0.4078 | S33: 0.74 | T33: 0.4596 | V33: 0.4025 | W33: 0.76 | X33: 0.4634 | Z33: 0.4241 | AA33: 0.73 | AB33: 0.4665 | AD33: 0.4078 | AE33: 0.74 | AF33: 0.4596 | AH33: 0.4025 | AI33: 0.76 | AJ33: 0.4634 | AL33: 0.4025 | AM33: 0.76 | AN33: 0.4634 | AP33: 0.4127 | AQ33: 0.74 | AR33: 0.4639 | AT33: 0.4025 | AU33: 0.76 | AV33: 0.4634 | AX33: 0.4241 | AY33: 0.73 | AZ33: 0.4665
B34: CLT-TAB without CATA and SQP | D34: =(N34+R34+V34+Z34+AD34+AH34+AL34+AP34+AT34+AX34)/10 -> 0.52528 | E34: =SQRT(((N34-D34)^2+(R34-D34)^2+(V34-D34)^2+(Z34-D34)^2+(AD34-D34)^2+(AH34-D34)^2+(AL34-D34)^2+(AP34-D34)^2+(AT34-D34)^2+(AX34-D34)^2)/10) -> 0.018537141 | F34: =E34/D34 -> 0.035290019 | G34: =(O34+S34+W34+AA34+AE34+AI34+AM34+AQ34+AU34+AY34)/10 -> 0.708 | H34: =SQRT(((O34-G34)^2+(S34-G34)^2+(W34-G34)^2+(AA34-G34)^2+(AE34-G34)^2+(AI34-G34)^2+(AM34-G34)^2+(AQ34-G34)^2+(AU34-G34)^2+(AY34-G34)^2)/10) -> 0.023579652 | I34: =H34/G34 -> 0.033304594 | J34: =(P34+T34+X34+AB34+AF34+AJ34+AN34+AR34+AV34+AZ34)/10 -> 0.48902 | K34: =SQRT(((P34-J34)^2+(T34-J34)^2+(X34-J34)^2+(AB34-J34)^2+(AF34-J34)^2+(AJ34-J34)^2+(AN34-J34)^2+(AR34-J34)^2+(AV34-J34)^2+(AZ34-J34)^2)/10) -> 0.018489608 | L34: =K34/J34 -> 0.037809513 | N34: 0.4886 | O34: 0.66 | P34: 0.4599 | R34: 0.5357 | S34: 0.73 | T34: 0.5123 | V34: 0.5349 | W34: 0.7 | X34: 0.5072 | Z34: 0.5218 | AA34: 0.72 | AB34: 0.4966 | AD34: 0.4914 | AE34: 0.68 | AF34: 0.4755 | AH34: 0.536 | AI34: 0.73 | AJ34: 0.5141 | AL34: 0.5363 | AM34: 0.7 | AN34: 0.4844 | AP34: 0.5266 | AQ34: 0.7 | AR34: 0.4651 | AT34: 0.5433 | AU34: 0.74 | AV34: 0.4983 | AX34: 0.5382 | AY34: 0.72 | AZ34: 0.4768
B35: FT-transformer | C35: =D34/D35-1 -> 0.40965569 | D35: =(N35+R35+V35+Z35+AD35+AH35+AL35+AP35+AT35+AX35)/10 -> 0.37263 | E35: =SQRT(((N35-D35)^2+(R35-D35)^2+(V35-D35)^2+(Z35-D35)^2+(AD35-D35)^2+(AH35-D35)^2+(AL35-D35)^2+(AP35-D35)^2+(AT35-D35)^2+(AX35-D35)^2)/10) -> 0.016933166 | F35: =E35/D35 -> 0.045442304 | G35: =(O35+S35+W35+AA35+AE35+AI35+AM35+AQ35+AU35+AY35)/10 -> 0.322 | H35: =SQRT(((O35-G35)^2+(S35-G35)^2+(W35-G35)^2+(AA35-G35)^2+(AE35-G35)^2+(AI35-G35)^2+(AM35-G35)^2+(AQ35-G35)^2+(AU35-G35)^2+(AY35-G35)^2)/10) -> 0.036 | I35: =H35/G35 -> 0.11180124 | J35: =(P35+T35+X35+AB35+AF35+AJ35+AN35+AR35+AV35+AZ35)/10 -> 0.34713 | K35: =SQRT(((P35-J35)^2+(T35-J35)^2+(X35-J35)^2+(AB35-J35)^2+(AF35-J35)^2+(AJ35-J35)^2+(AN35-J35)^2+(AR35-J35)^2+(AV35-J35)^2+(AZ35-J35)^2)/10) -> 0.028374956 | L35: =K35/J35 -> 0.081741582 | N35: 0.3543 | O35: 0.26 | P35: 0.3006 | R35: 0.3923 | S35: 0.35 | T35: 0.3684 | V35: 0.3669 | W35: 0.3 | X35: 0.3371 | Z35: 0.3511 | AA35: 0.29 | AB35: 0.3169 | AD35: 0.3666 | AE35: 0.37 | AF35: 0.3756 | AH35: 0.3864 | AI35: 0.34 | AJ35: 0.3716 | AL35: 0.3668 | AM35: 0.33 | AN35: 0.3455 | AP35: 0.3599 | AQ35: 0.28 | AR35: 0.3182 | AT35: 0.3744 | AU35: 0.33 | AV35: 0.3438 | AX35: 0.4076 | AY35: 0.37 | AZ35: 0.3936
B36: CatBoost | C36: =D34/D36-1 -> 0.037610619 | D36: =(N36+R36+V36+Z36+AD36+AH36+AL36+AP36+AT36+AX36)/10 -> 0.50624 | E36: =SQRT(((N36-D36)^2+(R36-D36)^2+(V36-D36)^2+(Z36-D36)^2+(AD36-D36)^2+(AH36-D36)^2+(AL36-D36)^2+(AP36-D36)^2+(AT36-D36)^2+(AX36-D36)^2)/10) -> 0.019672885 | F36: =E36/D36 -> 0.038860787 | G36: =(O36+S36+W36+AA36+AE36+AI36+AM36+AQ36+AU36+AY36)/10 -> 0.816 | H36: =SQRT(((O36-G36)^2+(S36-G36)^2+(W36-G36)^2+(AA36-G36)^2+(AE36-G36)^2+(AI36-G36)^2+(AM36-G36)^2+(AQ36-G36)^2+(AU36-G36)^2+(AY36-G36)^2)/10) -> 0.023323808 | I36: =H36/G36 -> 0.028583098 | J36: =(P36+T36+X36+AB36+AF36+AJ36+AN36+AR36+AV36+AZ36)/10 -> 0.48718 | K36: =SQRT(((P36-J36)^2+(T36-J36)^2+(X36-J36)^2+(AB36-J36)^2+(AF36-J36)^2+(AJ36-J36)^2+(AN36-J36)^2+(AR36-J36)^2+(AV36-J36)^2+(AZ36-J36)^2)/10) -> 0.012862333 | L36: =K36/J36 -> 0.026401602 | N36: 0.5069 | O36: 0.82 | P36: 0.474 | R36: 0.5117 | S36: 0.78 | T36: 0.5049 | V36: 0.4809 | W36: 0.78 | X36: 0.4685 | Z36: 0.5079 | AA36: 0.81 | AB36: 0.4894 | AD36: 0.5024 | AE36: 0.84 | AF36: 0.48 | AH36: 0.4748 | AI36: 0.85 | AJ36: 0.4843 | AL36: 0.5176 | AM36: 0.83 | AN36: 0.4882 | AP36: 0.546 | AQ36: 0.8 | AR36: 0.5079 | AT36: 0.4916 | AU36: 0.84 | AV36: 0.4746 | AX36: 0.5226 | AY36: 0.81 | AZ36: 0.5
B37: SCARF | C37: =D34/D37-1 -> 2.6067015 | D37: =(N37+R37+V37+Z37+AD37+AH37+AL37+AP37+AT37+AX37)/10 -> 0.14564 | E37: =SQRT(((N37-D37)^2+(R37-D37)^2+(V37-D37)^2+(Z37-D37)^2+(AD37-D37)^2+(AH37-D37)^2+(AL37-D37)^2+(AP37-D37)^2+(AT37-D37)^2+(AX37-D37)^2)/10) -> 0.011757398 | F37: =E37/D37 -> 0.080729179 | G37: =(O37+S37+W37+AA37+AE37+AI37+AM37+AQ37+AU37+AY37)/10 -> 0.416 | H37: =SQRT(((O37-G37)^2+(S37-G37)^2+(W37-G37)^2+(AA37-G37)^2+(AE37-G37)^2+(AI37-G37)^2+(AM37-G37)^2+(AQ37-G37)^2+(AU37-G37)^2+(AY37-G37)^2)/10) -> 0.050635956 | I37: =H37/G37 -> 0.12172105 | J37: =(P37+T37+X37+AB37+AF37+AJ37+AN37+AR37+AV37+AZ37)/10 -> 0.21802 | K37: =SQRT(((P37-J37)^2+(T37-J37)^2+(X37-J37)^2+(AB37-J37)^2+(AF37-J37)^2+(AJ37-J37)^2+(AN37-J37)^2+(AR37-J37)^2+(AV37-J37)^2+(AZ37-J37)^2)/10) -> 0.028448051 | L37: =K37/J37 -> 0.13048368 | N37: 0.1642 | O37: 0.46 | P37: 0.2521 | R37: 0.1634 | S37: 0.5 | T37: 0.2667 | V37: 0.1343 | W37: 0.38 | X37: 0.1979 | Z37: 0.1427 | AA37: 0.46 | AB37: 0.2383 | AD37: 0.1615 | AE37: 0.48 | AF37: 0.2487 | AH37: 0.134 | AI37: 0.4 | AJ37: 0.203 | AL37: 0.1431 | AM37: 0.36 | AN37: 0.192 | AP37: 0.1363 | AQ37: 0.39 | AR37: 0.2037 | AT37: 0.1392 | AU37: 0.37 | AV37: 0.1883 | AX37: 0.1377 | AY37: 0.36 | AZ37: 0.1895

Sheet Card Default
B1: Overview
B2: The Credit Card Default (UCI) dataset, also known as the “default of credit card clients” dataset, is a classic benchmark for binary classification in credit risk modelling. It was introduced by Yeh and Lien (2009) and has become a standard reference for evaluating machine learning methods in financial risk prediction . The dataset consists of 30,000 credit card clients in Taiwan, each described by 24 features. The data were collected from April to September 2005 and include demographic information, credit limits, bill amounts, and the repayment status for the past six months (April–September) as well as payments for the same period . There are 23 predictive attributes (demographic factors, historical payment records, bill statements and payment amounts) and a binary target variable default.payment.next.month, which takes the value 1 if the client defaulted on the following month's payment and 0 otherwise . The dataset exhibits a moderate class imbalance: about 22 % of the clients defaulted, while 78 % did not.
B3: We used the Credit Card Default (UCI) dataset, which contains 29 944 instances with a 22,1 % anomaly rate. It comprises 14 numerical and 9 categorical features. The data were used after preprocessing (missing values, duplicates, and constant features were removed). F1 and Recall scores were obtained with a threshold of 0.5. We used 452 instances for finetuning, of which 100 were anomalies, and the same number (452 instances, 100 anomalies) for testing.
B5: Random AUPRC | C5: 0.2212 | N5: Seed
G6: For reference | N6: 42 | R6: 43 | V6: 44 | Z6: 45 | AD6: 46 | AH6: 47 | AL6: 48 | AP6: 49 | AT6: 50 | AX6: 51
C7: effect, % | D7: AUPRC | G7: Recall | J7: F1 | N7: AUPRC | O7: For reference | R7: AUPRC | S7: For reference | V7: AUPRC | W7: For reference | Z7: AUPRC | AA7: For reference | AD7: AUPRC | AE7: For reference | AH7: AUPRC | AI7: For reference | AL7: AUPRC | AM7: For reference | AP7: AUPRC | AQ7: For reference | AT7: AUPRC | AU7: For reference | AX7: AUPRC | AY7: For reference
D8: mean | E8: σ | F8: CV | G8: mean | H8: σ | I8: CV | J8: mean | K8: σ | L8: CV | O8: Recall | P8: F1 | S8: Recall | T8: F1 | W8: Recall | X8: F1 | AA8: Recall | AB8: F1 | AE8: Recall | AF8: F1 | AI8: Recall | AJ8: F1 | AM8: Recall | AN8: F1 | AQ8: Recall | AR8: F1 | AU8: Recall | AV8: F1 | AY8: Recall | AZ8: F1
B9: LR | C9: =D10/D9-1 -> 0.42714692 | D9: =(N9+R9+V9+Z9+AD9+AH9+AL9+AP9+AT9+AX9)/10 -> 0.36203 | E9: =SQRT(((N9-D9)^2+(R9-D9)^2+(V9-D9)^2+(Z9-D9)^2+(AD9-D9)^2+(AH9-D9)^2+(AL9-D9)^2+(AP9-D9)^2+(AT9-D9)^2+(AX9-D9)^2)/10) -> 0.012039273 | F9: =E9/D9 -> 0.033254905 | G9: =(O9+S9+W9+AA9+AE9+AI9+AM9+AQ9+AU9+AY9)/10 -> 0.524 | H9: =SQRT(((O9-G9)^2+(S9-G9)^2+(W9-G9)^2+(AA9-G9)^2+(AE9-G9)^2+(AI9-G9)^2+(AM9-G9)^2+(AQ9-G9)^2+(AU9-G9)^2+(AY9-G9)^2)/10) -> 0.028354894 | I9: =H9/G9 -> 0.054112393 | J9: =(P9+T9+X9+AB9+AF9+AJ9+AN9+AR9+AV9+AZ9)/10 -> 0.42508 | K9: =SQRT(((P9-J9)^2+(T9-J9)^2+(X9-J9)^2+(AB9-J9)^2+(AF9-J9)^2+(AJ9-J9)^2+(AN9-J9)^2+(AR9-J9)^2+(AV9-J9)^2+(AZ9-J9)^2)/10) -> 0.014331629 | L9: =K9/J9 -> 0.033715134 | N9: 0.3493 | O9: 0.49 | P9: 0.405 | R9: 0.3597 | S9: 0.53 | T9: 0.4309 | V9: 0.3597 | W9: 0.53 | X9: 0.4309 | Z9: 0.3493 | AA9: 0.49 | AB9: 0.405 | AD9: 0.3597 | AE9: 0.53 | AF9: 0.4309 | AH9: 0.3943 | AI9: 0.49 | AJ9: 0.405 | AL9: 0.3597 | AM9: 0.53 | AN9: 0.4309 | AP9: 0.3692 | AQ9: 0.59 | AR9: 0.4504 | AT9: 0.3597 | AU9: 0.53 | AV9: 0.4309 | AX9: 0.3597 | AY9: 0.53 | AZ9: 0.4309
B10: CLT-TAB | D10: =(N10+R10+V10+Z10+AD10+AH10+AL10+AP10+AT10+AX10)/10 -> 0.51667 | E10: =SQRT(((N10-D10)^2+(R10-D10)^2+(V10-D10)^2+(Z10-D10)^2+(AD10-D10)^2+(AH10-D10)^2+(AL10-D10)^2+(AP10-D10)^2+(AT10-D10)^2+(AX10-D10)^2)/10) -> 0.027509128 | F10: =E10/D10 -> 0.053243129 | G10: =(O10+S10+W10+AA10+AE10+AI10+AM10+AQ10+AU10+AY10)/10 -> 0.61 | H10: =SQRT(((O10-G10)^2+(S10-G10)^2+(W10-G10)^2+(AA10-G10)^2+(AE10-G10)^2+(AI10-G10)^2+(AM10-G10)^2+(AQ10-G10)^2+(AU10-G10)^2+(AY10-G10)^2)/10) -> 0.019493589 | I10: =H10/G10 -> 0.031956703 | J10: =(P10+T10+X10+AB10+AF10+AJ10+AN10+AR10+AV10+AZ10)/10 -> 0.4965 | K10: =SQRT(((P10-J10)^2+(T10-J10)^2+(X10-J10)^2+(AB10-J10)^2+(AF10-J10)^2+(AJ10-J10)^2+(AN10-J10)^2+(AR10-J10)^2+(AV10-J10)^2+(AZ10-J10)^2)/10) -> 0.016693292 | L10: =K10/J10 -> 0.033621938 | N10: 0.5607 | O10: 0.6 | P10: 0.4858 | R10: 0.5217 | S10: 0.59 | T10: 0.4609 | V10: 0.5363 | W10: 0.59 | X10: 0.5043 | Z10: 0.5316 | AA10: 0.63 | AB10: 0.5185 | AD10: 0.5369 | AE10: 0.63 | AF10: 0.5122 | AH10: 0.5268 | AI10: 0.59 | AJ10: 0.4876 | AL10: 0.5062 | AM10: 0.61 | AN10: 0.488 | AP10: 0.4809 | AQ10: 0.63 | AR10: 0.502 | AT10: 0.5028 | AU10: 0.64 | AV10: 0.5161 | AX10: 0.4628 | AY10: 0.59 | AZ10: 0.4896
B11: FT-transformer | C11: =D10/D11-1 -> 0.47178465 | D11: =(N11+R11+V11+Z11+AD11+AH11+AL11+AP11+AT11+AX11)/10 -> 0.35105 | E11: =SQRT(((N11-D11)^2+(R11-D11)^2+(V11-D11)^2+(Z11-D11)^2+(AD11-D11)^2+(AH11-D11)^2+(AL11-D11)^2+(AP11-D11)^2+(AT11-D11)^2+(AX11-D11)^2)/10) -> 0.01900396 | F11: =E11/D11 -> 0.054134625 | G11: =(O11+S11+W11+AA11+AE11+AI11+AM11+AQ11+AU11+AY11)/10 -> 0.399 | H11: =SQRT(((O11-G11)^2+(S11-G11)^2+(W11-G11)^2+(AA11-G11)^2+(AE11-G11)^2+(AI11-G11)^2+(AM11-G11)^2+(AQ11-G11)^2+(AU11-G11)^2+(AY11-G11)^2)/10) -> 0.04414748 | I11: =H11/G11 -> 0.11064531 | J11: =(P11+T11+X11+AB11+AF11+AJ11+AN11+AR11+AV11+AZ11)/10 -> 0.39351 | K11: =SQRT(((P11-J11)^2+(T11-J11)^2+(X11-J11)^2+(AB11-J11)^2+(AF11-J11)^2+(AJ11-J11)^2+(AN11-J11)^2+(AR11-J11)^2+(AV11-J11)^2+(AZ11-J11)^2)/10) -> 0.033481352 | L11: =K11/J11 -> 0.085083865 | N11: 0.3331 | O11: 0.42 | P11: 0.4038 | R11: 0.3596 | S11: 0.38 | T11: 0.3551 | V11: 0.3604 | W11: 0.42 | X11: 0.4286 | Z11: 0.328 | AA11: 0.34 | AB11: 0.3469 | AD11: 0.3657 | AE11: 0.42 | AF11: 0.4179 | AH11: 0.3349 | AI11: 0.35 | AJ11: 0.3608 | AL11: 0.3643 | AM11: 0.38 | AN11: 0.3979 | AP11: 0.3214 | AQ11: 0.35 | AR11: 0.3571 | AT11: 0.3822 | AU11: 0.45 | AV11: 0.4306 | AX11: 0.3609 | AY11: 0.48 | AZ11: 0.4364
B12: CatBoost | C12: =D10/D12-1 -> -0.039396869 | D12: =(N12+R12+V12+Z12+AD12+AH12+AL12+AP12+AT12+AX12)/10 -> 0.53786 | E12: =SQRT(((N12-D12)^2+(R12-D12)^2+(V12-D12)^2+(Z12-D12)^2+(AD12-D12)^2+(AH12-D12)^2+(AL12-D12)^2+(AP12-D12)^2+(AT12-D12)^2+(AX12-D12)^2)/10) -> 0.031181026 | F12: =E12/D12 -> 0.057972384 | G12: =(O12+S12+W12+AA12+AE12+AI12+AM12+AQ12+AU12+AY12)/10 -> 0.544 | H12: =SQRT(((O12-G12)^2+(S12-G12)^2+(W12-G12)^2+(AA12-G12)^2+(AE12-G12)^2+(AI12-G12)^2+(AM12-G12)^2+(AQ12-G12)^2+(AU12-G12)^2+(AY12-G12)^2)/10) -> 0.038781439 | I12: =H12/G12 -> 0.07128941 | J12: =(P12+T12+X12+AB12+AF12+AJ12+AN12+AR12+AV12+AZ12)/10 -> 0.49042 | K12: =SQRT(((P12-J12)^2+(T12-J12)^2+(X12-J12)^2+(AB12-J12)^2+(AF12-J12)^2+(AJ12-J12)^2+(AN12-J12)^2+(AR12-J12)^2+(AV12-J12)^2+(AZ12-J12)^2)/10) -> 0.027043254 | L12: =K12/J12 -> 0.055143049 | N12: 0.5417 | O12: 0.57 | P12: 0.4935 | R12: 0.5453 | S12: 0.55 | T12: 0.5 | V12: 0.5502 | W12: 0.54 | X12: 0.5118 | Z12: 0.5571 | AA12: 0.57 | AB12: 0.5067 | AD12: 0.5562 | AE12: 0.54 | AF12: 0.4779 | AH12: 0.5628 | AI12: 0.57 | AJ12: 0.4957 | AL12: 0.4477 | AM12: 0.44 | AN12: 0.419 | AP12: 0.538 | AQ12: 0.56 | AR12: 0.5114 | AT12: 0.544 | AU12: 0.58 | AV12: 0.5133 | AX12: 0.5356 | AY12: 0.52 | AZ12: 0.4749
B13: SCARF | C13: =D10/D13-1 -> 1.5062818 | D13: =(N13+R13+V13+Z13+AD13+AH13+AL13+AP13+AT13+AX13)/10 -> 0.20615 | E13: =SQRT(((N13-D13)^2+(R13-D13)^2+(V13-D13)^2+(Z13-D13)^2+(AD13-D13)^2+(AH13-D13)^2+(AL13-D13)^2+(AP13-D13)^2+(AT13-D13)^2+(AX13-D13)^2)/10) -> 0.010437936 | F13: =E13/D13 -> 0.050632722 | G13: =(O13+S13+W13+AA13+AE13+AI13+AM13+AQ13+AU13+AY13)/10 -> 0.486 | H13: =SQRT(((O13-G13)^2+(S13-G13)^2+(W13-G13)^2+(AA13-G13)^2+(AE13-G13)^2+(AI13-G13)^2+(AM13-G13)^2+(AQ13-G13)^2+(AU13-G13)^2+(AY13-G13)^2)/10) -> 0.029732137 | I13: =H13/G13 -> 0.061177238 | J13: =(P13+T13+X13+AB13+AF13+AJ13+AN13+AR13+AV13+AZ13)/10 -> 0.29174 | K13: =SQRT(((P13-J13)^2+(T13-J13)^2+(X13-J13)^2+(AB13-J13)^2+(AF13-J13)^2+(AJ13-J13)^2+(AN13-J13)^2+(AR13-J13)^2+(AV13-J13)^2+(AZ13-J13)^2)/10) -> 0.013107494 | L13: =K13/J13 -> 0.044928683 | N13: 0.1928 | O13: 0.45 | P13: 0.2804 | R13: 0.2141 | S13: 0.5 | T13: 0.2924 | V13: 0.2175 | W13: 0.51 | X13: 0.3091 | Z13: 0.1873 | AA13: 0.46 | AB13: 0.273 | AD13: 0.1924 | AE13: 0.48 | AF13: 0.2909 | AH13: 0.2112 | AI13: 0.47 | AJ13: 0.2857 | AL13: 0.2134 | AM13: 0.54 | AN13: 0.3176 | AP13: 0.2071 | AQ13: 0.51 | AR13: 0.2991 | AT13: 0.2146 | AU13: 0.5 | AV13: 0.2907 | AX13: 0.2111 | AY13: 0.44 | AZ13: 0.2785
C15: effect, % | D15: AUPRC | G15: Recall | J15: F1 | N15: AUPRC | O15: For reference | R15: AUPRC | S15: For reference | V15: AUPRC | W15: For reference | Z15: AUPRC | AA15: For reference | AD15: AUPRC | AE15: For reference | AH15: AUPRC | AI15: For reference | AL15: AUPRC | AM15: For reference | AP15: AUPRC | AQ15: For reference | AT15: AUPRC | AU15: For reference | AX15: AUPRC | AY15: For reference
D16: mean | E16: σ | F16: CV | G16: mean | H16: σ | I16: CV | J16: mean | K16: σ | L16: CV | O16: Recall | P16: F1 | S16: Recall | T16: F1 | W16: Recall | X16: F1 | AA16: Recall | AB16: F1 | AE16: Recall | AF16: F1 | AI16: Recall | AJ16: F1 | AM16: Recall | AN16: F1 | AQ16: Recall | AR16: F1 | AU16: Recall | AV16: F1 | AY16: Recall | AZ16: F1
B17: LR | C17: =D18/D17-1 -> 0.40883352 | D17: =(N17+R17+V17+Z17+AD17+AH17+AL17+AP17+AT17+AX17)/10 -> 0.36203 | E17: =SQRT(((N17-D17)^2+(R17-D17)^2+(V17-D17)^2+(Z17-D17)^2+(AD17-D17)^2+(AH17-D17)^2+(AL17-D17)^2+(AP17-D17)^2+(AT17-D17)^2+(AX17-D17)^2)/10) -> 0.012039273 | F17: =E17/D17 -> 0.033254905 | G17: =(O17+S17+W17+AA17+AE17+AI17+AM17+AQ17+AU17+AY17)/10 -> 0.524 | H17: =SQRT(((O17-G17)^2+(S17-G17)^2+(W17-G17)^2+(AA17-G17)^2+(AE17-G17)^2+(AI17-G17)^2+(AM17-G17)^2+(AQ17-G17)^2+(AU17-G17)^2+(AY17-G17)^2)/10) -> 0.028354894 | I17: =H17/G17 -> 0.054112393 | J17: =(P17+T17+X17+AB17+AF17+AJ17+AN17+AR17+AV17+AZ17)/10 -> 0.42508 | K17: =SQRT(((P17-J17)^2+(T17-J17)^2+(X17-J17)^2+(AB17-J17)^2+(AF17-J17)^2+(AJ17-J17)^2+(AN17-J17)^2+(AR17-J17)^2+(AV17-J17)^2+(AZ17-J17)^2)/10) -> 0.014331629 | L17: =K17/J17 -> 0.033715134 | N17: 0.3493 | O17: 0.49 | P17: 0.405 | R17: 0.3597 | S17: 0.53 | T17: 0.4309 | V17: 0.3597 | W17: 0.53 | X17: 0.4309 | Z17: 0.3493 | AA17: 0.49 | AB17: 0.405 | AD17: 0.3597 | AE17: 0.53 | AF17: 0.4309 | AH17: 0.3943 | AI17: 0.49 | AJ17: 0.405 | AL17: 0.3597 | AM17: 0.53 | AN17: 0.4309 | AP17: 0.3692 | AQ17: 0.59 | AR17: 0.4504 | AT17: 0.3597 | AU17: 0.53 | AV17: 0.4309 | AX17: 0.3597 | AY17: 0.53 | AZ17: 0.4309
B18: CLT-TAB without CATA | D18: =(N18+R18+V18+Z18+AD18+AH18+AL18+AP18+AT18+AX18)/10 -> 0.51004 | E18: =SQRT(((N18-D18)^2+(R18-D18)^2+(V18-D18)^2+(Z18-D18)^2+(AD18-D18)^2+(AH18-D18)^2+(AL18-D18)^2+(AP18-D18)^2+(AT18-D18)^2+(AX18-D18)^2)/10) -> 0.012535326 | F18: =E18/D18 -> 0.024577143 | G18: =(O18+S18+W18+AA18+AE18+AI18+AM18+AQ18+AU18+AY18)/10 -> 0.601 | H18: =SQRT(((O18-G18)^2+(S18-G18)^2+(W18-G18)^2+(AA18-G18)^2+(AE18-G18)^2+(AI18-G18)^2+(AM18-G18)^2+(AQ18-G18)^2+(AU18-G18)^2+(AY18-G18)^2)/10) -> 0.026248809 | I18: =H18/G18 -> 0.043675224 | J18: =(P18+T18+X18+AB18+AF18+AJ18+AN18+AR18+AV18+AZ18)/10 -> 0.48235 | K18: =SQRT(((P18-J18)^2+(T18-J18)^2+(X18-J18)^2+(AB18-J18)^2+(AF18-J18)^2+(AJ18-J18)^2+(AN18-J18)^2+(AR18-J18)^2+(AV18-J18)^2+(AZ18-J18)^2)/10) -> 0.01792296 | L18: =K18/J18 -> 0.037157583 | N18: 0.5052 | O18: 0.61 | P18: 0.4919 | R18: 0.4847 | S18: 0.61 | T18: 0.4656 | V18: 0.5032 | W18: 0.62 | X18: 0.496 | Z18: 0.5192 | AA18: 0.64 | AB18: 0.4981 | AD18: 0.5139 | AE18: 0.6 | AF18: 0.4839 | AH18: 0.5375 | AI18: 0.61 | AJ18: 0.5083 | AL18: 0.5104 | AM18: 0.57 | AN18: 0.4634 | AP18: 0.5096 | AQ18: 0.54 | AR18: 0.4481 | AT18: 0.5081 | AU18: 0.6 | AV18: 0.4743 | AX18: 0.5086 | AY18: 0.61 | AZ18: 0.4939
B19: FT-transformer | C19: =D18/D19-1 -> 0.45289845 | D19: =(N19+R19+V19+Z19+AD19+AH19+AL19+AP19+AT19+AX19)/10 -> 0.35105 | E19: =SQRT(((N19-D19)^2+(R19-D19)^2+(V19-D19)^2+(Z19-D19)^2+(AD19-D19)^2+(AH19-D19)^2+(AL19-D19)^2+(AP19-D19)^2+(AT19-D19)^2+(AX19-D19)^2)/10) -> 0.01900396 | F19: =E19/D19 -> 0.054134625 | G19: =(O19+S19+W19+AA19+AE19+AI19+AM19+AQ19+AU19+AY19)/10 -> 0.399 | H19: =SQRT(((O19-G19)^2+(S19-G19)^2+(W19-G19)^2+(AA19-G19)^2+(AE19-G19)^2+(AI19-G19)^2+(AM19-G19)^2+(AQ19-G19)^2+(AU19-G19)^2+(AY19-G19)^2)/10) -> 0.04414748 | I19: =H19/G19 -> 0.11064531 | J19: =(P19+T19+X19+AB19+AF19+AJ19+AN19+AR19+AV19+AZ19)/10 -> 0.39351 | K19: =SQRT(((P19-J19)^2+(T19-J19)^2+(X19-J19)^2+(AB19-J19)^2+(AF19-J19)^2+(AJ19-J19)^2+(AN19-J19)^2+(AR19-J19)^2+(AV19-J19)^2+(AZ19-J19)^2)/10) -> 0.033481352 | L19: =K19/J19 -> 0.085083865 | N19: 0.3331 | O19: 0.42 | P19: 0.4038 | R19: 0.3596 | S19: 0.38 | T19: 0.3551 | V19: 0.3604 | W19: 0.42 | X19: 0.4286 | Z19: 0.328 | AA19: 0.34 | AB19: 0.3469 | AD19: 0.3657 | AE19: 0.42 | AF19: 0.4179 | AH19: 0.3349 | AI19: 0.35 | AJ19: 0.3608 | AL19: 0.3643 | AM19: 0.38 | AN19: 0.3979 | AP19: 0.3214 | AQ19: 0.35 | AR19: 0.3571 | AT19: 0.3822 | AU19: 0.45 | AV19: 0.4306 | AX19: 0.3609 | AY19: 0.48 | AZ19: 0.4364
B20: CatBoost | C20: =D18/D20-1 -> -0.051723497 | D20: =(N20+R20+V20+Z20+AD20+AH20+AL20+AP20+AT20+AX20)/10 -> 0.53786 | E20: =SQRT(((N20-D20)^2+(R20-D20)^2+(V20-D20)^2+(Z20-D20)^2+(AD20-D20)^2+(AH20-D20)^2+(AL20-D20)^2+(AP20-D20)^2+(AT20-D20)^2+(AX20-D20)^2)/10) -> 0.031181026 | F20: =E20/D20 -> 0.057972384 | G20: =(O20+S20+W20+AA20+AE20+AI20+AM20+AQ20+AU20+AY20)/10 -> 0.544 | H20: =SQRT(((O20-G20)^2+(S20-G20)^2+(W20-G20)^2+(AA20-G20)^2+(AE20-G20)^2+(AI20-G20)^2+(AM20-G20)^2+(AQ20-G20)^2+(AU20-G20)^2+(AY20-G20)^2)/10) -> 0.038781439 | I20: =H20/G20 -> 0.07128941 | J20: =(P20+T20+X20+AB20+AF20+AJ20+AN20+AR20+AV20+AZ20)/10 -> 0.49042 | K20: =SQRT(((P20-J20)^2+(T20-J20)^2+(X20-J20)^2+(AB20-J20)^2+(AF20-J20)^2+(AJ20-J20)^2+(AN20-J20)^2+(AR20-J20)^2+(AV20-J20)^2+(AZ20-J20)^2)/10) -> 0.027043254 | L20: =K20/J20 -> 0.055143049 | N20: 0.5417 | O20: 0.57 | P20: 0.4935 | R20: 0.5453 | S20: 0.55 | T20: 0.5 | V20: 0.5502 | W20: 0.54 | X20: 0.5118 | Z20: 0.5571 | AA20: 0.57 | AB20: 0.5067 | AD20: 0.5562 | AE20: 0.54 | AF20: 0.4779 | AH20: 0.5628 | AI20: 0.57 | AJ20: 0.4957 | AL20: 0.4477 | AM20: 0.44 | AN20: 0.419 | AP20: 0.538 | AQ20: 0.56 | AR20: 0.5114 | AT20: 0.544 | AU20: 0.58 | AV20: 0.5133 | AX20: 0.5356 | AY20: 0.52 | AZ20: 0.4749
B21: SCARF | C21: =D18/D21-1 -> 1.4741208 | D21: =(N21+R21+V21+Z21+AD21+AH21+AL21+AP21+AT21+AX21)/10 -> 0.20615 | E21: =SQRT(((N21-D21)^2+(R21-D21)^2+(V21-D21)^2+(Z21-D21)^2+(AD21-D21)^2+(AH21-D21)^2+(AL21-D21)^2+(AP21-D21)^2+(AT21-D21)^2+(AX21-D21)^2)/10) -> 0.010437936 | F21: =E21/D21 -> 0.050632722 | G21: =(O21+S21+W21+AA21+AE21+AI21+AM21+AQ21+AU21+AY21)/10 -> 0.486 | H21: =SQRT(((O21-G21)^2+(S21-G21)^2+(W21-G21)^2+(AA21-G21)^2+(AE21-G21)^2+(AI21-G21)^2+(AM21-G21)^2+(AQ21-G21)^2+(AU21-G21)^2+(AY21-G21)^2)/10) -> 0.029732137 | I21: =H21/G21 -> 0.061177238 | J21: =(P21+T21+X21+AB21+AF21+AJ21+AN21+AR21+AV21+AZ21)/10 -> 0.29174 | K21: =SQRT(((P21-J21)^2+(T21-J21)^2+(X21-J21)^2+(AB21-J21)^2+(AF21-J21)^2+(AJ21-J21)^2+(AN21-J21)^2+(AR21-J21)^2+(AV21-J21)^2+(AZ21-J21)^2)/10) -> 0.013107494 | L21: =K21/J21 -> 0.044928683 | N21: 0.1928 | O21: 0.45 | P21: 0.2804 | R21: 0.2141 | S21: 0.5 | T21: 0.2924 | V21: 0.2175 | W21: 0.51 | X21: 0.3091 | Z21: 0.1873 | AA21: 0.46 | AB21: 0.273 | AD21: 0.1924 | AE21: 0.48 | AF21: 0.2909 | AH21: 0.2112 | AI21: 0.47 | AJ21: 0.2857 | AL21: 0.2134 | AM21: 0.54 | AN21: 0.3176 | AP21: 0.2071 | AQ21: 0.51 | AR21: 0.2991 | AT21: 0.2146 | AU21: 0.5 | AV21: 0.2907 | AX21: 0.2111 | AY21: 0.44 | AZ21: 0.2785
